Workbook

Sheet Audit Report
A1: Bazaarvoice Product Catalog Audit Report
A2: All regional instances | All-time catalog snapshot | Run date in source: 2026-08-12 UTC
A3: Documentation: https://pgone.sharepoint.com/:p:/s/GlobalProductServices/IQAhg8ackh-HQ77DjbpXzz43ASkqCZKDUUbpZ9z4fYTL8-M?e=ELbrVw
A5: TOP PRIORITY ALERT
A6: Most Critical Issue | B6: Reviews are currently hidden because they are associated with inactive products.
A7: Total Impact | B7: =SUMIF('pampers-en_us'!D8:D129,"Inactive",'pampers-en_us'!M8:M129)+SUMIF('pampers-es'!D8:D38,"Inactive",'pampers-es'!M8:M38)+SUMIF('pampers-en_gb'!D8:D45,"Inactive",'pampers-en_gb'!M8:M45)+SUMIF('pampers-de_de'!D8:D43,"Inactive",'pampers-de_de'!M8:M43)+SUMIF('pampers-fr_fr'!D8:D86,"Inactive",'pampers-fr_fr'!M8:M86)+SUMIF(pgdodotspain!D8:D36,"Inactive",pgdodotspain!M8:M36)+SUMIF('pampers-ja_jp'!D8:D40,"Inactive",'pampers-ja_jp'!M8:M40) -> 62301
A8: Number of Affected Products | B8: =COUNTIFS('pampers-en_us'!D8:D129,"Inactive",'pampers-en_us'!M8:M129,">0")+COUNTIFS('pampers-es'!D8:D38,"Inactive",'pampers-es'!M8:M38,">0")+COUNTIFS('pampers-en_gb'!D8:D45,"Inactive",'pampers-en_gb'!M8:M45,">0")+COUNTIFS('pampers-de_de'!D8:D43,"Inactive",'pampers-de_de'!M8:M43,">0")+COUNTIFS('pampers-fr_fr'!D8:D86,"Inactive",'pampers-fr_fr'!M8:M86,">0")+COUNTIFS(pgdodotspain!D8:D36,"Inactive",pgdodotspain!M8:M36,">0")+COUNTIFS('pampers-ja_jp'!D8:D40,"Inactive",'pampers-ja_jp'!M8:M40,">0") -> 229
A9: Number of Reviews Hidden/Tagged to Inactive Products | B9: =SUMIF('pampers-en_us'!D8:D129,"Inactive",'pampers-en_us'!M8:M129)+SUMIF('pampers-es'!D8:D38,"Inactive",'pampers-es'!M8:M38)+SUMIF('pampers-en_gb'!D8:D45,"Inactive",'pampers-en_gb'!M8:M45)+SUMIF('pampers-de_de'!D8:D43,"Inactive",'pampers-de_de'!M8:M43)+SUMIF('pampers-fr_fr'!D8:D86,"Inactive",'pampers-fr_fr'!M8:M86)+SUMIF(pgdodotspain!D8:D36,"Inactive",pgdodotspain!M8:M36)+SUMIF('pampers-ja_jp'!D8:D40,"Inactive",'pampers-ja_jp'!M8:M40) -> 62301
A10: % Reviews Hidden/Tagged to Inactive Products | B10: =IFERROR(B9/(SUM('pampers-en_us'!M8:M129)+SUM('pampers-es'!M8:M38)+SUM('pampers-en_gb'!M8:M45)+SUM('pampers-de_de'!M8:M43)+SUM('pampers-fr_fr'!M8:M86)+SUM(pgdodotspain!M8:M36)+SUM('pampers-ja_jp'!M8:M40)),0) -> 0.25959399
A11: Required Action Summary | B11: Prioritize reviewed inactive products.
A12: Recommended Fix | B12: Map IDs to live PDPs; then activate.
A13: Suggestion Impact Level | B13: CRUCIAL
A15: SECTION 1: CRITICAL FIELD DEFINITIONS FOR AUDIT
A16: Critical Field | B16: Column Reference | C16: Why Critical | D16: Business Impact if Missing | E16: Recommended Action | F16: Documentation Reference
A17: Product ID | B17: C | C17: Primary catalog matching key. | D17: Matching and governance fail. | E17: Use one stable canonical ID. | F17: https://pgone.sharepoint.com/:p:/s/GlobalProductServices/IQAhg8ackh-HQ77DjbpXzz43ASkqCZKDUUbpZ9z4fYTL8-M?e=ELbrVw
A18: UPC/EAN | B18: I / J | C18: Regional syndication identifier. | D18: Syndication can be blocked. | E18: Populate UPC in NA; EAN elsewhere. | F18: https://pgone.sharepoint.com/:p:/s/GlobalProductServices/IQAhg8ackh-HQ77DjbpXzz43ASkqCZKDUUbpZ9z4fYTL8-M?e=ELbrVw
A19: Product Name | B19: E | C19: Customer-facing product identity. | D19: PDP clarity is reduced. | E19: Supply the approved local name. | F19: https://pgone.sharepoint.com/:p:/s/GlobalProductServices/IQAhg8ackh-HQ77DjbpXzz43ASkqCZKDUUbpZ9z4fYTL8-M?e=ELbrVw
A20: Product Description | B20: F | C20: Core product content. | D20: PDP completeness is reduced. | E20: Supply approved local copy. | F20: https://pgone.sharepoint.com/:p:/s/GlobalProductServices/IQAhg8ackh-HQ77DjbpXzz43ASkqCZKDUUbpZ9z4fYTL8-M?e=ELbrVw
A21: Product Page URL / PDP URL | B21: G | C21: Links reviews to the live PDP. | D21: Reviews may not render on PDP. | E21: Use the canonical live PDP URL. | F21: https://pgone.sharepoint.com/:p:/s/GlobalProductServices/IQAhg8ackh-HQ77DjbpXzz43ASkqCZKDUUbpZ9z4fYTL8-M?e=ELbrVw
A22: Image URL | B22: H | C22: Provides product imagery. | D22: Catalog presentation is weakened. | E22: Use a reachable canonical image. | F22: https://pgone.sharepoint.com/:p:/s/GlobalProductServices/IQAhg8ackh-HQ77DjbpXzz43ASkqCZKDUUbpZ9z4fYTL8-M?e=ELbrVw
A23: Brand | B23: B | C23: Supports attribution and reporting. | D23: Brand reporting can fragment. | E23: Use approved brand taxonomy. | F23: https://pgone.sharepoint.com/:p:/s/GlobalProductServices/IQAhg8ackh-HQ77DjbpXzz43ASkqCZKDUUbpZ9z4fYTL8-M?e=ELbrVw
A24: Product Status | B24: D | C24: Controls product visibility. | D24: Inactive items hide reviews. | E24: Validate Active/Inactive status. | F24: https://pgone.sharepoint.com/:p:/s/GlobalProductServices/IQAhg8ackh-HQ77DjbpXzz43ASkqCZKDUUbpZ9z4fYTL8-M?e=ELbrVw
A26: SECTION 2: VOLUME-BASED SUMMARY BY INSTANCE
A27: Instance / Region | B27: Total Products | C27: Active Products | D27: Inactive Products | E27: % Inactive | F27: Total Reviews | G27: Reviews Hidden/Tagged to Inactive Product | H27: % Reviews Hidden/Tagged to Inactive Product | I27: Missing UPC/EAN | J27: Missing Description | K27: Missing Image URL | L27: Business Impact | M27: Recommended Action | N27: Suggestion Impact
A28: United States (EN) | B28: =COUNTIF('pampers-en_us'!D8:D129,"<>") -> 122 | C28: =COUNTIF('pampers-en_us'!D8:D129,"Active") -> 20 | D28: =COUNTIF('pampers-en_us'!D8:D129,"Inactive") -> 102 | E28: =IFERROR(D28/B28,0) -> 0.83606557 | F28: =SUM('pampers-en_us'!M8:M129) -> 154472 | G28: =SUMIF('pampers-en_us'!D8:D129,"Inactive",'pampers-en_us'!M8:M129) -> 34000 | H28: =IFERROR(G28/F28,0) -> 0.22010461 | I28: {=SUMPRODUCT(--('pampers-en_us'!D8:D129<>""),--(LEN(TRIM('pampers-en_us'!I8:I129))=0))} -> 36 | J28: {=SUMPRODUCT(--('pampers-en_us'!D8:D129<>""),--(LEN(TRIM('pampers-en_us'!F8:F129))=0))} -> 38 | K28: {=SUMPRODUCT(--('pampers-en_us'!D8:D129<>""),--(LEN(TRIM('pampers-en_us'!H8:H129))=0))} -> 36 | L28: =IF(G28>0,"Hidden reviews reduce social proof.","No hidden-review impact found.") -> Hidden reviews reduce social proof. | M28: =IF(G28>0,"Map reviewed IDs; then activate.","Maintain status governance.") -> Map reviewed IDs; then activate. | N28: =IF(G28>0,"CRUCIAL",IF(I28>0,"HIGH",IF(J28+K28>0,"MEDIUM","LOW"))) -> CRUCIAL
A29: United States (ES) | B29: =COUNTIF('pampers-es'!D8:D38,"<>") -> 31 | C29: =COUNTIF('pampers-es'!D8:D38,"Active") -> 0 | D29: =COUNTIF('pampers-es'!D8:D38,"Inactive") -> 31 | E29: =IFERROR(D29/B29,0) -> 1 | F29: =SUM('pampers-es'!M8:M38) -> 1884 | G29: =SUMIF('pampers-es'!D8:D38,"Inactive",'pampers-es'!M8:M38) -> 1884 | H29: =IFERROR(G29/F29,0) -> 1 | I29: {=SUMPRODUCT(--('pampers-es'!D8:D38<>""),--(LEN(TRIM('pampers-es'!I8:I38))=0))} -> 3 | J29: {=SUMPRODUCT(--('pampers-es'!D8:D38<>""),--(LEN(TRIM('pampers-es'!F8:F38))=0))} -> 3 | K29: {=SUMPRODUCT(--('pampers-es'!D8:D38<>""),--(LEN(TRIM('pampers-es'!H8:H38))=0))} -> 2 | L29: =IF(G29>0,"Hidden reviews reduce social proof.","No hidden-review impact found.") -> Hidden reviews reduce social proof. | M29: =IF(G29>0,"Map reviewed IDs; then activate.","Maintain status governance.") -> Map reviewed IDs; then activate. | N29: =IF(G29>0,"CRUCIAL",IF(I29>0,"HIGH",IF(J29+K29>0,"MEDIUM","LOW"))) -> CRUCIAL
A30: United Kingdom | B30: =COUNTIF('pampers-en_gb'!D8:D45,"<>") -> 38 | C30: =COUNTIF('pampers-en_gb'!D8:D45,"Active") -> 15 | D30: =COUNTIF('pampers-en_gb'!D8:D45,"Inactive") -> 23 | E30: =IFERROR(D30/B30,0) -> 0.60526316 | F30: =SUM('pampers-en_gb'!M8:M45) -> 13143 | G30: =SUMIF('pampers-en_gb'!D8:D45,"Inactive",'pampers-en_gb'!M8:M45) -> 1580 | H30: =IFERROR(G30/F30,0) -> 0.12021608 | I30: {=SUMPRODUCT(--('pampers-en_gb'!D8:D45<>""),--(LEN(TRIM('pampers-en_gb'!J8:J45))=0))} -> 7 | J30: {=SUMPRODUCT(--('pampers-en_gb'!D8:D45<>""),--(LEN(TRIM('pampers-en_gb'!F8:F45))=0))} -> 5 | K30: {=SUMPRODUCT(--('pampers-en_gb'!D8:D45<>""),--(LEN(TRIM('pampers-en_gb'!H8:H45))=0))} -> 7 | L30: =IF(G30>0,"Hidden reviews reduce social proof.","No hidden-review impact found.") -> Hidden reviews reduce social proof. | M30: =IF(G30>0,"Map reviewed IDs; then activate.","Maintain status governance.") -> Map reviewed IDs; then activate. | N30: =IF(G30>0,"CRUCIAL",IF(I30>0,"HIGH",IF(J30+K30>0,"MEDIUM","LOW"))) -> CRUCIAL
A31: Germany | B31: =COUNTIF('pampers-de_de'!D8:D43,"<>") -> 36 | C31: =COUNTIF('pampers-de_de'!D8:D43,"Active") -> 11 | D31: =COUNTIF('pampers-de_de'!D8:D43,"Inactive") -> 25 | E31: =IFERROR(D31/B31,0) -> 0.69444444 | F31: =SUM('pampers-de_de'!M8:M43) -> 30459 | G31: =SUMIF('pampers-de_de'!D8:D43,"Inactive",'pampers-de_de'!M8:M43) -> 9214 | H31: =IFERROR(G31/F31,0) -> 0.30250501 | I31: {=SUMPRODUCT(--('pampers-de_de'!D8:D43<>""),--(LEN(TRIM('pampers-de_de'!J8:J43))=0))} -> 9 | J31: {=SUMPRODUCT(--('pampers-de_de'!D8:D43<>""),--(LEN(TRIM('pampers-de_de'!F8:F43))=0))} -> 6 | K31: {=SUMPRODUCT(--('pampers-de_de'!D8:D43<>""),--(LEN(TRIM('pampers-de_de'!H8:H43))=0))} -> 11 | L31: =IF(G31>0,"Hidden reviews reduce social proof.","No hidden-review impact found.") -> Hidden reviews reduce social proof. | M31: =IF(G31>0,"Map reviewed IDs; then activate.","Maintain status governance.") -> Map reviewed IDs; then activate. | N31: =IF(G31>0,"CRUCIAL",IF(I31>0,"HIGH",IF(J31+K31>0,"MEDIUM","LOW"))) -> CRUCIAL
A32: France | B32: =COUNTIF('pampers-fr_fr'!D8:D86,"<>") -> 79 | C32: =COUNTIF('pampers-fr_fr'!D8:D86,"Active") -> 46 | D32: =COUNTIF('pampers-fr_fr'!D8:D86,"Inactive") -> 33 | E32: =IFERROR(D32/B32,0) -> 0.41772152 | F32: =SUM('pampers-fr_fr'!M8:M86) -> 30952 | G32: =SUMIF('pampers-fr_fr'!D8:D86,"Inactive",'pampers-fr_fr'!M8:M86) -> 6541 | H32: =IFERROR(G32/F32,0) -> 0.21132722 | I32: {=SUMPRODUCT(--('pampers-fr_fr'!D8:D86<>""),--(LEN(TRIM('pampers-fr_fr'!J8:J86))=0))} -> 10 | J32: {=SUMPRODUCT(--('pampers-fr_fr'!D8:D86<>""),--(LEN(TRIM('pampers-fr_fr'!F8:F86))=0))} -> 4 | K32: {=SUMPRODUCT(--('pampers-fr_fr'!D8:D86<>""),--(LEN(TRIM('pampers-fr_fr'!H8:H86))=0))} -> 10 | L32: =IF(G32>0,"Hidden reviews reduce social proof.","No hidden-review impact found.") -> Hidden reviews reduce social proof. | M32: =IF(G32>0,"Map reviewed IDs; then activate.","Maintain status governance.") -> Map reviewed IDs; then activate. | N32: =IF(G32>0,"CRUCIAL",IF(I32>0,"HIGH",IF(J32+K32>0,"MEDIUM","LOW"))) -> CRUCIAL
A33: Spain | B33: =COUNTIF(pgdodotspain!D8:D36,"<>") -> 29 | C33: =COUNTIF(pgdodotspain!D8:D36,"Active") -> 1 | D33: =COUNTIF(pgdodotspain!D8:D36,"Inactive") -> 28 | E33: =IFERROR(D33/B33,0) -> 0.96551724 | F33: =SUM(pgdodotspain!M8:M36) -> 5979 | G33: =SUMIF(pgdodotspain!D8:D36,"Inactive",pgdodotspain!M8:M36) -> 5977 | H33: =IFERROR(G33/F33,0) -> 0.9996655 | I33: {=SUMPRODUCT(--(pgdodotspain!D8:D36<>""),--(LEN(TRIM(pgdodotspain!J8:J36))=0))} -> 10 | J33: {=SUMPRODUCT(--(pgdodotspain!D8:D36<>""),--(LEN(TRIM(pgdodotspain!F8:F36))=0))} -> 9 | K33: {=SUMPRODUCT(--(pgdodotspain!D8:D36<>""),--(LEN(TRIM(pgdodotspain!H8:H36))=0))} -> 9 | L33: =IF(G33>0,"Hidden reviews reduce social proof.","No hidden-review impact found.") -> Hidden reviews reduce social proof. | M33: =IF(G33>0,"Map reviewed IDs; then activate.","Maintain status governance.") -> Map reviewed IDs; then activate. | N33: =IF(G33>0,"CRUCIAL",IF(I33>0,"HIGH",IF(J33+K33>0,"MEDIUM","LOW"))) -> CRUCIAL
A34: Japan | B34: =COUNTIF('pampers-ja_jp'!D8:D40,"<>") -> 33 | C34: =COUNTIF('pampers-ja_jp'!D8:D40,"Active") -> 0 | D34: =COUNTIF('pampers-ja_jp'!D8:D40,"Inactive") -> 33 | E34: =IFERROR(D34/B34,0) -> 1 | F34: =SUM('pampers-ja_jp'!M8:M40) -> 3105 | G34: =SUMIF('pampers-ja_jp'!D8:D40,"Inactive",'pampers-ja_jp'!M8:M40) -> 3105 | H34: =IFERROR(G34/F34,0) -> 1 | I34: {=SUMPRODUCT(--('pampers-ja_jp'!D8:D40<>""),--(LEN(TRIM('pampers-ja_jp'!J8:J40))=0))} -> 10 | J34: {=SUMPRODUCT(--('pampers-ja_jp'!D8:D40<>""),--(LEN(TRIM('pampers-ja_jp'!F8:F40))=0))} -> 2 | K34: {=SUMPRODUCT(--('pampers-ja_jp'!D8:D40<>""),--(LEN(TRIM('pampers-ja_jp'!H8:H40))=0))} -> 3 | L34: =IF(G34>0,"Hidden reviews reduce social proof.","No hidden-review impact found.") -> Hidden reviews reduce social proof. | M34: =IF(G34>0,"Map reviewed IDs; then activate.","Maintain status governance.") -> Map reviewed IDs; then activate. | N34: =IF(G34>0,"CRUCIAL",IF(I34>0,"HIGH",IF(J34+K34>0,"MEDIUM","LOW"))) -> CRUCIAL
A35: TOTAL | B35: =SUM(B28:B34) -> 368 | C35: =SUM(C28:C34) -> 93 | D35: =SUM(D28:D34) -> 275 | E35: =IFERROR(D35/B35,0) -> 0.74728261 | F35: =SUM(F28:F34) -> 239994 | G35: =SUM(G28:G34) -> 62301 | H35: =IFERROR(G35/F35,0) -> 0.25959399 | I35: =SUM(I28:I34) -> 85 | J35: =SUM(J28:J34) -> 67 | K35: =SUM(K28:K34) -> 78 | L35: ="Hidden reviews: "&TEXT(G35,"#,##0") -> Hidden reviews: 62,301 | M35: ="Prioritize "&TEXT(G35,"#,##0")&" hidden reviews." -> Prioritize 62,301 hidden reviews. | N35: =IF(G35>0,"CRUCIAL","LOW") -> CRUCIAL
A37: Immediate attention: prioritize instances with the largest hidden-review volume; North American instances are listed first. No Canada instance is present in this workbook.
A39: SECTION 3: ISSUES WITH BUSINESS IMPACT, RECOMMENDATIONS & HOW TO FIX
A40: Instance / Region | B40: # | C40: Issue Category | D40: Critical Field | E40: Volume Impacted | F40: Business Impact | G40: Recommended Action | H40: How to Fix | I40: Suggestion Impact
A41: United States (EN) | B41: 1 | C41: Inactive Products → Reviews Hidden/Tagged to Inactive Product | D41: Product Status | E41: 77 products / 34000 reviews | F41: Hidden reviews reduce social proof. | G41: Reactivate or migrate reviewed products. | H41: Map IDs to live PDPs; then activate. | I41: CRUCIAL
A42: United States (EN) | B42: 2 | C42: Product ID Issues | D42: Product ID | E42: Numeric 60; alphanumeric 62; blank 0 | F42: Mixed IDs hinder catalog matching. | G42: Adopt one canonical ID standard. | H42: Map legacy IDs; publish canonical IDs. | I42: HIGH
A43: United States (EN) | B43: 3 | C43: UPC Data Missing Issues | D43: UPC | E43: 36 products | F43: Missing codes can block syndication. | G43: Populate approved UPC values. | H43: Validate source codes; update column I. | I43: HIGH
A44: United States (EN) | B44: 4 | C44: Missing Crucial Fields | D44: Name/PDP/Description/Image/Brand | E44: 53 products | F44: Missing content weakens PDP quality. | G44: Complete required catalog fields. | H44: Backfill from approved product masters. | I44: MEDIUM
A45: United States (EN) | B45: 5 | C45: Brand Name Issues | D45: Brand | E45: 3 variations | F45: Brand variants fragment reporting. | G45: Use one approved brand label. | H45: Normalize case, spacing, and aliases. | I45: MEDIUM
A46: United States (ES) | B46: 1 | C46: Inactive Products → Reviews Hidden/Tagged to Inactive Product | D46: Product Status | E46: 31 products / 1884 reviews | F46: Hidden reviews reduce social proof. | G46: Reactivate or migrate reviewed products. | H46: Map IDs to live PDPs; then activate. | I46: CRUCIAL
A47: United States (ES) | B47: 2 | C47: Product ID Issues | D47: Product ID | E47: Numeric 27; alphanumeric 4; blank 0 | F47: Mixed IDs hinder catalog matching. | G47: Adopt one canonical ID standard. | H47: Map legacy IDs; publish canonical IDs. | I47: HIGH
A48: United States (ES) | B48: 3 | C48: UPC Data Missing Issues | D48: UPC | E48: 3 products | F48: Missing codes can block syndication. | G48: Populate approved UPC values. | H48: Validate source codes; update column I. | I48: HIGH
A49: United States (ES) | B49: 4 | C49: Missing Crucial Fields | D49: Name/PDP/Description/Image/Brand | E49: 3 products | F49: Missing content weakens PDP quality. | G49: Complete required catalog fields. | H49: Backfill from approved product masters. | I49: MEDIUM
A50: United Kingdom | B50: 1 | C50: Inactive Products → Reviews Hidden/Tagged to Inactive Product | D50: Product Status | E50: 17 products / 1580 reviews | F50: Hidden reviews reduce social proof. | G50: Reactivate or migrate reviewed products. | H50: Map IDs to live PDPs; then activate. | I50: CRUCIAL
A51: United Kingdom | B51: 2 | C51: Product ID Issues | D51: Product ID | E51: Numeric 1; alphanumeric 37; blank 0 | F51: Mixed IDs hinder catalog matching. | G51: Adopt one canonical ID standard. | H51: Map legacy IDs; publish canonical IDs. | I51: HIGH
A52: United Kingdom | B52: 3 | C52: EAN Data Missing Issues | D52: EAN | E52: 7 products | F52: Missing codes can block syndication. | G52: Populate approved EAN values. | H52: Validate source codes; update column J. | I52: HIGH
... A74: Japan | B74: 5 | C74: Brand Name Issues | D74: Brand | E74: 2 variations | F74: Brand variants fragment reporting. | G74: Use one approved brand label. | H74: Normalize case, spacing, and aliases. | I74: MEDIUM
A76: SECTION 4: INACTIVE PRODUCTS WITH REVIEWS – MIGRATION CANDIDATES
A77: Instance / Region | B77: Product ID | C77: Product Name | D77: Brand | E77: Product Status | F77: Total Reviews Hidden/Tagged to Inactive Product | G77: Reviews on Product | H77: Suggested Migration Target / Action | I77: Business Impact | J77: How to Fix | K77: Suggestion Impact
A78: United States (EN) | B78: ='pampers-en_us'!C77 -> Pampers_Cruisers | C78: ='pampers-en_us'!E77 -> Pampers® Cruisers™ | D78: ='pampers-en_us'!B77 -> Pampers | E78: ='pampers-en_us'!D77 -> Inactive | F78: ='pampers-en_us'!M77 -> 10022 | G78: ='pampers-en_us'!M77 -> 10022 | H78: Find active successor; otherwise activate. | I78: Reviews are currently hidden because they are associated with inactive products. | J78: Map IDs to a live PDP; migrate or activate. | K78: CRUCIAL
A79: United States (EN) | B79: ='pampers-en_us'!C64 -> Pampers_Diapers_Swaddlers_Sensitive | C79: ='pampers-en_us'!E64 -> Pampers® Swaddlers Sensitive™ | D79: ='pampers-en_us'!B64 -> Pampers | E79: ='pampers-en_us'!D64 -> Inactive | F79: ='pampers-en_us'!M64 -> 5152 | G79: ='pampers-en_us'!M64 -> 5152 | H79: Find active successor; otherwise activate. | I79: Reviews are currently hidden because they are associated with inactive products. | J79: Map IDs to a live PDP; migrate or activate. | K79: CRUCIAL
A80: Germany | B80: ='pampers-de_de'!C22 -> 711155922-DE | C80: ='pampers-de_de'!E22 -> Pampers® Premium Protection™ New Baby | D80: ='pampers-de_de'!B22 -> Pampers | E80: ='pampers-de_de'!D22 -> Inactive | F80: ='pampers-de_de'!M22 -> 2821 | G80: ='pampers-de_de'!M22 -> 2821 | H80: Find active successor; otherwise activate. | I80: Reviews are currently hidden because they are associated with inactive products. | J80: Map IDs to a live PDP; migrate or activate. | K80: CRUCIAL
A81: United States (EN) | B81: ='pampers-en_us'!C48 -> 761042423 | C81: ='pampers-en_us'!E48 -> Pampers Easy Ups Training Underwear for Girls | D81: ='pampers-en_us'!B48 -> Pampers | E81: ='pampers-en_us'!D48 -> Inactive | F81: ='pampers-en_us'!M48 -> 2770 | G81: ='pampers-en_us'!M48 -> 2770 | H81: Find active successor; otherwise activate. | I81: Reviews are currently hidden because they are associated with inactive products. | J81: Map IDs to a live PDP; migrate or activate. | K81: CRUCIAL
A82: United States (EN) | B82: ='pampers-en_us'!C83 -> SwaddlersUltra | C82: ='pampers-en_us'!E83 -> Pampers Swaddlers Ultra Day + Night | D82: ='pampers-en_us'!B83 -> Pampers | E82: ='pampers-en_us'!D83 -> Inactive | F82: ='pampers-en_us'!M83 -> 2711 | G82: ='pampers-en_us'!M83 -> 2711 | H82: Find active successor; otherwise activate. | I82: Reviews are currently hidden because they are associated with inactive products. | J82: Map IDs to a live PDP; migrate or activate. | K82: CRUCIAL
A83: United States (EN) | B83: ='pampers-en_us'!C44 -> 761057122 | C83: ='pampers-en_us'!E44 -> Pampers® Complete Clean™ Unscented | D83: ='pampers-en_us'!B44 -> Pampers | E83: ='pampers-en_us'!D44 -> Inactive | F83: ='pampers-en_us'!M44 -> 2677 | G83: ='pampers-en_us'!M44 -> 2677 | H83: Find active successor; otherwise activate. | I83: Reviews are currently hidden because they are associated with inactive products. | J83: Map IDs to a live PDP; migrate or activate. | K83: CRUCIAL
A84: Germany | B84: ='pampers-de_de'!C37 -> 711155943-DE | C84: ='pampers-de_de'!E37 -> Pampers Baby-Dry | D84: ='pampers-de_de'!B37 -> Pampers | E84: ='pampers-de_de'!D37 -> Inactive | F84: ='pampers-de_de'!M37 -> 2555 | G84: ='pampers-de_de'!M37 -> 2555 | H84: Migrate reviews to active Product ID PAMPERS_BABY_DRY. | I84: Reviews are currently hidden because they are associated with inactive products. | J84: Map IDs to a live PDP; migrate or activate. | K84: CRUCIAL
A85: United States (EN) | B85: ='pampers-en_us'!C92 -> 761042421 | C85: ='pampers-en_us'!E92 -> Pampers Baby Dry Extra Protection | D85: ='pampers-en_us'!B92 -> Pampers | E85: ='pampers-en_us'!D92 -> Inactive | F85: ='pampers-en_us'!M92 -> 2320 | G85: ='pampers-en_us'!M92 -> 2320 | H85: Find active successor; otherwise activate. | I85: Reviews are currently hidden because they are associated with inactive products. | J85: Map IDs to a live PDP; migrate or activate. | K85: CRUCIAL
A86: Spain | B86: =pgdodotspain!C12 -> 2120000 | C86: =pgdodotspain!E12 -> TOALLITAS Dodot® Sensitive | D86: =pgdodotspain!B12 -> Pampers | E86: =pgdodotspain!D12 -> Inactive | F86: =pgdodotspain!M12 -> 1926 | G86: =pgdodotspain!M12 -> 1926 | H86: Find active successor; otherwise activate. | I86: Reviews are currently hidden because they are associated with inactive products. | J86: Map IDs to a live PDP; migrate or activate. | K86: CRUCIAL
A87: France | B87: ='pampers-fr_fr'!C62 -> FR-14 | C87: ='pampers-fr_fr'!E62 -> Pampers® Baby-Dry Pants™ | D87: ='pampers-fr_fr'!B62 -> Pampers | E87: ='pampers-fr_fr'!D62 -> Inactive | F87: ='pampers-fr_fr'!M62 -> 1924 | G87: ='pampers-fr_fr'!M62 -> 1924 | H87: Migrate reviews to active Product ID Babydry-FR. | I87: Reviews are currently hidden because they are associated with inactive products. | J87: Map IDs to a live PDP; migrate or activate. | K87: CRUCIAL
A88: Spain | B88: =pgdodotspain!C15 -> 2160000 | C88: =pgdodotspain!E15 -> PAÑALES Dodot® Bebé-Seco | D88: =pgdodotspain!B15 -> Pampers | E88: =pgdodotspain!D15 -> Inactive | F88: =pgdodotspain!M15 -> 1296 | G88: =pgdodotspain!M15 -> 1296 | H88: Find active successor; otherwise activate. | I88: Reviews are currently hidden because they are associated with inactive products. | J88: Map IDs to a live PDP; migrate or activate. | K88: CRUCIAL
A89: Spain | B89: =pgdodotspain!C21 -> 2180000 | C89: =pgdodotspain!E21 -> PAÑALES Dodot® Sensitive | D89: =pgdodotspain!B21 -> Pampers | E89: =pgdodotspain!D21 -> Inactive | F89: =pgdodotspain!M21 -> 1229 | G89: =pgdodotspain!M21 -> 1229 | H89: Find active successor; otherwise activate. | I89: Reviews are currently hidden because they are associated with inactive products. | J89: Map IDs to a live PDP; migrate or activate. | K89: CRUCIAL
A90: France | B90: ='pampers-fr_fr'!C77 -> 75 | C90: ='pampers-fr_fr'!E77 -> Pampers Baby-Dry | D90: ='pampers-fr_fr'!B77 -> Pampers | E90: ='pampers-fr_fr'!D77 -> Inactive | F90: ='pampers-fr_fr'!M77 -> 1101 | G90: ='pampers-fr_fr'!M77 -> 1101 | H90: Find active successor; otherwise activate. | I90: Reviews are currently hidden because they are associated with inactive products. | J90: Map IDs to a live PDP; migrate or activate. | K90: CRUCIAL
A91: United States (EN) | B91: ='pampers-en_us'!C63 -> 80859348 | C91: ='pampers-en_us'!E63 -> Pampers Ultra Clean | D91: ='pampers-en_us'!B63 -> Pampers | E91: ='pampers-en_us'!D63 -> Inactive | F91: ='pampers-en_us'!M63 -> 1054 | G91: ='pampers-en_us'!M63 -> 1054 | H91: Find active successor; otherwise activate. | I91: Reviews are currently hidden because they are associated with inactive products. | J91: Map IDs to a live PDP; migrate or activate. | K91: CRUCIAL
A92: Germany | B92: ='pampers-de_de'!C21 -> 19-DE | C92: ='pampers-de_de'!E21 -> FEUCHTTÜCHER Pampers® New Baby Sensitive™ Feuchttücher | D92: ='pampers-de_de'!B21 -> Pampers | E92: ='pampers-de_de'!D21 -> Inactive | F92: ='pampers-de_de'!M21 -> 1004 | G92: ='pampers-de_de'!M21 -> 1004 | H92: Find active successor; otherwise activate. | I92: Reviews are currently hidden because they are associated with inactive products. | J92: Map IDs to a live PDP; migrate or activate. | K92: CRUCIAL
A93: France | B93: ='pampers-fr_fr'!C76 -> 2-FR | C93: ='pampers-fr_fr'!E76 -> Pampers New Baby | D93: ='pampers-fr_fr'!B76 -> Pampers | E93: ='pampers-fr_fr'!D76 -> Inactive | F93: ='pampers-fr_fr'!M76 -> 962 | G93: ='pampers-fr_fr'!M76 -> 962 | H93: Find active successor; otherwise activate. | I93: Reviews are currently hidden because they are associated with inactive products. | J93: Map IDs to a live PDP; migrate or activate. | K93: CRUCIAL
A94: Germany | B94: ='pampers-de_de'!C36 -> 711155941-DE | C94: ='pampers-de_de'!E36 -> Pampers Active Fit | D94: ='pampers-de_de'!B36 -> Pampers | E94: ='pampers-de_de'!D36 -> Inactive | F94: ='pampers-de_de'!M36 -> 850 | G94: ='pampers-de_de'!M36 -> 850 | H94: Find active successor; otherwise activate. | I94: Reviews are currently hidden because they are associated with inactive products. | J94: Map IDs to a live PDP; migrate or activate. | K94: CRUCIAL
A95: United States (EN) | B95: ='pampers-en_us'!C14 -> 761042387 | C95: ='pampers-en_us'!E14 -> Kandoo Flushable Toilet Wipes | D95: ='pampers-en_us'!B14 -> Pampers | E95: ='pampers-en_us'!D14 -> Inactive | F95: ='pampers-en_us'!M14 -> 807 | G95: ='pampers-en_us'!M14 -> 807 | H95: Find active successor; otherwise activate. | I95: Reviews are currently hidden because they are associated with inactive products. | J95: Map IDs to a live PDP; migrate or activate. | K95: CRUCIAL
A96: France | B96: ='pampers-fr_fr'!C39 -> FR-af2 | C96: ='pampers-fr_fr'!E39 -> COUCHES Pampers Premium Protection Active Fit | D96: ='pampers-fr_fr'!B39 -> Pampers | E96: ='pampers-fr_fr'!D39 -> Inactive | F96: ='pampers-fr_fr'!M39 -> 796 | G96: ='pampers-fr_fr'!M39 -> 796 | H96: Find active successor; otherwise activate. | I96: Reviews are currently hidden because they are associated with inactive products. | J96: Map IDs to a live PDP; migrate or activate. | K96: CRUCIAL
A97: United States (EN) | B97: ='pampers-en_us'!C70 -> pampers-expressions-wipes | C97: ='pampers-en_us'!E70 -> Pampers® Expressions Wipes | D97: ='pampers-en_us'!B70 -> Pampers | E97: ='pampers-en_us'!D70 -> Inactive | F97: ='pampers-en_us'!M70 -> 792 | G97: ='pampers-en_us'!M70 -> 792 | H97: Find active successor; otherwise activate. | I97: Reviews are currently hidden because they are associated with inactive products. | J97: Map IDs to a live PDP; migrate or activate. | K97: CRUCIAL
A98: Japan | B98: ='pampers-ja_jp'!C30 -> Pampers_LeadingEdge_Star | C98: ='pampers-ja_jp'!E30 -> パンパースのはじめての肌へのいちばん（テープ） | D98: ='pampers-ja_jp'!B30 -> Pampers | E98: ='pampers-ja_jp'!D30 -> Inactive | F98: ='pampers-ja_jp'!M30 -> 727 | G98: ='pampers-ja_jp'!M30 -> 727 | H98: Find active successor; otherwise activate. | I98: Reviews are currently hidden because they are associated with inactive products. | J98: Map IDs to a live PDP; migrate or activate. | K98: CRUCIAL
A99: Spain | B99: =pgdodotspain!C13 -> 2140000 | C99: =pgdodotspain!E13 -> TOALLITAS Dodot® Activity | D99: =pgdodotspain!B13 -> Pampers | E99: =pgdodotspain!D13 -> Inactive | F99: =pgdodotspain!M13 -> 685 | G99: =pgdodotspain!M13 -> 685 | H99: Find active successor; otherwise activate. | I99: Reviews are currently hidden because they are associated with inactive products. | J99: Map IDs to a live PDP; migrate or activate. | K99: CRUCIAL
A100: United States (EN) | B100: ='pampers-en_us'!C88 -> 761043742 | C100: ='pampers-en_us'!E88 -> Pampers® Underjams™ | D100: ='pampers-en_us'!B88 -> Pampers | E100: ='pampers-en_us'!D88 -> Inactive | F100: ='pampers-en_us'!M88 -> 580 | G100: ='pampers-en_us'!M88 -> 580 | H100: Find active successor; otherwise activate. | I100: Reviews are currently hidden because they are associated with inactive products. | J100: Map IDs to a live PDP; migrate or activate. | K100: CRUCIAL
A101: United States (ES) | B101: ='pampers-es'!C36 -> 261044222 | C101: ='pampers-es'!E36 -> Pampers® Swaddlers™ | D101: ='pampers-es'!B36 -> Pampers | E101: ='pampers-es'!D36 -> Inactive | F101: ='pampers-es'!M36 -> 549 | G101: ='pampers-es'!M36 -> 549 | H101: Find active successor; otherwise activate. | I101: Reviews are currently hidden because they are associated with inactive products. | J101: Map IDs to a live PDP; migrate or activate. | K101: CRUCIAL
A102: United States (EN) | B102: ='pampers-en_us'!C39 -> 761044192 | C102: ='pampers-en_us'!E39 -> Kandoo Handsoap, Body Wash and Shampoo | D102: ='pampers-en_us'!B39 -> Pampers | E102: ='pampers-en_us'!D39 -> Inactive | F102: ='pampers-en_us'!M39 -> 542 | G102: ='pampers-en_us'!M39 -> 542 | H102: Find active successor; otherwise activate. | I102: Reviews are currently hidden because they are associated with inactive products. | J102: Map IDs to a live PDP; migrate or activate. | K102: CRUCIAL
A103: Germany | B103: ='pampers-de_de'!C26 -> Pampers_Active_Fit_2 | C103: ='pampers-de_de'!E26 -> WINDELN Pampers Premium Protection Active Fit | D103: ='pampers-de_de'!B26 -> Pampers | E103: ='pampers-de_de'!D26 -> Inactive | F103: ='pampers-de_de'!M26 -> 535 | G103: ='pampers-de_de'!M26 -> 535 | H103: Find active successor; otherwise activate. | I103: Reviews are currently hidden because they are associated with inactive products. | J103: Map IDs to a live PDP; migrate or activate. | K103: CRUCIAL
A104: France | B104: ='pampers-fr_fr'!C32 -> NBPP-FRFR | C104: ='pampers-fr_fr'!E32 -> COUCHES Pampers Premium Protection | D104: ='pampers-fr_fr'!B32 -> Pampers | E104: ='pampers-fr_fr'!D32 -> Inactive | F104: ='pampers-fr_fr'!M32 -> 532 | G104: ='pampers-fr_fr'!M32 -> 532 | H104: Find active successor; otherwise activate. | I104: Reviews are currently hidden because they are associated with inactive products. | J104: Map IDs to a live PDP; migrate or activate. | K104: CRUCIAL
A105: United States (EN) | B105: ='pampers-en_us'!C62 -> 761042441 | C105: ='pampers-en_us'!E62 -> Pampers UnderJams Absorbent Night Wear for Girls | D105: ='pampers-en_us'!B62 -> Pampers | E105: ='pampers-en_us'!D62 -> Inactive | F105: ='pampers-en_us'!M62 -> 501 | G105: ='pampers-en_us'!M62 -> 501 | H105: Find active successor; otherwise activate. | I105: Reviews are currently hidden because they are associated with inactive products. | J105: Map IDs to a live PDP; migrate or activate. | K105: CRUCIAL
A106: United States (EN) | B106: ='pampers-en_us'!C57 -> Pampers_Swaddlers_Sweet_Dreams | C106: ='pampers-en_us'!E57 -> Pampers® Swaddlers Sweet Dreams | D106: ='pampers-en_us'!B57 -> Pampers | E106: ='pampers-en_us'!D57 -> Inactive | F106: ='pampers-en_us'!M57 -> 494 | G106: ='pampers-en_us'!M57 -> 494 | H106: Find active successor; otherwise activate. | I106: Reviews are currently hidden because they are associated with inactive products. | J106: Map IDs to a live PDP; migrate or activate. | K106: CRUCIAL
A107: Spain | B107: =pgdodotspain!C24 -> 2150000 | C107: =pgdodotspain!E24 -> PAÑALES Dodot® Activity | D107: =pgdodotspain!B24 -> Pampers | E107: =pgdodotspain!D24 -> Inactive | F107: =pgdodotspain!M24 -> 474 | G107: =pgdodotspain!M24 -> 474 | H107: Find active successor; otherwise activate. | I107: Reviews are currently hidden because they are associated with inactive products. | J107: Map IDs to a live PDP; migrate or activate. | K107: CRUCIAL
A108: Japan | B108: ='pampers-ja_jp'!C35 -> pampers_main_line_pants | C108: ='pampers-ja_jp'!E35 -> さらさらケアパンツ Mたっち～XXL | D108: ='pampers-ja_jp'!B35 -> Pampers | E108: ='pampers-ja_jp'!D35 -> Inactive | F108: ='pampers-ja_jp'!M35 -> 449 | G108: ='pampers-ja_jp'!M35 -> 449 | H108: Find active successor; otherwise activate. | I108: Reviews are currently hidden because they are associated with inactive products. | J108: Map IDs to a live PDP; migrate or activate. | K108: CRUCIAL
A109: United Kingdom | B109: ='pampers-en_gb'!C11 -> PAMPERS_PREMIUM_PROTECTION | C109: ='pampers-en_gb'!E11 -> NAPPIES Pampers Premium Protection | D109: ='pampers-en_gb'!B11 -> Pampers | E109: ='pampers-en_gb'!D11 -> Inactive | F109: ='pampers-en_gb'!M11 -> 435 | G109: ='pampers-en_gb'!M11 -> 435 | H109: Find active successor; otherwise activate. | I109: Reviews are currently hidden because they are associated with inactive products. | J109: Map IDs to a live PDP; migrate or activate. | K109: CRUCIAL
A110: United Kingdom | B110: ='pampers-en_gb'!C35 -> Aqua_Pure_Wipes | C110: ='pampers-en_gb'!E35 -> Pampers® Aqua Pure™ | D110: ='pampers-en_gb'!B35 -> Pampers | E110: ='pampers-en_gb'!D35 -> Inactive | F110: ='pampers-en_gb'!M35 -> 433 | G110: ='pampers-en_gb'!M35 -> 433 | H110: Find active successor; otherwise activate. | I110: Reviews are currently hidden because they are associated with inactive products. | J110: Map IDs to a live PDP; migrate or activate. | K110: CRUCIAL
A111: France | B111: ='pampers-fr_fr'!C23 -> active-fit-pants-FR | C111: ='pampers-fr_fr'!E23 -> COUCHES-CULOTTES Pampers Active Fit Pants | D111: ='pampers-fr_fr'!B23 -> Pampers | E111: ='pampers-fr_fr'!D23 -> Inactive | F111: ='pampers-fr_fr'!M23 -> 433 | G111: ='pampers-fr_fr'!M23 -> 433 | H111: Find active successor; otherwise activate. | I111: Reviews are currently hidden because they are associated with inactive products. | J111: Map IDs to a live PDP; migrate or activate. | K111: CRUCIAL
A112: United States (EN) | B112: ='pampers-en_us'!C27 -> 10900827 | C112: ='pampers-en_us'!E27 -> Pampers® Cruisers diapers | D112: ='pampers-en_us'!B27 -> Pampers | E112: ='pampers-en_us'!D27 -> Inactive | F112: ='pampers-en_us'!M27 -> 394 | G112: ='pampers-en_us'!M27 -> 394 | H112: Find active successor; otherwise activate. | I112: Reviews are currently hidden because they are associated with inactive products. | J112: Map IDs to a live PDP; migrate or activate. | K112: CRUCIAL
A113: Germany | B113: ='pampers-de_de'!C18 -> PAMPERS_NEW_BABY_SENSITIVE | C113: ='pampers-de_de'!E18 -> Pampers New Baby Sensitive | D113: ='pampers-de_de'!B18 -> Pampers | E113: ='pampers-de_de'!D18 -> Inactive | F113: ='pampers-de_de'!M18 -> 373 | G113: ='pampers-de_de'!M18 -> 373 | H113: Find active successor; otherwise activate. | I113: Reviews are currently hidden because they are associated with inactive products. | J113: Map IDs to a live PDP; migrate or activate. | K113: CRUCIAL
A114: Japan | B114: ='pampers-ja_jp'!C36 -> Pampers_LeadingEdgePants_Star | C114: ='pampers-ja_jp'!E36 -> パンパースの肌へのいちばん（パンツ） | D114: ='pampers-ja_jp'!B36 -> Pampers | E114: ='pampers-ja_jp'!D36 -> Inactive | F114: ='pampers-ja_jp'!M36 -> 356 | G114: ='pampers-ja_jp'!M36 -> 356 | H114: Find active successor; otherwise activate. | I114: Reviews are currently hidden because they are associated with inactive products. | J114: Map IDs to a live PDP; migrate or activate. | K114: CRUCIAL
A115: Germany | B115: ='pampers-de_de'!C34 -> 711155944-DE | C115: ='pampers-de_de'!E34 -> Pampers Simply Dry | D115: ='pampers-de_de'!B34 -> Pampers | E115: ='pampers-de_de'!D34 -> Inactive | F115: ='pampers-de_de'!M34 -> 344 | G115: ='pampers-de_de'!M34 -> 344 | H115: Find active successor; otherwise activate. | I115: Reviews are currently hidden because they are associated with inactive products. | J115: Map IDs to a live PDP; migrate or activate. | K115: CRUCIAL
A116: Japan | B116: ='pampers-ja_jp'!C20 -> 4902430148887 | C116: ='pampers-ja_jp'!E20 -> パンパース さらさらパンツ | D116: ='pampers-ja_jp'!B20 -> Pampers | E116: ='pampers-ja_jp'!D20 -> Inactive | F116: ='pampers-ja_jp'!M20 -> 320 | G116: ='pampers-ja_jp'!M20 -> 320 | H116: Find active successor; otherwise activate. | I116: Reviews are currently hidden because they are associated with inactive products. | J116: Map IDs to a live PDP; migrate or activate. | K116: CRUCIAL
A117: Germany | B117: ='pampers-de_de'!C33 -> PAMPERS_NINJAMAS_PYJAMA_PANTS | C117: ='pampers-de_de'!E33 -> NINJAMAS PYJAMA PANTS | D117: ='pampers-de_de'!B33 -> Pampers | E117: ='pampers-de_de'!D33 -> Inactive | F117: ='pampers-de_de'!M33 -> 300 | G117: ='pampers-de_de'!M33 -> 300 | H117: Find active successor; otherwise activate. | I117: Reviews are currently hidden because they are associated with inactive products. | J117: Map IDs to a live PDP; migrate or activate. | K117: CRUCIAL
A118: United States (ES) | B118: ='pampers-es'!C24 -> 261044229 | C118: ='pampers-es'!E24 -> Pampers® Cruisers™ | D118: ='pampers-es'!B24 -> Pampers | E118: ='pampers-es'!D24 -> Inactive | F118: ='pampers-es'!M24 -> 291 | G118: ='pampers-es'!M24 -> 291 | H118: Find active successor; otherwise activate. | I118: Reviews are currently hidden because they are associated with inactive products. | J118: Map IDs to a live PDP; migrate or activate. | K118: CRUCIAL
A119: United States (EN) | B119: ='pampers-en_us'!C19 -> 10900826 | C119: ='pampers-en_us'!E19 -> Pampers® Swaddlers diapers | D119: ='pampers-en_us'!B19 -> Pampers | E119: ='pampers-en_us'!D19 -> Inactive | F119: ='pampers-en_us'!M19 -> 276 | G119: ='pampers-en_us'!M19 -> 276 | H119: Find active successor; otherwise activate. | I119: Reviews are currently hidden because they are associated with inactive products. | J119: Map IDs to a live PDP; migrate or activate. | K119: CRUCIAL
A120: Japan | B120: ='pampers-ja_jp'!C27 -> Pampers_premium_line_tape | C120: ='pampers-ja_jp'!E27 -> はじめての肌へのいちばんテープ | D120: ='pampers-ja_jp'!B27 -> Pampers | E120: ='pampers-ja_jp'!D27 -> Inactive | F120: ='pampers-ja_jp'!M27 -> 266 | G120: ='pampers-ja_jp'!M27 -> 266 | H120: Find active successor; otherwise activate. | I120: Reviews are currently hidden because they are associated with inactive products. | J120: Map IDs to a live PDP; migrate or activate. | K120: CRUCIAL
A121: United States (ES) | B121: ='pampers-es'!C35 -> 261044261 | C121: ='pampers-es'!E35 -> Pampers® Baby-Dry™ | D121: ='pampers-es'!B35 -> Pampers | E121: ='pampers-es'!D35 -> Inactive | F121: ='pampers-es'!M35 -> 264 | G121: ='pampers-es'!M35 -> 264 | H121: Find active successor; otherwise activate. | I121: Reviews are currently hidden because they are associated with inactive products. | J121: Map IDs to a live PDP; migrate or activate. | K121: CRUCIAL
A122: United States (ES) | B122: ='pampers-es'!C34 -> 261057381 | C122: ='pampers-es'!E34 -> Pampers® Sensitive™ | D122: ='pampers-es'!B34 -> Pampers | E122: ='pampers-es'!D34 -> Inactive | F122: ='pampers-es'!M34 -> 255 | G122: ='pampers-es'!M34 -> 255 | H122: Find active successor; otherwise activate. | I122: Reviews are currently hidden because they are associated with inactive products. | J122: Map IDs to a live PDP; migrate or activate. | K122: CRUCIAL
A123: Japan | B123: ='pampers-ja_jp'!C32 -> Pampers_main_line_tape | C123: ='pampers-ja_jp'!E32 -> さらさらケア テープ | D123: ='pampers-ja_jp'!B32 -> Pampers | E123: ='pampers-ja_jp'!D32 -> Inactive | F123: ='pampers-ja_jp'!M32 -> 247 | G123: ='pampers-ja_jp'!M32 -> 247 | H123: Find active successor; otherwise activate. | I123: Reviews are currently hidden because they are associated with inactive products. | J123: Map IDs to a live PDP; migrate or activate. | K123: CRUCIAL
A124: Spain | B124: =pgdodotspain!C25 -> 2130000 | C124: =pgdodotspain!E25 -> PAÑALES-BRAGUITA Dodot® Pants | D124: =pgdodotspain!B25 -> Pampers | E124: =pgdodotspain!D25 -> Inactive | F124: =pgdodotspain!M25 -> 245 | G124: =pgdodotspain!M25 -> 245 | H124: Find active successor; otherwise activate. | I124: Reviews are currently hidden because they are associated with inactive products. | J124: Map IDs to a live PDP; migrate or activate. | K124: CRUCIAL
A125: Japan | B125: ='pampers-ja_jp'!C37 -> 4902430707046 | C125: ='pampers-ja_jp'!E37 -> 肌へのいちばん おしりふき | D125: ='pampers-ja_jp'!B37 -> Pampers | E125: ='pampers-ja_jp'!D37 -> Inactive | F125: ='pampers-ja_jp'!M37 -> 245 | G125: ='pampers-ja_jp'!M37 -> 245 | H125: Find active successor; otherwise activate. | I125: Reviews are currently hidden because they are associated with inactive products. | J125: Map IDs to a live PDP; migrate or activate. | K125: CRUCIAL
A126: Japan | B126: ='pampers-ja_jp'!C22 -> Pampers_premium_line_pants | C126: ='pampers-ja_jp'!E22 -> 肌へのいちばんパンツMたっち～XL | D126: ='pampers-ja_jp'!B22 -> Pampers | E126: ='pampers-ja_jp'!D22 -> Inactive | F126: ='pampers-ja_jp'!M22 -> 220 | G126: ='pampers-ja_jp'!M22 -> 220 | H126: Find active successor; otherwise activate. | I126: Reviews are currently hidden because they are associated with inactive products. | J126: Map IDs to a live PDP; migrate or activate. | K126: CRUCIAL
A127: United States (EN) | B127: ='pampers-en_us'!C80 -> 80371909 | C127: ='pampers-en_us'!E80 -> Pampers Pure Protection | D127: ='pampers-en_us'!B80 -> Pampers | E127: ='pampers-en_us'!D80 -> Inactive | F127: ='pampers-en_us'!M80 -> 198 | G127: ='pampers-en_us'!M80 -> 198 | H127: Migrate reviews to active Product ID pampers_pure_protection_diapers. | I127: Reviews are currently hidden because they are associated with inactive products. | J127: Map IDs to a live PDP; migrate or activate. | K127: CRUCIAL
...

Sheet pampers-fr_fr
A1: Bazaarvoice
A2: Pampers-FR_FR R&R Key Metrics
A3: Run Date: Aug 12, 2026 12:00 AM UTC
A4: Instance: pampers-fr_fr
A5: Date range: All Time
A6: Date field: Review Submission Date
A7: Brand ID | B7: Brand | C7: Product ID | D7: Product Status | E7: Product Name | F7: Description | G7: Product Page URL | H7: Image URL | I7: UPC | J7: EAN | K7: Product Family | L7: Product Family - Expand | M7: # Approved Reviews
A8: 7-FR | B8: Pampers FR | C8: 181156484-FR | D8: Inactive | E8: Lingettes Pampers Sensitive | F8: Pendant que vous nettoyez et prenez soin de la peau de votre bébé, vous pouvez en profiter pour créer un lien avec lui. Offrez à votre bébé une toilette rafraîchissante avec les nouvelles lingettes Pampers Sensitive, qui intègrent à présent la nouvelle Soft Grip Texture™ unique. Elles sont désormais 15 % plus épaisses avec un motif ultra-doux. Ces lingettes sont plus efficaces pour une toilette plus douce. Donc, la seule chose que votre bébé sent lorsque vous le changez, c'est votre amour. | G8: http://dev.pampers.fr/Lingettes-Pampers-Sensitive | H8: http://dev.pampers.fr/fr_FR/images/pc/hb/lsp/products/prod_image_main_wipes_sensitive.png | M8: 1
A9: 7-FR | B9: Pampers FR | C9: 181156482-FR | D9: Inactive | E9: Pampers Active Fit | F9: Pampers Active Fit sont nos couches les plus absorbantes et les mieux ajustées. Elles offrent à votre bébé jusqu'à 12 heures bien au sec et, grâce à leur système d'ajustement 3-Way Fit, s'adaptent parfaitement au niveau de la taille, des cuisses et de l'entrejambe. | G9: http://dev.pampers.fr/Pampers-Active-Fit | H9: http://dev.pampers.fr/fr_FR/images/pc/hb/lsp/products/prod_image_main_diaper_activefit.png | J9: 4015400598947, 4015400599180, 4015400599241, 4015400599272, 4015400599302, 4015400617693, 4015400617778, 4015400617792, 4015400618218, 4015400618232, 4015400618256, 4015400618270, 4015400618836, 4015400618898, 4015400618928, 4015400618959, 4015400622543, 4015400696315, 4015400696346, 4015400696377, 4015400696407, 4015400696438, 4015400696469, 4015400696506, 4015400696544, 4015400696582, 4015400696629, 4015400696667, 4015400697374, 4015400697459, 4015400697497, 4015400697572, 4015400697626, 4015400697664, 4015400697701, 4015400697763, 4015400697909, 4015400697947, 4015400699422 | M9: 11
A10: 7-FR | B10: Pampers FR | C10: 181148361-FR | D10: Inactive | E10: Lingettes Pampers Sensitive | F10: Chaque pli et chaque fossette ont besoin de votre amour. C'est pourquoi Les lingettes Pampers Sensitive sont imprégnées de la lotion Pure Care qui nettoie tout en douceur et rétablit le pH naturel de la peau. | G10: http://www.pampers.fr/lingettes-pour-bebes-pampers-sensitive | H10: http://www.pampers.fr/fr_FR/images/pc/hb/products/prod_img_wipes_sensitiveNor.jpg | M10: 4
A11: 7-FR | B11: Pampers FR | C11: 8-FR | D11: Inactive | E11: Lingettes Pampers Sans Parfum | F11: Les lingettes Pampers nettoient et rafraîchissent la peau de bébé. La toilette Pampers existe aussi sans parfum | G11: http://64.58.71.185/fr_FR/proddetail/baby-products/naturals/id/8 | H11: http://64.58.71.185/fr_FR/products/images/nt_gb_183_173_b.gif | M11: 1
A12: 7-FR | B12: Pampers FR | C12: 181156481-FR | D12: Inactive | E12: Pampers New Baby | F12: Notre meilleure protection pour la peau des nouveau-nés. Chaque petit miracle mérite la meilleure protection, c'est pourquoi nos nouvelles couches New Baby sont à présent dotées d'un indicateur d’urine coloré. Il devient bleu quand bébé fait pipi pour vous signaler qu'il faut changer sa couche. Elles sont dotées du système Double Absorption exclusif, spécialement conçu pour absorber les selles molles des nouveau-nés et les garder bien au sec. Et elles sont maintenant encore plus douces pour apporter à votre bébé un confort et une protection exceptionnels. En complément, utilisez les nouvelles lingettes Sensitive Maximum Care, nos lingettes les plus douces pour une toilette Pampers tout en douceur de la peau délicate de votre bébé. | G12: http://dev.pampers.fr/Pampers-New-Baby | H12: http://dev.pampers.fr/fr_FR/images/pc/hb/lsp/products/prod_image_main_diaper_newbaby.png | M12: 30
A13: 7-FR | B13: Pampers FR | C13: 1-FR | D13: Inactive | E13: Couches Pampers Micro | F13: A la sortie de la maternité, les couches Pampers Micro sont conçues pour le change des bébés de petit poids et des prématurés. Dotée de toute la protection Pampers, la couche Pampers Micro s’adapte à la morphologie de bébés de petit poids (de 1 kg à 2,5 kg) | G13: http://64.58.71.185/fr_FR/proddetail/baby-products/micro/id/1/sectionid/0 | H13: http://64.58.71.185/fr_FR/products/images/af_fr_183_173_b.gif | M13: 7
A14: 7-FR | B14: Pampers FR | C14: 181156483-FR | D14: Inactive | E14: Simply Dry | F14: Les couches Pampers Simply Dry sont une bonne solution pour les mamans qui veulent faire attention à leurs dépenses. Elles vous offrent l'absorption Pampers à un prix abordable, pour profiter pleinement des moments passés avec votre bébé sans vous ruiner. | G14: http://dev.pampers.fr/Simply-Dry | H14: http://dev.pampers.fr/fr_FR/images/pc/hb/lsp/products/prod_image_main_diaper_simplydry.png | J14: 4015400549710, 4015400549741, 4015400549802, 4015400549833, 4015400549864, 4015400549895, 4015400549925, 4015400686484, 4015400687030, 4015400687054, 4015400687078 | M14: 16
A15: PAMPERS | B15: Pampers | C15: 8006540704615 | D15: Active | E15: PAMPERS PP GEANT T3 X46 | F15: PAMPERS PP GEANT T3 X46 | G15: https://fd12-courses.leclercdrive.fr/magasin-077201-077201-Ferte-Bernard/fiche-produits-205935-Couches-Pampers-Premium.aspx | H15: https://fd12-courses.leclercdrive.fr/magasin-077201-077201-Ferte-Bernard/fiche-produits-205935-Couches-Pampers-Premium.aspx | J15: 8006540704615 | M15: 19
A16: PAMPERS | B16: Pampers | C16: 8700216263764 | D16: Active | E16: PAMPERS BABY DRY MAXI T6 X78 | F16: PAMPERS BABY DRY MAXI T6 X78 | G16: https://fd9-courses.leclercdrive.fr/magasin-010901-010901-Saint-Jean-du-Falga/fiche-produits-212904-Couches-Pampers-Baby-Dry.aspx | H16: https://fd9-photos.leclercdrive.fr/image.ashx?id=2696438&use=d&cat=p&typeid=i | J16: 8700216263764 | M16: 9
A17: PAMPERS | B17: Pampers | C17: PAMPERS_SENSITIVE_ZERO_PLASTIQUE_LINGETTES | D17: Inactive | E17: Pampers® Sensitive 0% Plastique | F17: Pampers® Sensitive 0% Plastique | G17: https://www.pampers.fr/couches-et-lingettes/pampers-sensitive-zero-plastique-lingettes | H17: https://images.ctfassets.net/g4icgs65at4c/5zaINWN2mqjmpFe4O5x1Nk/62ce5ee0531349ac2d409be41161ef71/200x200_pampersSensitive_wipes.png | J17: 8006540523056, 8006540523087, 8006540523124 | M17: 8
A18: PAMPERS | B18: Pampers | C18: 8006540715802 | D18: Active | E18: PAMPERS BABY DRY GEANT T5 X39 | F18: PAMPERS BABY DRY GEANT T5 X39 | G18: https://fd12-courses.leclercdrive.fr/magasin-077201-077201-Ferte-Bernard/fiche-produits-205853-Couches-Pampers-Baby-dry.aspx | H18: https://fd12-courses.leclercdrive.fr/magasin-077201-077201-Ferte-Bernard/fiche-produits-205853-Couches-Pampers-Baby-dry.aspx | J18: 8006540715802 | M18: 18
A19: PAMPERS | B19: Pampers | C19: PPP-FRFR | D19: Active | E19: Pampers® Premium Protection™ Pants | F19: Pampers® Premium Protection™ Pants | G19: https://www.pampers.fr/couches-et-lingettes/pampers-premium-protection-pants-couches-culottes | H19: https://images.ctfassets.net/g4icgs65at4c/6Epbbb9TInXvKI9IMVqyzP/2491c83c3023dffa8f649a586bb55030/2099_44_Pampers_FR_PPPants_PDPUpdate_FEB24-PPP-324x286.png | J19: 8001090184009, 8006540710074, 8006540710104, 8006540710135, 8006540710166, 8006540710197, 8006540710227, 8006540710357, 8006540710395, 8006540710418, 8006540710432, 8006540710456, 8006540710470, 8006540710494, 8006540710517, 8006540710531, 8006540759059, 8700216664332, 8700216679091, 8700216679107, 8700216679121, 8700216679176, 8700216679183, 8700216679268, 8700216679275, 8700216679312, 8700216679336, 8700216679381, 8700216679404, 8700216679466 | M19: 1160
A20: PAMPERS | B20: Pampers | C20: 8006540704646 | D20: Active | E20: PAMPERS PP GEANT T4 X39 | F20: PAMPERS PP GEANT T4 X39 | G20: https://fd12-courses.leclercdrive.fr/magasin-077201-077201-Ferte-Bernard/fiche-produits-202858-Couches-Pampers-Premium.aspx | H20: https://fd12-courses.leclercdrive.fr/magasin-077201-077201-Ferte-Bernard/fiche-produits-202858-Couches-Pampers-Premium.aspx | J20: 8006540704646 | M20: 16
A21: PAMPERS | B21: Pampers | C21: 8700216290951 | D21: Active | E21: PAMPERS BD PANTS MAXI T5 X82 | F21: PAMPERS BD PANTS MAXI T5 X82 | G21: https://fd12-courses.leclercdrive.fr/magasin-077201-077201-Ferte-Bernard/fiche-produits-223871-Couches-culottes-Pampers-Baby.aspx | H21: https://fd12-courses.leclercdrive.fr/magasin-077201-077201-Ferte-Bernard/fiche-produits-223871-Couches-culottes-Pampers-Baby.aspx | J21: 8700216290951 | M21: 10
A22: PAMPERS | B22: Pampers | C22: 8700216251327 | D22: Active | E22: PAMPERS HARMONIE GEANT T4 X36 | F22: PAMPERS HARMONIE GEANT T4 X36 | G22: https://fd12-courses.leclercdrive.fr/magasin-077201-077201-Ferte-Bernard/fiche-produits-223903-Couches-Pampers-Harmonie.aspx | H22: https://fd12-courses.leclercdrive.fr/magasin-077201-077201-Ferte-Bernard/fiche-produits-223903-Couches-Pampers-Harmonie.aspx | J22: 8700216251327 | M22: 10
A23: PAMPERS | B23: Pampers | C23: active-fit-pants-FR | D23: Inactive | E23: COUCHES-CULOTTES Pampers Active Fit Pants | F23: COUCHES-CULOTTES Pampers Active Fit Pants | G23: https://www.pampers.fr/produits/pampers-premium-active-fit-pants-couches-culottes | H23: http://azcdn.multibrand.pgsitecore.com/fr-FR/-/media/Pampers/Pampers-FR/Images/Products/Product-Oasis/Closed-Module/Active-Fit-Pants/ClosedModule-ActiveFitsPants-FR.png?v=3-201803140534 | M23: 433
A24: PAMPERS | B24: Pampers | C24: 8006540715734 | D24: Active | E24: PAMPERS BABY DRY GEANT T4 X45 | F24: PAMPERS BABY DRY GEANT T4 X45 | G24: https://fd12-courses.leclercdrive.fr/magasin-077201-077201-Ferte-Bernard/fiche-produits-205941-Couches-Pampers-Baby-dry.aspx | H24: https://fd12-courses.leclercdrive.fr/magasin-077201-077201-Ferte-Bernard/fiche-produits-205941-Couches-Pampers-Baby-dry.aspx | J24: 8006540715734 | M24: 14
A25: PAMPERS | B25: Pampers | C25: 8006540780350 | D25: Active | E25: PAMPERS PP NB GEANT T1 X42 | F25: PAMPERS PP NB GEANT T1 X42 | G25: https://fd12-courses.leclercdrive.fr/magasin-077201-077201-Ferte-Bernard/fiche-produits-205945-Couches-Pampers-Premium.aspx | H25: https://fd12-courses.leclercdrive.fr/magasin-077201-077201-Ferte-Bernard/fiche-produits-205945-Couches-Pampers-Premium.aspx | J25: 8006540780350 | M25: 11
A26: PAMPERS | B26: Pampers | C26: 8700216263795 | D26: Active | E26: PAMPERS BABY DRY MAXI T5 X90 | F26: PAMPERS BABY DRY MAXI T5 X90 | G26: https://fd12-courses.leclercdrive.fr/magasin-077201-077201-Ferte-Bernard/fiche-produits-223862-Couches-Pampers-Baby-Dry-Maxi.aspx | H26: https://fd12-photos.leclercdrive.fr/image.ashx?id=2685479&use=d&cat=p&typeid=i | J26: 8700216263795 | M26: 13
A27: PAMPERS | B27: Pampers | C27: PAMPERS_BABY_DRY_NIGHT_PANTS | D27: Active | E27: Pampers® Baby-Dry™ Night Pants | F27: Pampers® Baby-Dry™ Night Pants | G27: https://www.pampers.fr/couches-et-lingettes/pampers-baby-dry-night-pants | H27: https://images.ctfassets.net/g4icgs65at4c/6Qudm6RtfxEqaVFcqLQR5r/8ea9327f35f8bfb5c333ff00565d73f7/2099_48_Pampers_FR_BDYNP_PDPUpdate_FEB24-BDNP-324x286.png | J27: 8006540234792, 8006540234853, 8006540710739, 8006540710975, 8006540711309, 8006540711569, 8006540711828, 8006540711910, 8700216669696, 8700216669764, 8700216669795, 8700216669887 | M27: 130
A28: PAMPERS | B28: Pampers | C28: 11-FR | D28: Inactive | E28: Kandoo | F28: Kandoo | G28: https://www.pampers.fr/produit-normal/kandoo | H28: http://cdn.multibrand.pgsitecore.com/fr-FR/-/media/Pampers/Pampers-FR/Images/Products/Primary/pampers-kandoo-refill-toilet-wipes-melon-50-630x330.png?v=1-201505060814 | J28: 4015400192381, 4015400192787, 4015400192930 | M28: 20
A29: PAMPERS | B29: Pampers | C29: 8006540715697 | D29: Active | E29: PAMPERS BABY DRY GEANT T3 X52 | F29: PAMPERS BABY DRY GEANT T3 X52 | G29: https://fd12-courses.leclercdrive.fr/magasin-077201-077201-Ferte-Bernard/fiche-produits-205942-Couches-Pampers-Baby-dry.aspx | H29: https://fd12-courses.leclercdrive.fr/magasin-077201-077201-Ferte-Bernard/fiche-produits-205942-Couches-Pampers-Baby-dry.aspx | J29: 8006540715697 | M29: 18
A30: PAMPERS | B30: Pampers | C30: 6-FR | D30: Active | E30: Pampers® Sensitive™ | F30: Pampers® Sensitive™ | G30: https://www.pampers.fr/couches-et-lingettes/pampers-sensitive-lingettes | H30: https://images.ctfassets.net/g4icgs65at4c/1Jt1ydaFV2AP8pN9M47fy5/6ffaf5a9cc7f7ca1e12509229a5a864f/2099_63_Pampers_FR_Sensitive_Wipes_PDP_APR24-wipes-sensitive-324x286.png | J30: 8001841041391, 8001841041483, 8001841062556, 8001841062624, 8001841063188 | M30: 538
A31: PAMPERS | B31: Pampers | C31: 7-FR | D31: Active | E31: Pampers® Fresh Clean | F31: Pampers® Fresh Clean | G31: https://www.pampers.fr/couches-et-lingettes/pampers-fresh-clean-lingettes | H31: https://images.ctfassets.net/g4icgs65at4c/1ihhKZiaU9XtyqblumvJZx/b452707c9897b62f37349b9895d79541/2099_66_Pampers_FR_Fresh_Clean_Wipes_PDP_APR24-freshclean-324x286.png | J31: 4015400622567, 8001841041360, 8001841077598, 8001841077864, 8001841077949, 8001841078441, 8001841078496 | M31: 146
A32: PAMPERS | B32: Pampers | C32: NBPP-FRFR | D32: Inactive | E32: COUCHES Pampers Premium Protection | F32: COUCHES Pampers Premium Protection | G32: https://www.pampers.fr/produits/pampers-premium-protection-new-baby-couches | H32: https://res.cloudinary.com/pmprs/image/upload/c_scale,f_auto,q_60/v20191203225559/pampersc1/fr-fr/-/media/pampers/pampers-fr/images/products/product-oasis/closed-module/premium-protection-nb/closedmodule-premiumprotectionnb-fr.png?v=4-201904191351 | J32: 4015400557425, 4015400599425, 4015400599517, 4015400599548, 4015400599685, 4015400639015, 4015400701569, 4015400835646, 4015400835776, 4015400835851, 4015400835974, 4015400836025, 4015400849087, 4015400849155, 8001841057842, 8001841057866, 8718969860550 | M32: 532
A33: PAMPERS | B33: Pampers | C33: PAMPERS_HARMONIE_HYBRIDE | D33: Inactive | E33: Couches Pampers® Harmonie Hybrid | F33: Couches Pampers® Harmonie Hybrid | G33: https://www.pampers.fr/couches-et-lingettes/pampers-harmonie-hybrid-old | H33: https://images.ctfassets.net/g4icgs65at4c/zMpKbvNe5sfLotMzhivSQ/f8fa23163c381b2e7119cbabbf666497/200x200_pampersHybrid_probeerkit.png | J33: 8006540284254, 8006540284407, 8006540297933, 8006540297995, 8006540298022, 8006540354094, 8006540354155 | M33: 46
A34: PAMPERS | B34: Pampers | C34: 8700216207263 | D34: Active | E34: PAMPERS PP MAXI T4 X86 | F34: PAMPERS PP MAXI T4 X86 | G34: https://fd12-courses.leclercdrive.fr/magasin-077201-077201-Ferte-Bernard/fiche-produits-223899-Couches-Pampers-Premium.aspx | H34: https://fd12-photos.leclercdrive.fr/image.ashx?id=2737827&use=d&cat=p&typeid=i | J34: 8700216207263 | M34: 12
A35: PAMPERS | B35: Pampers | C35: 8700216207645 | D35: Active | E35: PAMPERS PP NB PAQUET T1 X24 | F35: PAMPERS PP NB PAQUET T1 X24 | G35: https://fd12-courses.leclercdrive.fr/magasin-077201-077201-Ferte-Bernard/fiche-produits-206094-Coucjes-Pampers-Premium.aspx | H35: https://fd12-courses.leclercdrive.fr/magasin-077201-077201-Ferte-Bernard/fiche-produits-206094-Coucjes-Pampers-Premium.aspx | J35: 8700216207645 | M35: 4
... A74: PAMPERS | B74: Pampers | C74: 181156501-FR | D74: Inactive | E74: LINGETTES Pampers New Baby Sensitive | F74: LINGETTES Pampers New Baby Sensitive | G74: https://www.pampers.fr/produits/pampers-new-baby-sensitive-lingettes | H74: http://azcdn.multibrand.pgsitecore.com/fr-FR/-/media/Pampers/Pampers-FR/Images/Products/Product-Oasis/Closed-Module/Wipes-NB-Sensitive/Closedmodule-Wipes-NB-Sensitive_FR.png?v=2-201709221355 | J74: 4015400623496, 4015400623663 | M74: 190
A75: PAMPERS_FR | B75: Pampers | C75: 5-FR | D75: Inactive | E75: Pampers Baby Dry | F75: Pampers Baby Dry | G75: http://www.pampers.fr/produit-star/pampers-baby-dry | J75: 4015400689218, 4015400689331, 4015400689416, 4015400689614, 4015400689652, 4015400696278, 4015400696872, 4015400705130, 4015400833260, 4015400833307, 4015400833338, 4015400833369, 4015400833390, 4015400833420, 4015400833444, 4015400833505, 4015400833550, 4015400833581, 4015400833628, 4015400833659, 4015400833765, 4015400833796, 4015400833826, 4015400833857, 4015400833871, 4015400833918, 4015400833956, 4015400833987, 4015400834021, 4015400834052, 4015400834083, 4015400834113, 4015400834144, 4015400834168, 4015400834205, 4015400834243, 4015400834274, 4015400834311, 4015400834335, 4015400834366, 4015400834397, 4015400834410, 4015400834458, 4015400834489, 4015400834748, 4015400834762, 4015400844006, 4015400844044, 4015400844082, 4015400844129, 4015400844150 | M75: 15
A76: PAMPERS_FR | B76: Pampers | C76: 2-FR | D76: Inactive | E76: Pampers New Baby | F76: Pampers New Baby | G76: http://www.pampers.fr/produit-star/pampers-new-baby | J76: 4015400599456, 4015400639015, 4015400835646, 4015400835776, 4015400835851, 4015400835936, 4015400836025, 4015400849087, 4015400849155, 4015400849193 | M76: 962
A77: PAMPERS_FR | B77: Pampers | C77: 75 | D77: Inactive | E77: Pampers Baby-Dry | F77: Pampers Baby-Dry | G77: http://www.pampers.fr/produit-star/pampers-baby-dry | J77: 4015400542902, 4015400542940, 4015400543480, 4015400601876, 4015400602149, 4015400602170, 4015400602248, 4015400602309, 4015400602330, 4015400602361, 4015400625896, 4015400626428, 4015400646242, 4015400646341, 4015400646839, 4015400659921, 4015400659952, 4015400659976, 4015400689218, 4015400689263, 4015400689331, 4015400689416, 4015400689454, 4015400689492, 4015400689539, 4015400689614, 4015400689652, 4015400694458, 4015400694489, 4015400694502, 4015400694526, 4015400695578, 4015400695592, 4015400695615, 4015400695639, 4015400695653, 4015400695677, 4015400695691, 4015400695714, 4015400695769, 4015400695783, 4015400695806, 4015400695837, 4015400696155, 4015400696186, 4015400696216, 4015400696247, 4015400696278, 4015400696872, 4015400696933, 4015400705130, 4015400705161, 4015400729624, 4015400729655, 4015400729679, 4015400730804, 4015400730835 | M77: 1101
A78: PAMPERS_FR | B78: Pampers | C78: 4-FR | D78: Inactive | E78: Pampers Easy Up | F78: Pampers Easy Up | J78: 4015400293637, 4015400535690, 4015400535737, 4015400535805, 4015400535843, 4015400535881, 4015400535942, 4015400535973, 4015400536000, 4015400536086, 4015400536123, 4015400536178, 4015400536208, 4015400536239, 4015400536253, 4015400536277, 4015400536291 | M78: 17
A79: PAMPERS_FR | B79: Pampers | C79: FR-af1 | D79: Inactive | E79: Pampers Active Fit | F79: Pampers Active Fit | J79: 4015400557487, 4015400557517, 4015400557548, 4015400557579, 4015400598947, 4015400599180, 4015400599241, 4015400599272, 4015400599302, 4015400617693, 4015400617778, 4015400617792, 4015400618218, 4015400618232, 4015400618256, 4015400618270, 4015400618836, 4015400618898, 4015400618928, 4015400618959, 4015400622543, 4015400696315, 4015400696346, 4015400696377, 4015400696407, 4015400696438, 4015400696469, 4015400696506, 4015400696544, 4015400696582, 4015400696629, 4015400696667, 4015400697374, 4015400697459, 4015400697497, 4015400697572, 4015400697626, 4015400697664, 4015400697701, 4015400697763, 4015400697909, 4015400697947, 4015400699422, 4015400702481, 4015400702504, 4015400702528, 4015400702542 | M79: 7
A80: PAMPERS_FR | B80: Pampers | C80: 3-FR | D80: Inactive | E80: Pampers Active Fit | F80: Pampers Active Fit | G80: http://www.pampers.fr/produit-star/pampers-active-fit | J80: 4015400557456, 4015400557487, 4015400557517, 4015400557548, 4015400557579, 4015400702481, 4015400702504, 4015400702528, 4015400771333 | M80: 45
A81: pampers-fr_fr | B81: PAMPERS | C81: Pampers_harmonie_couches | D81: Active | E81: Pampers® Harmonie | F81: Pampers® Harmonie | G81: https://www.pampers.fr/couches-et-lingettes/pampers-harmonie-couches | H81: https://images.ctfassets.net/g4icgs65at4c/7sCbWFgsgzb3SwB7IwyLn6/9d6a719c30e51419804a196eacdeafcc/2099_46_Pampers_FR_HarmonieTaped_PDPUpdate_FEB24-HAR-324x286.png | J81: 8001090933294, 8001090933331, 8001090933393, 8001090933423, 8001090933430, 8001090933454, 8001090933492, 8001090933515, 8001090933607, 8001090933614, 8001090933645, 8001090933676, 8006540867808, 8006540867839, 8006540867860, 8006540867891, 8006540867921, 8006540929414, 8006540929445, 8006540929476, 8006540929506, 8006540929544, 8006540929575, 8006540929605, 8006540929636, 8006540929667, 8006540929698, 8006540929728, 8006540937778, 8006540937808, 8006540937853, 8006540937877, 8006540937914, 8006540938034, 8006540938058, 8006540938072, 8006540938126, 8006540938157, 8006540938188, 8006540938195, 8006540941294, 8006540941300, 8006540987230, 8700216251235, 8700216251259, 8700216668156, 8700216668194, 8700216668224, 8700216668231, 8700216668286, 8700216668323, 8700216668347, 8700216668378, 8700216668392, 8700216668446, 8700216668477, 8700216668484, 8700216668521, 8700216668545, 8700216668576, 8700216668606, 8700216668668, 8700216668675, 8700216668699, 8700216668729, 8700216668767, 8700216668798, 8700216678704, 8700216678728, 8700216678773 | M81: 2054
A82: pampers-fr_fr | B82: PAMPERS | C82: Pampers_aqua_harmonie_lingettes | D82: Active | E82: Pampers® Harmonie Aqua | F82: Pampers® Harmonie Aqua | G82: https://www.pampers.fr/couches-et-lingettes/pampers-aqua-harmonie-lingettes | H82: https://images.ctfassets.net/g4icgs65at4c/1KTbKP7NtjM76xG9vnfRu1/5dac234f150178d90fb615999d9b9a40/2099_51_Pampers_FR_HarmonieAquaWipes_PDPUpdate_FEB24-Wipes_HARAQUA-324x286.png | J82: 8001090934444, 8001090934482, 8001090934529, 8006540458525, 8006540458563, 8006540510247, 8006540556139, 8006540811245, 8006540811276 | M82: 568
C83: 181082376-FR | D83: Inactive | M83: 40
C84: {58F048B9-3836-46E2-8040-DC554AA22699} | D84: Inactive | M84: 0
C85: pampers-premium-protection-new-baby-couches | D85: Inactive | M85: 0
C86: 8006540469071 | D86: Inactive | M86: 0

Sheet pampers-en_gb
A1: Bazaarvoice
A2: Pampers-EN_GB R&R Key Metrics
A3: Run Date: Aug 12, 2026 12:00 AM UTC
A4: Instance: pampers-en_gb
A5: Date range: All Time
A6: Date field: Review Submission Date
A7: Brand ID | B7: Brand | C7: Product ID | D7: Product Status | E7: Product Name | F7: Description | G7: Product Page URL | H7: Image URL | I7: UPC | J7: EAN | K7: Product Family | L7: Product Family - Expand | M7: # Approved Reviews
A8: PAMPERS | B8: Pampers | C8: 171156441-GB | D8: Active | E8: Pampers® Sensitive™ | F8: Pampers® Sensitive™ | G8: https://www.pampers.co.uk/products/pampers-sensitive | H8: https://images.ctfassets.net/3shtzlb7cz90/48cDtEQSjqSWO1EBQEyMCN/cf1f7b947709171b52bbb7284a7761c4/2146_37_Pampers_UK_Sensitive_Wipes_PDP_MAR24_Cross_sell_1.png | J8: 8001841062792, 8001841041391, 8001841062754, 8006540836194, 8001841062303, 8001841062976, 8001841041421, 8001841041483, 8001841062440, 8001841063188, 8001841062624, 8001841062334, 8001841276151 | M8: 178
A9: PAMPERS | B9: Pampers | C9: 171156443-GB | D9: Inactive | E9: WIPES Pampers Complete Clean Scented | F9: WIPES Pampers Complete Clean Scented | G9: https://www.pampers.co.uk/products/pampers-complete-clean-scented-wipes | H9: https://azcdn.multibrand.pgsitecore.com/en-GB/-/media/Pampers/Pampers-UK/Images/Products/Product-Oasis/Complete-Clean-scented/Complete_Clean_scented_Closed_box_Packshot.png?v=1-201706161100 | J9: 4015400622734, 4015400622840 | M9: 14
A10: PAMPERS | B10: Pampers | C10: PAMPERS_HARMONIE_PANTS | D10: Active | E10: Pampers® Harmonie | F10: Pampers® Harmonie | G10: https://www.pampers.co.uk/products/pampers-harmonie-pants | H10: https://images.ctfassets.net/3shtzlb7cz90/7LSCfrCqciY5v0jaJUyZoZ/55e5d519618be4931290175042750382/Packshot_img_1_324x286.png | J10: 8006540460610, 8006540460672, 8006540460733, 8006540867952, 8006540867990, 8700216235648, 8700216235655, 8700216235693 | M10: 1
A11: PAMPERS | B11: Pampers | C11: PAMPERS_PREMIUM_PROTECTION | D11: Inactive | E11: NAPPIES Pampers Premium Protection | F11: NAPPIES Pampers Premium Protection | G11: https://www.pampers.co.uk/products/pampers-premium-protection-nappies | H11: https://res.cloudinary.com/pmprs/image/upload/c_fill,f_auto/v20191128114838/pampersc1/en-gb/-/media/pampers/pampers-uk/images/products/product-oasis/updated-packshots/premium-protection_150x150.png?v=2-201911281148 | J11: 4015400599456, 4015400835332, 4015400835370, 4015400835448, 4015400835509, 4015400835936, 4015400849193, 4015400849247, 4015400849285, 4015400855293, 4015400855323, 4015400855354, 8001090287861, 8001090287946, 8001090287984, 8001090288011, 8001090299642, 8001090608840, 8001090609380, 8001090609557, 8001090609632, 8001090610058, 8001841201276, 8001841201306 | M11: 435
A12: PAMPERS | B12: Pampers | C12: Harmonie_99percent_Water | D12: Inactive | E12: Pampers® 99% Water Wipe | F12: Pampers® 99% Water Wipe | G12: https://www.pampers.co.uk/products/pampers-aqua-baby-wipes-plastic-free | H12: https://images.ctfassets.net/2ql69mthp94m/D7gwYdv5XHA8GZr9E6zsz/dcf25c494ae1329d60d358e82a567b48/3881_22_Pampers_UK_Wipes_Product_Pages_JAN26_packs_Pure_skin_400x350.png?fm=avif&w=500 | J12: 8006530116558, 8006530116305, 8006530116152, 8006530116374, 8006530116459, 8006530116206 | M12: 56
A13: PAMPERS | B13: Pampers | C13: PAMPERS_NINJAMAS_PYJAMA_PANTS | D13: Active | E13: PAMPERS® NINJAMAS | F13: PAMPERS® NINJAMAS | G13: https://www.pampers.co.uk/products/pampers-ninjamas-pyjama-pants | H13: https://images.ctfassets.net/3shtzlb7cz90/23EKtrYTU7TcncYQWiiBLH/27d1ff67260edc8af63756aea50390c2/2146_10_Pampers_UK_Ninjamas_PDP_JUL23_324x286.png | J13: 8006540630464, 8006540630488, 8006540630518, 8006540630549, 8006540630563, 8006540630587, 8006540630617, 8006540630648, 8700216189583, 8700216189613, 8700216189644, 8700216189651 | M13: 672
A14: PAMPERS | B14: Pampers | C14: PAMPERS_BABY_DRY_TAPE | D14: Active | E14: Pampers® Baby-Dry™ | F14: Pampers® Baby-Dry™ | G14: https://www.pampers.co.uk/products/pampers-baby-dry | H14: https://images.ctfassets.net/3shtzlb7cz90/3FfQbEdwQ4BPcKJAomggsJ/34e9abe6105ad7c099c5d3fcec4809c9/Packshot_img_324x286.png | J14: 4015400542940, 4015400566663, 4015400566700, 4015400566748, 4015400566786, 4015400566823, 4015400566892, 4015400601876, 4015400602149, 4015400689263, 4015400689331, 4015400689454, 4015400689539, 4015400689614, 4015400695677, 4015400695691, 4015400695714, 4015400833444, 4015400833871, 4015400834274, 4015400834410, 4015400834489, 4015400834991, 4015400835035, 4015400835097, 8001090156839, 8001090197672, 8001090197740, 8001090197887, 8001090197917, 8001090268679, 8001090298300, 8001090368553, 8001090368577, 8001090383648, 8001090406507, 8001090672216, 8001090672247, 8001090672285, 8001090672414, 8001090672520, 8001841793085, 8001841793108, 8001841793122, 8001841793146, 8006540697801, 8006540697825, 8006540697849, 8006540697863, 8006540827215, 8006540827277, 8006540827307, 8006540827338, 8006540861691, 8006540861714, 8006540861738, 8006540861752, 8700216036191, 8700216036214, 8700216036245, 8700216036276, 8700216036306, 8700216036344, 8700216036375, 8700216036412, 8700216036436, 8700216458733 | M14: 2208
A15: PAMPERS | B15: Pampers | C15: Sensitive-0-Plastic | D15: Active | E15: Pampers® Sensitive™ 0% Plastic | F15: Pampers® Sensitive™ 0% Plastic | G15: https://www.pampers.co.uk/products/pampers-sensitive-0-plastic | H15: https://images.ctfassets.net/3shtzlb7cz90/blYUTMacSopZ379S4BFYj/836326cdd5a87669e5c80f4c0cb9a87b/2146_47_Pampers_UK_Sensitive_Zero_Plastic_PDP_APR24-Packshot.png | J15: 8006540523056, 8006540523087, 8006540523124 | M15: 3
A16: PAMPERS | B16: Pampers | C16: pampers-kids-hygiene-on-the-go-wipes | D16: Inactive | E16: Pampers® Kids Hygiene on-the-go Wipes | F16: Pampers® Kids Hygiene on-the-go Wipes | G16: https://www.pampers.co.uk/products/pampers-hygiene-wipes | H16: https://images.ctfassets.net/3shtzlb7cz90/01E7PQ50LFBOCyXJ50n8ek/5c09f67196d372683aaacf44869a3c03/KidsHygiene.png | J16: 8006540222089, 8006540222140, 8006540222324 | M16: 158
A17: PAMPERS | B17: Pampers | C17: 171153601-GB | D17: Inactive | E17: New Baby Sensitive | F17: New Baby Sensitive | G17: https://www.pampers.co.uk/star-product/new-baby-sensitive | H17: http://cdn.multibrand.pgsitecore.com/en-GB/-/media/Pampers/Pampers-Master/Images/Products/UK/Regular-Products/Secondary/Pampers-New-Baby-Sensitive-Size-1-Carry-Pack-23-Nappies_4015400611356_630x330.png?v=1-201503020743 | J17: 4015400611356, 4015400635109, 4015400635178, 4015400635215 | M17: 19
A18: PAMPERS | B18: Pampers | C18: PAMPERS_COCONUT_PURE_WIPES | D18: Active | E18: Pampers® Harmonie Protect & Care 0% Plastic | F18: Pampers® Harmonie Protect & Care 0% Plastic | G18: https://www.pampers.co.uk/products/pampers-harmonie-protect-care-plastic-free | H18: https://images.ctfassets.net/3shtzlb7cz90/2wwOup1wCJY9dHF8GJxCty/27a7b0f66349a56ac185851f3995a25e/Image_Background_Remover__1_.png | M18: 31
A19: PAMPERS | B19: Pampers | C19: PAMPERS_NEW_BABY | D19: Active | E19: Pampers® Premium Protection New Baby Wipe | F19: Pampers® Premium Protection New Baby Wipe | G19: https://www.pampers.co.uk/products/pampers-premium-protection-new-baby-wipes | H19: https://images.ctfassets.net/2ql69mthp94m/6mFfqz6dzyUmDfFzmG1Gaz/4bd22dce4ff9bf8b71bd82d14ac59e9f/3881_22_Pampers_UK_Wipes_Product_Pages_JAN26_packs_New_baby_400x350.png?fm=avif&w=500 | J19: 8700216038546, 8001841859088, 8001841794884, 8001841794822, 8006530145985, 8006530145992, 8700216038294, 8001841794761, 8001841794853, 8001841859187, 8006530145947, 8001841794792, 8001841859163, 8006530145893, 8001841859156, 8001841859101, 8006530146067, 8700216038317, 8001841794730, 4015400639015, 8006530145954, 8700216038638 | M19: 1673
A20: PAMPERS | B20: Pampers | C20: 171074149-GB | D20: Inactive | E20: Pampers Kandoo toilet wipes for children | F20: Pampers Kandoo toilet wipes for children | G20: https://www.pampers.co.uk/product/pampers-kandoo-toilet-wipes-for-children | H20: http://cdn.multibrand.pgsitecore.com/en-GB/-/media/Pampers/Pampers-Master/Images/Products/UK/Regular-Products/Secondary/Pampers-Kandoo-Refill-Toilet-Wipes-Melon-50-per-pack-_4015400192381_630x330.png?v=1-201503020743 | M20: 2
A21: PAMPERS | B21: Pampers | C21: Harmonie_Aqua_Baby_Wipes_Plastic_Free | D21: Active | E21: Pampers Harmonie Aqua 0% plastic | F21: Pampers Harmonie Aqua 0% plastic | G21: https://www.pampers.co.uk/products/pampers-aqua-baby-wipes-plastic-free | H21: https://images.ctfassets.net/3shtzlb7cz90/3E0sVXNzipHQLx1yaucyca/cb8d935edecb670c410b59b83cb96836/packshot_img_324x286.png | J21: 8006540458525, 8006540458563, 8006540510247, 8006540556139, 8006540811245, 8006540811276, 8700216722476, 8700216722520 | M21: 443
A22: PAMPERS | B22: Pampers | C22: 171155881-GB | D22: Inactive | E22: Sleep and Play | F22: Sleep and Play | G22: https://www.pampers.co.uk/product/simply-dry | H22: http://cdn.multibrand.pgsitecore.com/en-GB/-/media/Pampers/Pampers-Master/Images/Products/UK/Regular-Products/Secondary/Pampers-Simply-Dry-Size-3-Carry-Pack-30-Nappies_4015400549567_630x330.png?v=1-201608190828 | J22: 4015400549567, 4015400549659, 4015400549680, 4015400549710, 4015400549741, 4015400549772, 4015400549802, 4015400549833, 4015400549864, 4015400549895, 4015400549925, 4015400613879, 4015400613909, 4015400686484, 4015400687030, 4015400687054, 4015400687078, 4015400687092 | M22: 9
A23: PAMPERS | B23: Pampers | C23: PAMPERS_HARMONIE_NEW_BABY_WIPES | D23: Active | E23: Pampers® Harmonie New Baby | F23: Pampers® Harmonie New Baby | G23: https://www.pampers.co.uk/products/pampers-harmonie-new-baby-wipes | H23: https://images.ctfassets.net/3shtzlb7cz90/68D4S68smhj72R6MjTXUoe/44fa600c0aae53a75d5d2fe2897f8d8d/product_page_benefit_2A_mobile_165x165.png | J23: 8006540815762, 8006540815885, 8700216026253 | M23: 80
A24: PAMPERS | B24: Pampers | C24: 171074138-GB | D24: Inactive | E24: Pampers – Underjams (Girls) | F24: Pampers – Underjams (Girls) | G24: https://www.pampers.co.uk/product/pampers-underjams-girls | H24: http://cdn.multibrand.pgsitecore.com/en-GB/-/media/Pampers/Pampers-Master/Images/Products/UK/Regular-Products/Secondary/Pampers-Underjams-Girls-S_630x330.png?v=1-201503020743 | J24: 4015400345053, 4015400345305 | M24: 0
A25: PAMPERS | B25: Pampers | C25: pampers-new-baby-sensitive-wipes | D25: Inactive | E25: Pampers® New Baby Wipes | F25: Pampers® New Baby Wipes | G25: https://www.pampers.co.uk/products/pampers-new-baby-sensitive-wipes | H25: https://images.ctfassets.net/3shtzlb7cz90/3D2HSapq6t3PQZObnuWe4q/a4524a887260d25b84af374298e423d3/NBS__1_.png | J25: 4015400623496, 4015400623663, 4015400670414 | M25: 39
A26: PAMPERS | B26: Pampers | C26: PAMPERS_BABY_DRY_NIGHT_PANTS | D26: Inactive | E26: Pampers® Baby-Dry™ Night Nappy Pants | F26: Pampers® Baby-Dry™ Night Nappy Pants | G26: https://www.pampers.co.uk/products/pampers-baby-dry-night-pants-old | H26: https://images.ctfassets.net/3shtzlb7cz90/6Zw6K7EI7SK5Gf9cbyZQ4a/b05d5e0a0b5872fe44585a9d97ed8de5/2146_4_Pampers_UK_Night_Pants_PDP_JUL23_200x200.png | J26: 8006540234792, 8006540234822, 8006540234853, 8006540291900, 8006540291924, 8006540291948, 8006540416242, 8006540416273, 8006540416303, 8700216039369, 8700216039390, 8700216039406 | M26: 110
A27: PAMPERS | B27: Pampers | C27: 20150226-1-GB | D27: Inactive | E27: WIPES Pampers Sensitive Protect | F27: WIPES Pampers Sensitive Protect | G27: https://www.pampers.co.uk/products/pampers-sensitive-protect-wipes | H27: https://azcdn.multibrand.pgsitecore.com/en-GB/-/media/Pampers/Pampers-UK/Images/Products/Product-Oasis/Pampers-Sensitive-Protect-Wipes/SENSITIVE_PROTECT_IMG_PACK.png?v=1-201706190510 | J27: 4015400621966, 4015400622079, 4015400622222, 4015400622284 | M27: 140
A28: PAMPERS | B28: Pampers | C28: PAMPERS_ACTIVE_FIT_NAPPY_PANTS | D28: Active | E28: Pampers® Premium Protection | F28: Pampers® Premium Protection | G28: https://www.pampers.co.uk/products/pampers-premium-protection-nappy-pants | H28: https://images.ctfassets.net/3shtzlb7cz90/6KS4yvelCPzANmVo1w0Z8Q/12c9811b6f698ca0f8c649af80f749a9/3197_22_Pampers_UK_Product_Pages_Updates_JAN25_PPP_Packshots_324x286.png | J28: 8001090184009, 8001090184047, 8001090184092, 8001841770611, 8001841770642, 8001841770673, 8001841770703, 8001841770734, 8001841770765, 8006540132272, 8006540132296, 8006540132319, 8700216038928, 8700216038935, 8700216038942, 8700216039031, 8700216039062, 8700216039086, 8700216123303, 8700216123341, 8700216705387 | M28: 1221
A29: PAMPERS | B29: Pampers | C29: 171074137-GB | D29: Inactive | E29: Pampers – Underjams (boys) | F29: Pampers – Underjams (boys) | G29: https://www.pampers.co.uk/product/pampers-underjams-boys | H29: http://cdn.multibrand.pgsitecore.com/en-GB/-/media/Pampers/Pampers-Master/Images/Products/UK/Regular-Products/Secondary/Pampers-Underjams-Boys-S_630x330.png?v=1-201503020743 | J29: 4015400345022, 4015400345275 | M29: 1
A30: PAMPERS | B30: Pampers | C30: 171156442-GB | D30: Inactive | E30: WIPES Pampers Complete Clean Unscented | F30: WIPES Pampers Complete Clean Unscented | G30: https://www.pampers.co.uk/products/pampers-complete-clean-unscented-wipes | H30: https://azcdn.multibrand.pgsitecore.com/en-GB/-/media/Pampers/Pampers-UK/Images/Products/Product-Oasis/Complete-Clean-Unscented/Complete-clean-unscented-closed-box-packshot.png?v=1-201706161059 | J30: 4015400622413, 4015400622482 | M30: 5
A31: PAMPERS | B31: Pampers | C31: PAMPERS_BABY_DRY_PANTS | D31: Active | E31: Pampers® Baby-Dry™ | F31: Pampers® Baby-Dry™ | G31: https://www.pampers.co.uk/products/pampers-baby-dry-pants | H31: https://images.ctfassets.net/3shtzlb7cz90/2GxAU0eNZc4rux9YdC8VAb/f5216ff65b6353e0c57b7b8a20e6f2f7/2146_44_Pampers_UK_Baby_Dry_Pants_PDP_APR24-BDYP-324x286.png | J31: 4015400744887, 4015400744917, 4015400744948, 4015400749608, 4015400749646, 4015400841043, 4015400841524, 4015400841593, 8001090706485, 8001090706577, 8001090706645, 8001090706713, 8001090706850, 8001090706898, 8001090706935, 8001090924759, 8001090967961, 8001090968029, 8001090968081, 8001841072562, 8001841072722, 8001841072760, 8001841072999, 8001841073149, 8001841103365, 8001841122854, 8001841122885, 8001841129075, 8001841129099, 8001841159430, 8001841159461, 8001841159492, 8001841159522, 8001841159553, 8001841159584, 8001841159614, 8001841159652, 8001841159676, 8001841159706, 8001841793337, 8001841793368, 8001841793399, 8006540002452, 8006540002483, 8006540002513, 8006540337417, 8006540450451, 8006540450482, 8006540450512, 8006540463383, 8006540710876, 8006540711248, 8006540711767, 8006540825297, 8006540825327, 8700216039116, 8700216039161, 8700216039192, 8700216039222, 8700216039246, 8700216039260, 8700216039284, 8700216039314, 8700216039338, 8700216039345, 8700216455787, 8700216455794, 8700216455817, 8700216705226, 8700216705257, 8700216705264, 8700216705318 | M31: 1543
A32: PAMPERS | B32: Pampers | C32: PAMPERS_FRESH_CLEAN_PLASTIC_FREE | D32: Inactive | E32: Pampers® Fresh Clean 0% Plastic Wipe | F32: Pampers® Fresh Clean 0% Plastic Wipe | G32: https://www.pampers.co.uk/products/pampers-fresh-clean-plastic-free-baby-wipes | H32: https://images.ctfassets.net/2ql69mthp94m/DQNSPkrMy14kCeTQl0CTf/261aa691b6d04f318708f440ebdef687/3881_22_Pampers_UK_Wipes_Product_Pages_JAN26_packs_Fresh_clean_V2_400x350.png?fm=avif&w=500 | J32: 8006530098366, 8006530098403, 8006530098441 | M32: 64
A33: PAMPERS | B33: Pampers | C33: PAMPERS_SENSITIVE_PLASTIC_FREE | D33: Inactive | E33: Pampers® Sensitive™ 0% Plastic | F33: Pampers® Sensitive™ 0% Plastic | G33: https://www.pampers.co.uk/products/pampers-sensitive-0-plastic | H33: https://images.ctfassets.net/3shtzlb7cz90/blYUTMacSopZ379S4BFYj/836326cdd5a87669e5c80f4c0cb9a87b/2146_47_Pampers_UK_Sensitive_Zero_Plastic_PDP_APR24-Packshot.png | J33: 8006540523056, 8006540523100, 8006540523124, 8700216783491 | M33: 36
A34: PAMPERS_UK | B34: Pampers | C34: 171074136-GB | D34: Inactive | E34: Pampers Easy Up Pants | F34: Pampers Easy Up Pants | J34: 4015400535942, 4015400535973, 4015400536000, 4015400536031, 4015400536062, 4015400536239, 4015400536253, 4015400605232, 4015400605256 | M34: 0
A35: PAMPERS_UK | B35: Pampers | C35: Aqua_Pure_Wipes | D35: Inactive | E35: Pampers® Aqua Pure™ | F35: Pampers® Aqua Pure™ | G35: https://www.pampers.co.uk/products/pampers-aqua-pure-wipes | H35: https://images.ctfassets.net/3shtzlb7cz90/7K9ioh7Kn65yUDoGPRQfOm/6af2ad8a93078f6e4ffb80277bb5b7a4/Pampers-Aqua-Pure-280x195.png | J35: 8001090603296, 8001090603326, 8001090603388, 8001090603470, 8001090603500, 8001090603562, 8001090603609, 8001090603623, 8001090603661 | M35: 433
A36: PAMPERS_UK | B36: Pampers | C36: 20150226-GB | D36: Inactive | E36: Pampers Sensitive Baby Wipes Perfume Free | F36: Pampers Sensitive Baby Wipes Perfume Free | J36: 4015400621966, 4015400622079, 4015400622116, 4015400622284, 4015400630791, 4015400670414 | M36: 0
A37: pampers-en_gb | B37: PAMPERS | C37: Pure_Protection_Nappies | D37: Active | E37: Pampers® Harmonie | F37: Pampers® Harmonie | G37: https://www.pampers.co.uk/products/pampers-harmonie-nappies | H37: https://images.ctfassets.net/3shtzlb7cz90/75smodrmOcXB8T6YTP4Env/6dff3465f7ce8ba7d33fd95e2f3e6d96/2146_59_Pampers_UK_Harmonie_Pants_Packshot_Update_JUN24_harmonie__1_.png | J37: 8006540867921, 8006540156599, 8700216251716, 8006540156476, 8001841023120, 8006540156353, 8001841115979, 8001090834904, 8700216251792, 8700216251259, 8700216251235, 8700216251754, 8001090834843, 8006540156414, 8006540156636, 8001090834720, 8001841115917, 8006540156674, 8700216251679, 8001090834966, 8006540156551, 8001090834782, 8001841116037, 8001090971982, 8006540867808, 8006540867891, 8006540156384, 8001090972026, 8700216251686, 8006540156155, 8006540156445 | M37: 680
A38: pampers-en_gb | B38: PAMPERS | C38: PAMPER_ACTIVE_FIT | D38: Active | E38: Pampers® Active Fit | F38: Pampers® Active Fit | G38: https://www.pampers.co.uk/products/pampers-active-fit-nappies | H38: https://images.ctfassets.net/3shtzlb7cz90/4f996eb73e5afe297516099754e8dd5a27fffbae1ebb29bd5321bc0afb1d984c/5680a8575dcb1402507d6cf4e43e4d73/PROJ024724-P_G-Pampers-Standard-Packshot-4-324x286-v0.01.png | J38: 8001841808499, 8001841808550, 8001841808611, 8001841808680, 8001841808741, 8001841808772, 8001841808833, 8001841808901, 8001841809038, 8001841809052, 8001841809076, 8700216038379, 8700216038393, 8700216038416, 8700216038560, 8700216038591, 8700216038607 | M38: 2724
A39: pampers-en_gb | B39: PAMPERS | C39: PAMPERS_SPLASHERS | D39: Active | E39: Pampers® Splashers Baby Shark™ | F39: Pampers® Splashers Baby Shark™ | G39: https://www.pampers.co.uk/products/pampers-splashers | H39: https://images.ctfassets.net/3shtzlb7cz90/1YjQuCWgqXJdxahUSr90Rj/08af74edfad5a09b25152a98ff937f25/1026_63_Pampers_FR_Splashers_UpdatePDP_MAR23_324x286.png | J39: 8001090698346, 8001090698384, 8001090728951 | M39: 24
A40: pampers-en_gb | B40: PAMPERS | C40: PAMPERS_FRESH_CLEAN | D40: Active | E40: Pampers® Fresh Clean | F40: Pampers® Fresh Clean | G40: https://www.pampers.co.uk/products/pampers-fresh-clean | H40: https://images.ctfassets.net/3shtzlb7cz90/6RDoT3S9z87DOK2OK6O73U/9dd86e111337904dd346100567ab0149/2146_38_Pampers_UK_Fresh_Clean_Wipes_PDP_MAR24_benefit2A_mobile_165x165.png | J40: 8001841077789, 8001841077598, 8001841078052, 8001841276007, 8001841078137, 8001841078441, 8001841077949, 8001841078496, 8001841041360 | M40: 82
C41: 2-UK | D41: Inactive | M41: 0
C42: 171074134-GB | D42: Inactive | M42: 0
C43: 171074135-GB | D43: Inactive | M43: 0
C44: PAMPERS_PREMIUM_PROTECTION_NEW_BABY_WIPES | D44: Inactive | M44: 57
C45: 241044174 | D45: Inactive | M45: 2

Sheet pampers-en_us
A1: Bazaarvoice
A2: Pampers-EN_US R&R Key Metrics
A3: Run Date: Aug 12, 2026 12:00 AM UTC
A4: Instance: pampers
A5: Date range: All Time
A6: Date field: Review Submission Date
A7: Brand ID | B7: Brand | C7: Product ID | D7: Product Status | E7: Product Name | F7: Description | G7: Product Page URL | H7: Image URL | I7: UPC | J7: EAN | K7: Product Family | L7: Product Family - Expand | M7: # Approved Reviews
A8: 16n8p5scqgr7lpve64m2tvx8c | B8: Pampers | C8: 037000275046 | D8: Inactive | E8: Pampers Pure Hybrid Starter Kit | F8: Pampers Pure Protection Hybrid Cloth Diaper Starter Kit - 3 Reusable Covers + 25 Disposable Inserts | H8: https://target.scene7.com/is/image/Target/GUEST_9740c937-0d2b-42fa-8462-c6595948f112?fmt=webp&wid=1400&qlt=80 | I8: 037000275046 | M8: 116
A9: 16n8p5scqgr7lpve64m2tvx8c | B9: Pampers | C9: 10900806 | D9: Inactive | E9: Easy Ups Trainers for Girls | F9: <li>Helps potty training make sense during the day and protects against leaks at night</li> <li>Training pants designed for toddlers or preschoolers ready for potty training (18+ months old)</li> <li>The Feel 'n Learn&reg; Liner helps your little girl feel when she's wet, so she can learn to stay dry</li> | G9: http://www.pampers.com/potty-training-girls-easy-ups | H9: https://www.pampers.com/en_US/images/pc/hb/products/prod_img_pampers_easy_ups_girls_NA.jpg | I9: 037000066989, 037000067634, 037000067726 | M9: 22
A10: 16n8p5scqgr7lpve64m2tvx8c | B10: Pampers | C10: 900815 | D10: Inactive | E10: Pampers® SoftCare Unscented Wipes | F10: <li>SoftCare unscented baby wipes are made with pure water</li> <li>Lotion with natural aloe & vitamin E</li> <li>SoftCare baby wipes have thousands of soft cleansing buds</li> <li>Cleans gently like a baby’s washcloth</li> <li>Hypoallergenic</li> | G10: http://www.pampers.com/softcare-unscented-wipes | H10: https://www.pampers.com/en_US/images/pc/hb/products/prod_img_wipes_softcare_unscented_NA.jpg | I10: 037000061618 | M10: 3
A11: 16n8p5scqgr7lpve64m2tvx8c | B11: Pampers | C11: 10900805 | D11: Inactive | E11: Easy Ups Trainers for Boys | F11: <li>Helps potty training make sense during the day and protects against leaks at night</li> <li>Training pants designed for toddlers or preschoolers ready for potty training (18+ months old)</li> <li>The Feel 'n Learn&reg; Liner helps your little boy feel when he's wet, so he can learn to stay dry</li> | G11: http://www.pampers.com/potty-training-boys-easy-ups | H11: https://www.pampers.com/en_US/images/pc/hb/products/prod_img_pampers_easy_ups_boys_NA.jpg | I11: 037000067559, 037000067702, 037000067795 | M11: 37
A12: 16n8p5scqgr7lpve64m2tvx8c | B12: Pampers | C12: 900804 | D12: Inactive | E12: Baby Dry Diapers | F12: <li>Extra flexible tabs expand and contract with your baby</li> <li>UltraAbsorb Core&trade; Outstanding overnight absorbance</li> <li>Comfortable contoured fit</li> | G12: http://www.pampers.com/baby-diaper-baby-dry | H12: https://www.pampers.com/en_US/images/pc/hb/products/prdt_116x128_babydry.gif | I12: 037000066859, 037000067450, 037000067511, 037000312901, 037000452157, 037000601487 | M12: 0
A13: 16n8p5scqgr7lpve64m2tvx8c | B13: Pampers | C13: 900826 | D13: Inactive | E13: Pampers® Swaddlers diapers | F13: <li>Color-changing Wetness Indicator (size NB, 1 and 2)</li> <li>The #1 choice of hospitals (based on sales data)</li> <li>Quilted blanket-like softness wraps babies in comfort and security</li> <li>Soft stretchy sides and overlapping fasteners give infants a flexible fit</li> <li>Umbilical cord notch (size NB only)</li> | G13: http://www.pampers.com/new-baby-diapers-swaddlers | H13: https://www.pampers.com/en_US/images/pc/hb/products/prod_img_diapers_swaddlers_NA.jpg | I13: 037000285199, 037000285229, 037000285397, 037000285502, 037000348955, 037000397984 | M13: 1
A14: 16n8p5scqgr7lpve64m2tvx8c | B14: Pampers | C14: 761042387 | D14: Inactive | E14: Kandoo Flushable Toilet Wipes | F14: <li>Cleans up to 30% better than toilet paper</li> <li>Perfect fit for little hands- about the size of two pieces of toilet paper</li> <li>Available in a variety of scents, including Smellin' Melon, Magic Melon, Funny Berry, and Sensitive</li> | G14: http://www.pampers.com/flushable-wipes-kandoo | H14: https://www.pampers.com/en_US/images/pc/hb/lsp/products/prod_image_wipes_kandoo.png | I14: 037000041757, 037000048770, 037000159186, 037000449904 | M14: 807
A15: 16n8p5scqgr7lpve64m2tvx8c | B15: Pampers | C15: 900807 | D15: Inactive | E15: Pampers® Sensitive Baby Wipes | F15: <li>Pampers Sensitive baby wipes have PureCare lotion which conditions baby’s skin</li> <li>Pampers Sensitive wipes are dermatologist tested</li> <li>Hypoallergenic and Perfume Free</li> <li>#1 baby wipe of hospitals (based on sales data)</li> <li>Clinically proven mild baby wipes for your baby’s skin</li> | G15: http://www.pampers.com/pampers-sensitive-baby-wipes | H15: https://www.pampers.com/en_US/images/pc/hb/products/prod_img_wipes_sensitive_NA.jpg | I15: 037000436904 | M15: 1
A16: 16n8p5scqgr7lpve64m2tvx8c | B16: Pampers | C16: Pampers_Clean_&_Calm | D16: Active | E16: Pampers® Clean & Calm™ | F16: Pampers® Clean & Calm™ Cotton Blossom Scent | G16: https://www.pampers.com/en-us/products/pampers-clean-and-calm-wipes | H16: https://sampling2-product-images-prod.s3.amazonaws.com/bvsampling/Pampers-Pampers_Clean_and_Calm.png?t=1741790457602 | I16: 030772204313, 030772204320, 030772204344, 030772204368 | M16: 1124
A17: 16n8p5scqgr7lpve64m2tvx8c | B17: Pampers | C17: 900803 | D17: Inactive | G17: http://www.pampers.com/pampers-cruisers | H17: https://www.pampers.com/en_US/images/pc/hb/products/prod_img_pampers_cruisers_NA.jpg | I17: 037000063964, 037000064008, 037000064039, 037000064060, 037000119104 | M17: 141
A18: 16n8p5scqgr7lpve64m2tvx8c | B18: Pampers | C18: 900821 | D18: Inactive | E18: Bibsters | G18: http://stage.pampers.com/en_US/proddetail/baby-products/baby-bibs-bibsters/id/900821 | H18: https://stage.pampers.com/en_US/products/new_layout/images/Nprdt_bibster.gif | I18: 037000401803 | M18: 5
A19: 16n8p5scqgr7lpve64m2tvx8c | B19: Pampers | C19: 10900826 | D19: Inactive | E19: Pampers® Swaddlers diapers | F19: <li>Color-changing Wetness Indicator (size NB, 1 and 2)</li> <li>The #1 choice of hospitals (based on sales data)</li> <li>Quilted blanket-like softness wraps babies in comfort and security</li> <li>Soft stretchy sides and overlapping fasteners give infants a flexible fit</li> <li>Umbilical cord notch (size NB only)</li> | G19: http://www.pampers.com/new-baby-diapers-swaddlers | H19: https://www.pampers.com/en_US/images/pc/hb/products/prod_img_diapers_swaddlers_NA.jpg | I19: 037000285199, 037000285229, 037000285397, 037000285502, 037000348955, 037000397984 | M19: 276
A20: 16n8p5scqgr7lpve64m2tvx8c | B20: Pampers | C20: 80335332 | D20: Inactive | E20: Expressions Wipes | F20: Baby Wipe | H20: https://sampling-photos-prod.s3.amazonaws.com/photos/4d1c690d414dfd615901088bb360aba5_image_%2823%29.jpg | I20: 037000579939 | M20: 49
A21: 16n8p5scqgr7lpve64m2tvx8c | B21: Pampers | C21: 10900802 | D21: Inactive | E21: Pampers® Swaddlers Sensitive diapers | F21: <li>Gentle and hypoallergenic</li> <li>Made with a touch of aloe</li> <li>Ultra breathability</li> <li>Color-changing Wetness Indicator (size NB, 1, 2)</li> <li>Umbilical cord notch (size NB only)</li> | G21: http://www.pampers.com/swaddlers-sensitive-diapers | H21: https://www.pampers.com/en_US/images/pc/hb/products/prod_img_diapers_swaddlers_sensitive_NA.jpg | I21: 037000172311, 037000172406, 037000172468 | M21: 87
A22: 16n8p5scqgr7lpve64m2tvx8c | B22: Pampers | C22: 900801 | D22: Inactive | G22: http://www.pampers.com/new-baby-diapers-swaddlers | H22: https://www.pampers.com/en_US/images/pc/hb/products/prod_img_diapers_swaddlers_NA.jpg | I22: 037000063902, 037000063919, 037000071082, 037000119210, 037000348955, 037000397984 | M22: 44
A23: 16n8p5scqgr7lpve64m2tvx8c | B23: Pampers | C23: 10900829 | D23: Inactive | E23: Pampers® ThickCare Unscented Wipes | F23: <li>Pampers ThickCare baby wipes are hypoallergenic</li> <li>Over 50% stronger than Huggies Natural Care®*</li> <li>ThickCare baby wipes have a thick, quilted texture</li> <li>Unscented</li> <li>Cleans like a washcloth</li> <br> *Huggies Natural Care is a registered trademark of Kimberly-Clark Worldwide, Inc. | G23: http://www.pampers.com/thickcare-unscented-wipes | H23: https://www.pampers.com/en_US/images/pc/hb/products/prod_img_wipes_pampers_thickcare_unscented_NA.jpg | I23: 037000298885 | M23: 58
A24: 16n8p5scqgr7lpve64m2tvx8c | B24: Pampers | C24: 900809 | D24: Inactive | E24: Clean 'n Go Wipes | F24: <li>Helps wipe away dirt and germs from head to toe</li> <li>Dermatologically tested</li> <li>Tear-free</li> | G24: http://stage.pampers.com/en_US/proddetail/baby-products/wipes-clean-and-go/id/900809 | H24: https://stage.pampers.com/en_US/products/new_layout/images/Nprdt_cleanngo1.gif | I24: 037000121244 | M24: 22
A25: 16n8p5scqgr7lpve64m2tvx8c | B25: Pampers | C25: 900829 | D25: Inactive | E25: Pampers® ThickCare Unscented Wipes | F25: <li>Pampers ThickCare baby wipes are hypoallergenic</li> <li>Over 50% stronger than Huggies Natural Care®*</li> <li>ThickCare baby wipes have a thick, quilted texture</li> <li>Unscented</li> <li>Cleans like a washcloth</li> <br> *Huggies Natural Care is a registered trademark of Kimberly-Clark Worldwide, Inc. | G25: http://www.pampers.com/thickcare-unscented-wipes | H25: https://www.pampers.com/en_US/images/pc/hb/products/prod_img_wipes_pampers_thickcare_unscented_NA.jpg | I25: 037000298885 | M25: 8
A26: 16n8p5scqgr7lpve64m2tvx8c | B26: Pampers | C26: 900812 | D26: Inactive | E26: Calming Lavender Wipes | F26: <li>Comforting lavender scent helps calm your baby</li> <li>Thousands of soft cleansing buds leave your baby's skin feeling perfectly clean</li> <li>Made with pure water</li> | G26: http://stage.pampers.com/en_US/proddetail/baby-products/pampers-baby-wipes-calming-lavender/id/900812 | H26: https://stage.pampers.com/en_US/products/new_layout/images/Nprdt_lavender.gif | I26: 037000060673 | M26: 3
A27: 16n8p5scqgr7lpve64m2tvx8c | B27: Pampers | C27: 10900827 | D27: Inactive | E27: Pampers® Cruisers diapers | F27: <li>3-Way Fit gives babies our best fit ever so they have the freedom to play their way</li> <li>Pampers Cruisers diapers offer up to 12 hours of leakage protection</li> <li>Now with the quilted softness of Swaddlers</li> <li>New Sesame Street graphics feature your favorite characters on every diaper</li> | G27: http://www.pampers.com/pampers-cruisers | H27: https://www.pampers.com/en_US/images/pc/hb/products/prod_img_pampers_cruisers_NA.jpg | I27: 037000262640, 037000278481, 037000278740, 037000279402, 037000279525 | M27: 394
A28: 16n8p5scqgr7lpve64m2tvx8c | B28: Pampers | C28: 900808 | D28: Inactive | E28: Swipers Wipes | F28: <li>Up to 20% thicker than regular Pampers Wipes</li> <li>Washcloth Weave texture for more durability over the leading brand</li> <li>Lightly scented</li> | G28: http://stage.pampers.com/en_US/proddetail/baby-products/pampers-wipes-swipers/id/900808 | H28: https://stage.pampers.com/en_US/products/new_layout/images/Nprdt1_swiper1.gif | I28: 037000119722 | M28: 4
A29: 16n8p5scqgr7lpve64m2tvx8c | B29: Pampers | C29: 761054761 | D29: Inactive | E29: Pampers® Cruisers USA Prints | F29: <li>New Limited Edition USA Prints</li> <li>3-Way Fit gives babies the freedom to play their way</li> <li>Up to 12 hours of leakage protection</li> | G29: http://www.pampers.com/pampers-cruisers-usa-prints | H29: https://www.pampers.com/en_US/images/pc/hb/lsp/products/prod_img_diapers_cruiser_usa_NA.jpg | I29: 037000830122, 037000830139, 037000830146 | M29: 17
A30: 16n8p5scqgr7lpve64m2tvx8c | B30: Pampers | C30: 10900814 | D30: Inactive | E30: Pampers SoftCare Baby Fresh Wipes | F30: <li>SoftCare baby wipes clean gently like a baby’s washcloth</li> <li>Made with pure water and lotion with vitamin E</li> <li>Pampers SoftCare baby wipes are hypoallergenic </li> <li>Pleasant baby powder scent</li> <li>Thousands of soft cleansing buds to help leave baby’s skin feeling perfectly clean</li> | G30: http://www.pampers.com/softcare-baby-fresh-wipes | H30: https://www.pampers.com/en_US/images/pc/hb/products/prod_img_wipes_babyfresh_NA.jpg | I30: 037000060826 | M30: 13
A31: 16n8p5scqgr7lpve64m2tvx8c | B31: Pampers | C31: 900828 | D31: Inactive | E31: Pampers Limited Edition Prints Diapers for Boys and Girls | F31: <li>Two fun designs in every box: argyle and cars for boys, flowers and polka dots for girls</li> <li>Same absorbency and fit you've come to love with Pampers diapers</li> <li>Super-Stretchy sides for flexible fit</li> <li>Fun diapers that make great baby shower gifts</li> | G31: http://stage.pampers.com/en_US/proddetail/baby-products/pampers-prints-diapers/id/900828 | H31: https://stage.pampers.com/en_US/products/new_layout/images/Nprd_print_new.gif | I31: 037000500964, 037000500971, 037000501022, 037000501053, 037000503354, 037000503361 | M31: 169
A32: 16n8p5scqgr7lpve64m2tvx8c | B32: Pampers | C32: 930825 | D32: Inactive | E32: Pampers® Sensitive ThickCare Baby Wipes | F32: <li>Pampers Sensitive ThickCare wipes have PureCare lotion to condition baby’s skin</li> <li>Sensitive ThickCare baby wipes are dermatologist tested & hypoallergenic</li> <li>Clinically proven mild & perfume-free</li> <li>Thicker* to lift away mess from the skin (*vs. Pampers SoftCare™)</li> <li>Made with pure water</li> | G32: http://www.pampers.com/pampers-sensitive-thickcare-wipes | H32: https://www.pampers.com/en_US/images/pc/hb/products/prod_img_wipes_pampers_thickcare_sensitive_NA.jpg | I32: 037000229476 | M32: 5
A33: 16n8p5scqgr7lpve64m2tvx8c | B33: Pampers | C33: 900832 | D33: Inactive | E33: Pampers ThickCare Touch of Chamomile Wipes | F33: <li>Pampers ThickCare baby wipes are hypoallergenic</li> <li>Lightly scented</li> <li>ThickCare baby wipes are over 50% stronger than Huggies Natural Care*</li> <li>Thick, quilted texture</li> <li>Cleans like a washcloth</li> | G33: http://www.pampers.com/thickcare-touch-of-chamomile-wipes | H33: https://www.pampers.com/en_US/images/pc/hb/products/prod_img_wipes_pampers_thickcare_chamomile_NA.jpg | I33: 037000298854 | M33: 5
A34: 16n8p5scqgr7lpve64m2tvx8c | B34: Pampers | C34: 10930825 | D34: Inactive | E34: Pampers® Sensitive ThickCare Baby Wipes | F34: <li>Pampers Sensitive ThickCare wipes have PureCare lotion to condition baby’s skin</li> <li>Sensitive ThickCare baby wipes are dermatologist tested & hypoallergenic</li> <li>Clinically proven mild & perfume-free</li> <li>Thicker* to lift away mess from the skin (*vs. Pampers SoftCare™)</li> <li>Made with pure water</li> | G34: http://www.pampers.com/pampers-sensitive-thickcare-wipes | H34: https://www.pampers.com/en_US/images/pc/hb/products/prod_img_wipes_pampers_thickcare_sensitive_NA.jpg | I34: 037000229476 | M34: 21
A35: 16n8p5scqgr7lpve64m2tvx8c | B35: Pampers | C35: 900820 | D35: Inactive | E35: Pocket Bibsters | G35: http://stage.pampers.com/en_US/proddetail/baby-products/pocket-bibs-bibsters/id/900820 | H35: https://stage.pampers.com/en_US/products/new_layout/images/Nprdt_bibster_pock.gif | I35: 037000357919 | M35: 5
A36: 16n8p5scqgr7lpve64m2tvx8c | B36: Pampers | C36: 900802 | D36: Inactive | E36: Pampers® Swaddlers Sensitive diapers | F36: <li>Gentle and hypoallergenic</li> <li>Made with a touch of aloe</li> <li>Ultra breathability</li> <li>Color-changing Wetness Indicator (size NB, 1, 2)</li> <li>Umbilical cord notch (size NB only)</li> | G36: http://www.pampers.com/swaddlers-sensitive-diapers | H36: https://www.pampers.com/en_US/images/pc/hb/products/prod_img_diapers_swaddlers_sensitive_NA.jpg | I36: 037000172311, 037000172406, 037000172468 | M36: 0
A37: 16n8p5scqgr7lpve64m2tvx8c | B37: Pampers | C37: 10900807 | D37: Inactive | E37: Pampers® Sensitive Baby Wipes | F37: <li>Pampers Sensitive baby wipes have PureCare lotion which conditions baby’s skin</li> <li>Pampers Sensitive wipes are dermatologist tested</li> <li>Hypoallergenic and Perfume Free</li> <li>#1 baby wipe of hospitals (based on sales data)</li> <li>Clinically proven mild baby wipes for your baby’s skin</li> | G37: http://www.pampers.com/pampers-sensitive-baby-wipes | H37: https://www.pampers.com/en_US/images/pc/hb/products/prod_img_wipes_sensitive_NA.jpg | I37: 037000436904 | M37: 38
A38: 16n8p5scqgr7lpve64m2tvx8c | B38: Pampers | C38: 10900815 | D38: Inactive | E38: Pampers® SoftCare Unscented Wipes | F38: <li>SoftCare unscented baby wipes are made with pure water</li> <li>Lotion with natural aloe & vitamin E</li> <li>SoftCare baby wipes have thousands of soft cleansing buds</li> <li>Cleans gently like a baby’s washcloth</li> <li>Hypoallergenic</li> | G38: http://www.pampers.com/softcare-unscented-wipes | H38: https://www.pampers.com/en_US/images/pc/hb/products/prod_img_wipes_softcare_unscented_NA.jpg | I38: 037000061618 | M38: 8
A39: 16n8p5scqgr7lpve64m2tvx8c | B39: Pampers | C39: 761044192 | D39: Inactive | E39: Kandoo Handsoap, Body Wash and Shampoo | G39: http://www.pampers.com/hand-soap-for-kids-kandoo | H39: https://www.pampers.com/en_US/images/pc/hb/lsp/products/prod_img_more_kandoo_soap_NA.jpg | I39: 037000002116, 037000002123, 037000002130, 037000002178, 037000008002, 037000065883 | M39: 542
A40: Lumi | B40: LUMI | C40: Pampers_SSC_SmartSleepCoachSubscription | D40: Inactive | E40: Smart Sleep Coach | F40: Your plan is ready and waiting to guide you step by step to sleep success. Get access today: | G40: https://www.lumibypampers.com/pricing | M40: 41
A41: Lumi | B41: LUMI | C41: E00000001 | D41: Inactive | E41: Smart Baby Monitor + Sleep System | F41: A better night’s sleep for the whole family. Combine the Smart Sleep System with the award-winning Smart Baby Monitor and peaceful nights become more than just a dream. | G41: https://www.pampers.com/en-us/lumi/smart-baby-monitor-sleep-kit-bundle | H41: https://res.cloudinary.com/pmprs/image/upload/c_scale,dpr_1.0,f_auto,q_auto/v20210120122830/pampersc3/en-us/-/media/pampers/estore-us/images/fullkit-image/pdp/nov/bundle_mustardbg.png?v=2-202101201228 | I41: 020800924320, 020800924344, 020800924368, 020800924382, 020800924405, 020800924429, 037000641612 | M41: 94
A42: Lumi | B42: LUMI | C42: E000000011 | D42: Inactive | E42: Smart Baby Monitor | F42: Designed with Logitech, a leader in smart monitoring systems. Never miss a moment with crystal clear HD resolution day or night, ultra-wide 180° view, 2-way and continuous background audio, and temperature and humidity tracking. | G42: https://www.pampers.com/en-us/lumi/smart-baby-monitor | H42: https://res.cloudinary.com/pmprs/image/upload/c_scale,dpr_1.0,f_auto,q_auto/v20201113061747/pampersc3/en-us/-/media/pampers/estore-us/images/fullkit-image/pdp/nov/monitor_tealbg.png?v=1-202011130617 | I42: 037000802372, 037000965190 | M42: 73
A43: PAMPERS | B43: Pampers | C43: Pampers_Pure_Hybrid_StarterKit | D43: Inactive | E43: Pampers® Pure Hybrid Starter Kit | F43: Pampers® Pure Hybrid Starter Kit | G43: https://www.pampers.com/en-us/diapers-wipes/pampers-pure-protection-diapers-hybrid | H43: https://images.ctfassets.net/9wtva4vhlgxb/5deQNd9L7lSksuM3U7CYg3/38cb19a953e352777874d7c35f4e8eaf/PureHybrid_280x195.png | I43: 037000275046, 037000275084, 037000275435, 037000275459, 037000275497, 037000275565, 037000275848, 037000276067, 037000276142, 037000276159, 037000276166, 037000276371 | M43: 147
A44: PAMPERS | B44: Pampers | C44: 761057122 | D44: Inactive | E44: Pampers® Complete Clean™ Unscented | F44: Pampers® Complete Clean™ Unscented | G44: https://www.pampers.com/en-us/diapers-wipes/pampers-fragrance-free-wipes | H44: https://images.ctfassets.net/9wtva4vhlgxb/3NAv0tzwSGHcZv3L81qg45/1a137a754cd35f0e39cf96d56874c049/cc_unscented_324x286.png | I44: 037000507246, 037000754619, 037000754671, 037000755227, 037000755234, 037000755241, 037000755258, 037000755326, 037000755333, 037000755340, 037000755357, 037000760207, 037000792963, 037000792994, 037000793199, 037000799474 | M44: 2677
A45: PAMPERS | B45: Pampers | C45: Pampers_Free_and_Gentle | D45: Active | E45: Pampers® Free & Gentle™ | F45: Pampers® Free & Gentle™ | G45: https://www.pampers.com/en-us/products/pampers-free-and-gentle-wipes | H45: https://images.ctfassets.net/9wtva4vhlgxb/7tEtA6OaT6giQexbATglgK/11958ea591652cb906d8aef2c2e9e46b/06.png | I45: 030772104286, 030772104293, 030772104309, 030772104316, 030772104323, 030772104330, 030772104347, 030772204337 | M45: 1345
A46: PAMPERS | B46: Pampers | C46: 037000275497 | D46: Inactive | E46: Pampers Pure Hybrid Overnight Disposable Inserts | F46: Pampers Pure Protection Hybrid Cloth Diaper Overnight Disposable Inserts 52ct | H46: https://sampling-photos-prod.s3.amazonaws.com/photos/4a9d4bec7f58242ef3006fae82e731d6_PAMP_PURE_HYB_NT_INSRT_ENORM_TGT_00037000275565_C1C1.jpeg | I46: 037000275497, 037000275565 | K46: pampers_pure_hybrid | L46: BV_WB_FAMILY:pampers_pure_hybrid | M46: 170
A47: PAMPERS | B47: Pampers | C47: pampers_swaddlers_overnights | D47: Active | E47: Pampers® Swaddlers Overnights™ | F47: Pampers® Swaddlers Overnights™ | G47: https://www.pampers.com/en-us/products/pampers-swaddlers-overnights | H47: https://images.ctfassets.net/9wtva4vhlgxb/6LrP3P8XkaIWRYbFtCIGBg/38b83808a180df9642d9174807bb07ca/05.png | I47: 037000833963, 037000833970, 037000833987, 037000834021 | M47: 62
A48: PAMPERS | B48: Pampers | C48: 761042423 | D48: Inactive | E48: Pampers Easy Ups Training Underwear for Girls | F48: Pampers Easy Ups Training Underwear for Girls | G48: https://www.pampers.com/en-us/diapers-wipes/pampers-easy-ups-trainers-for-girls | H48: http://cdn.multibrand3.pgsitecore.com/en-US/-/media/Pampers/Pampers-US/Images/Products/D1C1_NA_GFTSRWRD_GIRLS_424x355hk.jpg?h=355&w=424&v=1-201707131328&hash=B1D982358DB1A9FFB1C389A4D96794C82358A6E2&crop=1&sc=0 | I48: 037000233145, 037000265832, 037000265856, 037000265870, 037000820000, 037000820024, 037000820116, 037000827498, 037000827511, 037000827535, 037000959915, 037000959991, 037000960010, 037000960034, 037000960058, 037000960072, 037000960096, 037000969167, 037000969181, 037000969204 | M48: 2770
A49: PAMPERS | B49: Pampers | C49: Pampers_AMORE | D49: Active | E49: Pampers AMORE | F49: Pampers AMORE is Pampers’ best diaper yet. Thoughtfully crafted with 60+ years of Pampers quality and expertise, reimagined for today. Built with 5 layers of protection, it is our most absorbent diaper. Pampers AMORE provides premium performance without compromise. They are Dermatologically accredited by the Skin Health Alliance and tested for 1000+ harmful chemicals. They are hypoallergenic and free of fragrance, parabens, elemental chlorine and latex (no natural rubber). They are crafted with the finest materials, making them soft as cashmere and gentle on your baby’s skin. Each diaper also features delicate patterns as cute as your little one. Pampers AMORE diapers are made with love in every detail. | G49: https://www.pampers.com/en-us/product/amore | H49: https://sampling2-product-images-prod.s3.amazonaws.com/bvsampling/Amore-En_US-Pampers_AMORE.png?t=1766183882253 | I49: 030772244470, 030772244463, 030772244562, 030772244449, 030772244524, 030772244579, 030772244418, 030772244555, 030772244517, 030772244548, 030772244425, 030772244456, 030772244494, 030772244531, 030772244500, 030772244432, 030772244395, 030772244487, 030772244371, 030772244401 | M49: 4767
A50: PAMPERS | B50: Pampers | C50: pampers_pure_protection_diapers | D50: Active | E50: Pampers® Pure Protection | F50: Pampers® Pure Protection | G50: https://www.pampers.com/en-us/products/pampers-pure-protection-diapers | H50: https://images.ctfassets.net/9wtva4vhlgxb/3D2vSDnInBBOCBIlRvHsv5/96fc36d7ff09b19a33f2af622b54cd90/Pampers_pure_protection.png | I50: 037000596554, 037000596431, 037000595946, 037000972006, 037000976509, 037000596448, 037000971900, 037000595656, 037000596271, 037000971368, 037000596059, 030772080634, 030772079010, 030772080672, 037000596516, 037000595939, 037000595601, 037000596073, 037000596479, 037000596486, 030772046517, 037000596455, 037000596066, 030772054185, 037000596530, 037000971177, 037000595908, 037000596547, 030772098158, 037000595700, 030772079027 | K50: Pampers_Pure | L50: BV_WB_FAMILY:Pampers_Pure | M50: 1762
A51: PAMPERS | B51: Pampers | C51: Pampers_AquaPure | D51: Active | E51: Pampers® Aqua Pure™ | F51: Pampers® Aqua Pure™ | G51: https://www.pampers.com/en-us/products/pampers-aqua-pure-wipes | H51: https://images.ctfassets.net/9wtva4vhlgxb/FwBT0mJ962pgTGebq893M/59e1090627ed0443dc1fb183343fc4ad/02.png | I51: 030772043738, 030772073407, 030772098523, 030772204375, 037000754145, 037000754152, 037000754169, 037000914471 | M51: 158
A52: PAMPERS | B52: Pampers | C52: 80372028 | D52: Inactive | E52: Pampers Pure Protection | F52: Ready to potty train? From Pampers, the #1 pediatrician recommended brand, here is a training pant that will have you singing. Featuring the irresistible Baby Shark characters, Pampers Pure Training Underwear gives you up to 100% leak protection, day and night. The incredibly soft, breathable material is 100% fragrance-free and made with 0% elemental chlorine, parabens, and natural rubber latex. Our dynamic 360 degree Stretchy Waistband moves with toddlers, giving them a comfortable, underwear-like fit that's easy to pull up and down. Just like real underwear! Pampers Pure Training Underwear also has Easy-Tear Sides that give parents ultimate flexibility when it's time for a quick change. Say goodbye to diapers and hello to the comfy softness of Pampers Pure Training Underwear. | G52: https://www.pampers.com/en-us/products/pampers-pure-protection-training-underwear | H52: https://images.ctfassets.net/9wtva4vhlgxb/4tu1TSDdNuzpkny2ALbpmC/172cd938888b65a9badf2c14e9ded208/purepants_324x286.png | I52: 030772050057 | M52: 136
A53: PAMPERS | B53: Pampers | C53: Pampers_MultiUse | D53: Inactive | E53: Pampers® Multi-Use | F53: Pampers® Multi-Use | G53: https://www.pampers.com/en-us/products/pampers-multi-use-wipes | H53: https://images.ctfassets.net/9wtva4vhlgxb/ibieobHIHoyT1MoQAZt7a/9a30ec4bff0c10014c0574b10498b73a/multiuse_wipes_280x195.png | I53: 037000506553, 037000506836, 037000507123, 037000580102, 037000580133, 037000872115, 037000872146, 037000872153 | M53: 51
A54: PAMPERS | B54: Pampers | C54: PAMPERS_SWADDLERS_360 | D54: Active | E54: Pampers® Swaddlers 360°™ | F54: Pampers® Swaddlers 360°™ | G54: https://www.pampers.com/en-us/products/pampers-swaddlers-360 | H54: https://images.ctfassets.net/9wtva4vhlgxb/6LYy5MuuvwV1IgIimP8mwe/4c8e926fcacf96f23db2de22e35743d5/Swaddlers_360_PCP.png | I54: 030772133446, 030772133453, 030772133460, 030772133477, 030772133484, 030772133491, 030772133507, 030772133514, 030772133521, 030772133538, 030772133545, 030772133552, 030772133569, 030772133576, 030772133583, 030772133590, 030772170632, 030772170670, 030772170687, 030772170694, 030772181416, 030772181423, 030772181430, 030772204771, 030772204788, 030772204825, 030772204832, 030772204887 | M54: 1164
A55: PAMPERS | B55: Pampers | C55: Pampers_Fragrance_Free | D55: Active | E55: Pampers® Baby-Clean Fragrance-Free Wipe | F55: Pampers® Baby-Clean Fragrance-Free Wipe | G55: https://www.pampers.com/en-us/products/pampers-fragrance-free-wipes | H55: https://images.ctfassets.net/9wtva4vhlgxb/7yEUixCuKiZeihSiwGdBFC/4cfada35d5ca97e60245581ec09d7b1f/12.png | I55: 037000754671, 037000755333 | M55: 4
A56: PAMPERS | B56: Pampers | C56: 037000275435 | D56: Inactive | E56: Pampers Pure Hybrid Disposable Inserts | F56: Pampers Pure Protection Hybrid Cloth Diaper Disposable Inserts 62ct | H56: https://target.scene7.com/is/image/Target/GUEST_29d93984-959d-40a7-8880-d253ea7c7a99?fmt=webp&wid=1400&qlt=80 | I56: 037000275435, 037000275459 | K56: pampers_pure_hybrid | M56: 117
A57: PAMPERS | B57: Pampers | C57: Pampers_Swaddlers_Sweet_Dreams | D57: Inactive | E57: Pampers® Swaddlers Sweet Dreams | F57: Pampers® Swaddlers Sweet Dreams | G57: https://www.pampers.com/en-us/products/swaddlers-sweet-dreams-wipes | H57: https://images.ctfassets.net/9wtva4vhlgxb/3Kuomk1112JgeEmusARQeF/edca8ff147096842ece8bdf75316b454/sweetdreams_324x286.png | I57: 030772018798, 030772018811 | M57: 494
A58: PAMPERS | B58: Pampers | C58: PAMPERS_PURE_PROTECTION_TRAINING_UNDERWEAR | D58: Inactive | E58: Pampers® Pure Protection Training Underwear™ | F58: Pampers® Pure Protection Training Underwear™ | G58: https://www.pampers.com/en-us/products/pampers-pure-protection-training-underwear | H58: https://images.ctfassets.net/9wtva4vhlgxb/4tu1TSDdNuzpkny2ALbpmC/8d62af4ab7bff7003b73d8480bdd95ce/14.png | I58: 030772049358, 030772049341, 030772049334, 030772050019, 030772050057 | M58: 3
A59: PAMPERS | B59: Pampers | C59: Pampers_Pure_Hybrid_Cover | D59: Inactive | E59: Pampers® Pure Hybrid Cloth Diaper Cover | F59: Pampers® Pure Hybrid Cloth Diaper Cover | G59: https://www.pampers.com/en-us/diapers-wipes/pampers-pure-protection-diapers-hybrid | H59: https://images.ctfassets.net/9wtva4vhlgxb/5deQNd9L7lSksuM3U7CYg3/38cb19a953e352777874d7c35f4e8eaf/PureHybrid_280x195.png | I59: 037000275046, 037000275084, 037000275435, 037000275459, 037000275497, 037000275565, 037000275848, 037000276067, 037000276142, 037000276159, 037000276166, 037000276371 | M59: 43
A60: PAMPERS | B60: Pampers | C60: 037000275084 | D60: Inactive | E60: Pampers Pure Hybrid Trial Kit | F60: Pampers Pure Protection Hybrid Cloth Diaper Trial Kit - 1 Reusable Cover + 13 Dispoable Inserts | H60: https://sampling-photos-prod.s3.amazonaws.com/photos/7421def26e12483c404817cb3e69950f_PAMP_PURE_HYB_TRIAL_KIT_TGT_1X_00037000275084_C1C1.jpeg | I60: 037000275046, 037000275084 | K60: pampers_pure_hybrid | L60: BV_WB_FAMILY:pampers_pure_hybrid | M60: 175
A61: PAMPERS | B61: Pampers | C61: Pampers_Swaddlers_360_EWOK_Size_4 | D61: Active | E61: Swaddlers 360 Size 4 | F61: Pampers Swaddlers 360 Size 4, Pull-on diaper | G61: https://www.pampers.com/en-us/products/pampers-swaddlers-360 | H61: https://sampling2-product-images-prod.s3.amazonaws.com/bvsampling/Pampers-Pampers_Swaddlers_360_EWOK.jpeg?t=1776262829491 | I61: 030772133538, 030772181416, 030772170670, 030772133545, 030772204832, 030772204825, 030772204771, 030772133446, 030772133491, 030772133507, 030772133514, 030772133477, 030772170687, 030772170694, 030772133576, 030772133569, 030772133590, 030772170632, 030772204788, 030772133552, 030772133484, 030772133521, 030772133460, 030772133453, 030772204887, 030772133583, 030772181423 | J61: 0030772181423, 0030772204788, 0030772133460, 0030772181416, 0030772133521, 0030772133484, 0030772204825, 0030772170687, 0030772133477, 0030772204887, 0030772133576, 0030772133491, 0030772204832, 0030772133538, 0030772133552, 0030772133446, 0030772133569, 0030772133545, 0030772133583, 0030772133507, 0030772170670, 0030772204771, 0030772133590, 0030772170694, 0030772133514, 0030772170632, 0030772133453 | M61: 2181
A62: PAMPERS | B62: Pampers | C62: 761042441 | D62: Inactive | E62: Pampers UnderJams Absorbent Night Wear for Girls | F62: Pampers UnderJams Absorbent Night Wear for Girls | G62: https://www.pampers.com/en-us/diapers-wipes/pampers-underjams-absorbent-night-wear-for-girls | H62: http://cdn.multibrand3.pgsitecore.com/en-US/-/media/Pampers/Pampers-US/Images/Products/Underjams_Girls_Open.png?v=1-201503191811 | I62: 037000173922, 037000174011, 037000929567, 037000929581, 037000929604, 037000929628 | M62: 501
A63: PAMPERS | B63: Pampers | C63: 80859348 | D63: Inactive | E63: Pampers Ultra Clean | F63: •5X Stronger: Pampers Ultra Clean Baby Wipes are 5X stronger than the leading US subbrand to help prevent tearing during diaper changes •Textured Cloth: Pampers Ultra Clean Baby Wipes grip the mess for a superior clean without fear of tearing • Superior Clean: Pampers Ultra Clean Baby Wipes clean better so you can use less (vs. the leading US Value Brand) • Free Of Harmful Ingredients: Hypoallergenic, unscented, 0% alcohol, fragrance, parabens, and plastic-free • pH-Balancing Formula: Pampers Ultra Clean Baby Wipes ph formula helps restore skin’s natural pH for clean, healthy skin • Multi-Purpose Wipes: Not just for diaper changes - Pampers Ultra Clean wipes are perfect for wiping hands, faces, removing makeup, or even cleaning off your pets’ paws! • 52 Baby Wipes | G63: https://www.pampers.com/en-us/products/pampers-ultraclean-wipes | H63: https://sampling2-product-images-prod.s3.amazonaws.com/bvsampling/Pampers-80859348.png?t=1754945413164 | I63: 030772204337, 030772104323, 030772104293, 030772104347, 030772104309, 030772104330, 030772104286, 030772104316 | M63: 1054
A64: PAMPERS | B64: Pampers | C64: Pampers_Diapers_Swaddlers_Sensitive | D64: Inactive | E64: Pampers® Swaddlers Sensitive™ | F64: Pampers® Swaddlers Sensitive™ | G64: https://www.pampers.com/en-us/diapers-wipes/pampers-swaddlers-sensitive-diapers | H64: https://images.ctfassets.net/9wtva4vhlgxb/6Q6nbuFRikWbtEQP147iaE/362be9dc8dee7f35436b24567fd8cae4/M_SENSITIVE_DIAPER_324x286_RETINA.png | I64: 037000866084, 037000866152, 037000866169, 037000866176, 037000866213, 037000866220, 037000866282 | M64: 5152
A65: PAMPERS | B65: Pampers | C65: 80371910 | D65: Inactive | E65: Pampers Pure Protection | F65: Ready to potty train? From Pampers, the #1 pediatrician recommended brand, here is a training pant that will have you singing. Featuring the irresistible Baby Shark characters, Pampers Pure Training Underwear gives you up to 100% leak protection, day and night. The incredibly soft, breathable material is 100% fragrance-free and made with 0% elemental chlorine, parabens, and natural rubber latex. Our dynamic 360 degree Stretchy Waistband moves with toddlers, giving them a comfortable, underwear-like fit that's easy to pull up and down. Just like real underwear! Pampers Pure Training Underwear also has Easy-Tear Sides that give parents ultimate flexibility when it's time for a quick change. Say goodbye to diapers and hello to the comfy softness of Pampers Pure Training Underwear. | G65: https://www.pampers.com/en-us/products/pampers-pure-protection-training-underwear | H65: https://images.ctfassets.net/9wtva4vhlgxb/4tu1TSDdNuzpkny2ALbpmC/172cd938888b65a9badf2c14e9ded208/purepants_324x286.png | I65: 030772049341 | M65: 177
A66: PAMPERS | B66: Pampers | C66: 037000276142 | D66: Inactive | E66: Pampers Pure Hybrid Cloth Diaper Cover - Full Floral | F66: Pampers Pure Protection Hybrid Cloth Diaper Reusable Cover 1ct | H66: https://sampling-photos-prod.s3.amazonaws.com/photos/4fc7794af4a1aec4bbeb6f619712d16d_00037000276142_C1C1.jpeg | I66: 037000276067, 037000275848, 037000276166, 037000276142, 037000276371 | M66: 1
A67: PAMPERS | B67: Pampers | C67: Pampers_GiftSet | D67: Active | E67: PampersGiftSet Newborn | F67: Newborn Gift Set- diapers with onesie, hat, milestone cards, coupons, and shutterfly gift | G67: https://www.pampers.com/en-us/products/pampers-newborn-gift-set | H67: https://sampling2-product-images-prod.s3.amazonaws.com/bvsampling/Pampers-Pampers_GiftSet.jpeg | I67: 030772256794 | J67: 0030772256794 | M67: 708
A68: PAMPERS | B68: Pampers | C68: Pampers_Diapers_Swaddlers | D68: Inactive | E68: Pampers® Swaddlers™ | F68: Pampers® Swaddlers™ | G68: https://www.pampers.com/en-us/products/pampers-swaddlers-diapers | H68: https://images.ctfassets.net/9wtva4vhlgxb/2HlnCBa6TS7BgdotuDDb5v/8ee224519a051f193c49882f4955bfcf/swaddlers_280x195.png | I68: 030772005378, 030772035498, 030772035504, 030772035511, 030772035528, 030772035542, 030772042809, 030772042823, 030772042830, 030772097533, 030772097540, 030772097564, 030772098141, 030772132920, 037000067290, 037000303749, 037000749585, 037000749592, 037000749615, 037000749622, 037000749684, 037000749691, 037000749714, 037000749738, 037000749837, 037000749844, 037000749875, 037000749882, 037000772552, 037000773061, 037000773078, 037000773108, 037000773115, 037000788782, 037000794660, 037000799788, 037000799818, 037000799825, 037000799832, 037000828358, 037000828365, 037000828426, 037000828433, 037000828761, 037000828792, 037000828815, 037000829126, 037000829317, 037000829324, 037000831822, 037000832058, 037000832133, 037000832249, 037000832775, 037000832805, 037000832959, 037000833086, 037000833109, 037000833178, 037000833260, 037000863403, 037000978138, 037000978145, 037000978152, 037000978169, 037000978176, 037000978183 | M68: 0
A69: PAMPERS | B69: Pampers | C69: 37000949022 | D69: Inactive | E69: Pampers Premium Care | F69: Pampers Premium Care | G69: http://www.pampers.com/en-us/diapers-wipes/pampers-premium-care | H69: http://cdn.multibrand3.pgsitecore.com/en-US/-/media/Pampers/Pampers-US/Images/Products/WMT_Premium_Open.png?v=1-201509041204 | I69: 037000948988, 037000948995, 037000949008, 037000949015, 037000949022, 037000949039, 037000949046, 037000949053, 037000949060, 037000949077 | M69: 135
A70: PAMPERS | B70: Pampers | C70: pampers-expressions-wipes | D70: Inactive | E70: Pampers® Expressions Wipes | F70: Pampers® Expressions Wipes | G70: https://www.pampers.com/en-us/diapers-wipes/pampers-expressions-wipes | H70: https://images.ctfassets.net/9wtva4vhlgxb/3EAShoqCQcB1QGrhxGRgK5/dc1d4e5dc332a603316c824cc9cc80cf/Gexpressions_324x286.png | I70: 037000506553, 037000506836, 037000507123, 037000579823, 037000579939, 037000580102, 037000580133, 037000872115, 037000872146, 037000872153 | K70: pampers-expressions-wipes | L70: BV_WB_FAMILY:pampers-expressions-wipes | M70: 792
A71: PAMPERS | B71: Pampers | C71: Pampers_Cruisers360 | D71: Active | E71: Pampers® Cruisers 360°™ | F71: Pampers® Cruisers 360°™ | G71: https://www.pampers.com/en-us/products/pampers-cruisers-360 | H71: https://images.ctfassets.net/9wtva4vhlgxb/5KRyHCvdzwkmqvWKGZKCUL/94a2968893f42df10b600645db8df052/13.png | I71: 030772094464, 037000715092, 037000748618, 037000717072, 030772163306, 037000714835, 030772204924, 037000716853, 037000717119, 030772040928, 030772046074, 037000714576, 00030772207284, 037000717379, 030772046050, 037000714774, 030772204900, 037000718512, 030772094471, 030772204931, 037000714866, 030772204894, 037000715122, 037000716679, 030772142592, 00030772207277, 00030772207307, 037000714477, 037000716556, 037000715078, 037000715436, 030772046043, 030772204863, 030772094488, 037000718529, 037000716785, 037000714873, 037000716549, 030772046067 | M71: 1830
A72: PAMPERS | B72: Pampers | C72: 037000963769 | D72: Inactive | E72: Pampers Swaddlers Overnights | F72: Pampers Swaddlers Overnights | G72: https://www.pampers.com/en-us/diapers-wipes/pampers-swaddlers-overnights | H72: http://cdn.multibrand3.pgsitecore.com/en-US/-/media/Pampers/Pampers-US/Images/Products/17_Pampers_Swaddlers_355x215_nosize.jpg?h=215&w=355&v=1-201707171944&crop=1&sc=0 | I72: 037000963769, 037000963776, 037000963783, 037000963790 | M72: 0
A73: PAMPERS | B73: Pampers | C73: Pampers_EasyUps | D73: Active | E73: Pampers® Easy Ups™ | F73: Potty train with Pampers Easy Ups, featuring up to 100% leakproof protection day and night. | G73: https://www.pampers.com/en-us/products/pampers-easy-ups-trainers-for-boys-and-girls | I73: 037000607304, 037000724063, 037000785064, 030772123072, 037000607168, 030772123065, 030772279014, 030772234075, 037000724162, 037000764168, 030772203170, 030772266946, 030772203095, 037000792710, 037000764656, 037000607083, 030772221174, 037000785088, 037000764410, 037000764908, 037000724506, 030772189931, 037000724773, 030772032688, 037000764885, 030772221105, 030772203163, 030772213513, 030772032701, 351114707317, 037000764700, 030772270707, 030772254226, 037000764878, 030772032718, 037000796183, 030772123041, 037000764373, 037000724780, 037000724148, 037000764663, 037000724186, 030772032695, 037000764380, 030772032756, 037000764632, 037000724025, 030772234044, 030772213506, 030772189955, 030772270677, 030772270684, 030772203194, 030772267004, 0330858377390, 037000785071, 037000764434, 037000785057, 037000764564, 037000724070, 037000764052, 037000764694, 037000607236, 037000764687, 030772221150, 030772221112, 037000765103, 030772221181, 030772203118, 030772266984, 030772032725, 030772123058, 037000764861, 037000764397, 030772221136, 037000764892, 037000764366, 030772270691, 030772230756, 037000724216, 037000724056, 030772213537, 037000607151, 037000764649, 037000764403, 030772266991 | J73: 030772266946, 5430477571638, 030772213513, 0351114707317, 030772213506, 0330858377390, 0037000724025, 030772266984, 030772123058, 0030772279014, 030772213537, 030772266991, 0030772203194, 030772267004, 0030772203118, 0030772230756 | K73: Pampers_Easy_Ups | L73: BV_WB_FAMILY:Pampers_Easy_Ups | M73: 4542
A74: PAMPERS | B74: Pampers | C74: Pampers_Swaddlers_360_EWOK_Size_5 | D74: Active | E74: Swaddlers 360 Size 5 | F74: Pampers Swaddlers 360 Size 5, Pull-on diaper | G74: https://www.pampers.com/en-us/products/pampers-swaddlers-360 | H74: https://sampling2-product-images-prod.s3.amazonaws.com/bvsampling/Pampers-Pampers_Swaddlers_360_EWOK.jpeg?t=1776262829491 | I74: 030772133538, 030772181416, 030772170670, 030772133545, 030772204832, 030772204825, 030772204771, 030772133446, 030772133491, 030772133507, 030772133514, 030772133477, 030772170687, 030772170694, 030772133576, 030772133569, 030772133590, 030772170632, 030772204788, 030772133552, 030772133484, 030772133521, 030772133460, 030772133453, 030772204887, 030772133583, 030772181423 | J74: 0030772181423, 0030772204788, 0030772133460, 0030772181416, 0030772133521, 0030772133484, 0030772204825, 0030772170687, 0030772133477, 0030772204887, 0030772133576, 0030772133491, 0030772204832, 0030772133538, 0030772133552, 0030772133446, 0030772133569, 0030772133545, 0030772133583, 0030772133507, 0030772170670, 0030772204771, 0030772133590, 0030772170694, 0030772133514, 0030772170632, 0030772133453 | M74: 2297
A75: PAMPERS | B75: Pampers | C75: pampers-pure-protection-diapers-hybrid | D75: Inactive | E75: Pampers® Pure Protection Hybrid Diapers | F75: Pampers® Pure Protection Hybrid Diapers | G75: https://www.pampers.com/en-us/diapers-wipes/pampers-pure-protection-diapers-hybrid | H75: https://images.ctfassets.net/9wtva4vhlgxb/5deQNd9L7lSksuM3U7CYg3/38cb19a953e352777874d7c35f4e8eaf/PureHybrid_280x195.png | I75: 037000275046, 037000275084, 037000275435, 037000275459, 037000275497, 037000275565, 037000275848, 037000276067, 037000276142, 037000276159, 037000276166, 037000276371 | K75: pampers_pure_hybrid | L75: BV_WB_FAMILY:pampers_pure_hybrid | M75: 5
A76: PAMPERS | B76: Pampers | C76: Pampers_Baby_Fresh | D76: Active | E76: Pampers® Baby-Clean Baby Fresh™ Scent | F76: Pampers® Baby-Clean Baby Fresh™ Scent | G76: https://www.pampers.com/en-us/products/pampers-baby-fresh-scent-wipes | H76: https://images.ctfassets.net/9wtva4vhlgxb/5wjwKWQnBbPezlq8p7ca4F/2aa17de180574c6e508fb6afe6f98b3d/15.png | I76: 030772054840, 030772073278, 037000754770 | M76: 4546
A77: PAMPERS | B77: Pampers | C77: Pampers_Cruisers | D77: Inactive | E77: Pampers® Cruisers™ | F77: Pampers® Cruisers™ | G77: https://www.pampers.com/en-us/products/pampers-cruisers-diapers | H77: https://images.ctfassets.net/9wtva4vhlgxb/1BN1cotlV0UebGSXqey7sA/40a2115d0c24dd1a80e76f919df7e9fb/Cruisers_280x195.png | I77: 030772044131, 037000644552, 037000644576, 037000714873, 037000715092, 037000751960, 037000752004, 037000752028, 037000752035, 037000752097, 037000752103, 037000752127, 037000752394, 037000752608, 037000752615, 037000775447, 037000775454, 037000775478, 037000775485, 037000775669, 037000795230, 037000799726, 037000799733, 037000799740, 037000799764, 037000799771, 037000819202, 037000820338, 037000820345, 037000862581, 037000862598, 037000862604, 037000862611, 037000862628, 037000862642, 037000862680, 037000862697, 037000862703, 037000862710, 037000862796, 037000862802, 037000862819, 037000862864, 037000862871, 037000862888, 037000862901, 037000862918, 037000862925, 037000862949, 037000868576, 037000932024, 037000933380, 037000933564 | M77: 10022
A78: PAMPERS | B78: Pampers | C78: 37000775843 | D78: Inactive | E78: Pampers Swaddlers Overnights Diapers Size 6 42 Count | F78: Swaddlers protection with nighttime in mind! Pampers Swaddlers Overnights diapers feature Pampers All Night Protection*, which means they're designed to handle even the heaviest nights. The outer cover is Blankie Soft, just like regular Swaddlers, so you can wrap her in comfort all night long. And, thanks to a color-changing wetness indicator, you'll know when it's time for a change. Swaddlers Overnights diapers also feature a Heart Quilt liner that pulls wetness and mess away from your baby's delicate skin. Plus, Air Channels help distribute moisture evenly for a comfortable night's sleep. For sweet dreams, try our softest nighttime diaper: Swaddlers Overnights. *Up to 12 hours of protection | H78: https://sampling-photos-prod.s3.amazonaws.com/photos/3a19e0d22fa5e03a4f21612bfc6c9030_f78f80d2-a441-4a46-97f9-f01c7a1689c5_1.a4fab7d9c9ce7c8565d68d305dbdf828_.jpeg | I78: 037000775843 | M78: 49
A79: PAMPERS | B79: Pampers | C79: Pampers_Diapers_Cruisers | D79: Inactive | E79: Pampers® Cruisers™ | F79: Pampers® Cruisers™ | G79: https://www.pampers.com/en-us/products/pampers-cruisers-diapers | H79: https://images.ctfassets.net/9wtva4vhlgxb/1BN1cotlV0UebGSXqey7sA/40a2115d0c24dd1a80e76f919df7e9fb/Cruisers_280x195.png | I79: 030772044131, 037000751960, 037000752004, 037000752028, 037000752035, 037000752394, 037000752608, 037000752615, 037000775447, 037000775454, 037000775478, 037000775485, 037000795230, 037000799726, 037000799733, 037000799740, 037000799764, 037000799771 | M79: 1
A80: PAMPERS | B80: Pampers | C80: 80371909 | D80: Inactive | E80: Pampers Pure Protection | F80: Ready to potty train? From Pampers, the #1 pediatrician recommended brand, here is a training pant that will have you singing. Featuring the irresistible Baby Shark characters, Pampers Pure Training Underwear gives you up to 100% leak protection, day and night. The incredibly soft, breathable material is 100% fragrance-free and made with 0% elemental chlorine, parabens, and natural rubber latex. Our dynamic 360 degree Stretchy Waistband moves with toddlers, giving them a comfortable, underwear-like fit that's easy to pull up and down. Just like real underwear! Pampers Pure Training Underwear also has Easy-Tear Sides that give parents ultimate flexibility when it's time for a quick change. Say goodbye to diapers and hello to the comfy softness of Pampers Pure Training Underwear. | G80: https://www.pampers.com/en-us/products/pampers-pure-protection-training-underwear | H80: https://images.ctfassets.net/9wtva4vhlgxb/4tu1TSDdNuzpkny2ALbpmC/172cd938888b65a9badf2c14e9ded208/purepants_324x286.png | I80: 030772049334 | M80: 198
A81: PAMPERS | B81: Pampers | C81: 037000275848 | D81: Inactive | E81: Pampers Pure Hybrid Cloth Diaper Cover - Jungle | F81: Pampers Pure Protection Hybrid Cloth Diaper Reusable Cover 1ct | H81: https://sampling-photos-prod.s3.amazonaws.com/photos/2adaad81645a4d1ec40b2b58f9e8586b_00037000275848_C1C1.jpeg | I81: 037000275848, 037000276067 | M81: 110
A82: PAMPERS | B82: Pampers | C82: Pampers_BabyDry | D82: Active | E82: Pampers® Baby-Dry™ | F82: Pampers® Baby-Dry™ Pampers Baby Dry Pampers BabyDry | G82: https://www.pampers.com/en-us/products/pampers-baby-dry-diapers | H82: https://images.ctfassets.net/9wtva4vhlgxb/eXvBk6nXcZk2h0p5HlBEK/bb0423bbe819b5247b3d4fa12fcc2078/08.png | I82: 030772145401, 037000862352, 037000838258, 030772034361, 037000862093, 037000783169, 037000893097, 037000862345, 037000862369, 037000838265, 037000783817, 037000862208, 030772197875, 037000838180, 037000864448, 030772034354, 030772034347, 037000783800, 037000783831, 037000862109, 030772197967, 037000864196, 030772197905, 00030772034354, 030772034385, 037000870692, 037000862222, 030772213971, 037000862215, 030772197974, 037000862130, 037000862260, 030772034408, 037000862253, 030772197899, 00030772034392, 030772034392, 00030772034361, 037000862116, 037000863939, 030772091081, 030772091364, 030772213988, 00030772034385, 037000838173, 030772091098, 037000862239, 037000864349, 037000783794, 030772213995, 037000838272, 037000783824, 00030772034408, 037000862246, 030772198018, 037000862086, 00030772034347, 00030772091074, 030772091074, 037000862123 | M82: 14971
A83: PAMPERS | B83: Pampers | C83: SwaddlersUltra | D83: Inactive | E83: Pampers Swaddlers Ultra Day + Night | F83: Swaddlers Ultra Day + Night Our most absorbent for up to 12H of Sleep | G83: https://www.pampers.com/en-us/products/pampers-swaddlers-ultra | H83: https://sampling2-product-images-prod.s3.amazonaws.com/bvsampling/Pampers-SwaddlersUltra.jpeg | I83: 030772250228, 030772250181, 030772250174, 030772249314, 030772249284, 030772250167, 030772249352, 030772249321, 030772249345, 030772249291, 030772250211, 030772250198, 030772250150, 030772249277, 030772250204, 030772249338, 030772250143, 030772249307 | M83: 2711
A84: PAMPERS | B84: Pampers | C84: Cruisers_360 | D84: Inactive | E84: Pampers® Cruisers 360° Fit™ | F84: Pampers® Cruisers 360° Fit™ | G84: https://www.pampers.com/en-us/diapers-wipes/pampers-cruisers-360 | H84: https://images.ctfassets.net/9wtva4vhlgxb/1UjwZnfAcgp0drDks8IgGv/7ab0d6853445f1f0569afb3116623ce0/Packshot.png | I84: 037000714477, 037000714576, 037000714774, 037000714835, 037000714866, 037000714873, 037000715078, 037000715092, 037000715122, 037000715436, 037000716549, 037000716556, 037000716679, 037000716785, 037000716853, 037000717072, 037000717119, 037000717379, 037000718512, 037000718529, 037000744900, 037000744993, 037000745037, 037000745211, 037000748618, 037000810186, 037000929413, 037000929529, 037000931980, 037000931997, 037000932000, 037000932048, 037000932093, 037000932482, 037000932512, 037000932550, 037000991434, 477199916373, 477199917301 | M84: 25
A85: PAMPERS | B85: Pampers | C85: Pampers_Swaddlers | D85: Active | E85: Pampers® Swaddlers™ | F85: Pampers® Swaddlers™ | G85: https://www.pampers.com/en-us/products/pampers-swaddlers-diapers | H85: https://images.ctfassets.net/2ql69mthp94m/1RKbw0c8rZttOQ1c7tCCOG/e9c42ca7cac2d0b5993d12dcd53ef318/Swaddlers_New_Clean.png | I85: 037000828761, 030772097564, 037000788782, 037000829324, 037000828792, 030772035504, 037000828365, 030772035511, 037000749691, 037000773078, 030772131039, 037000799825, 037000799818, 037000773061, 037000749684, 037000833109, 037000749790, 030772132920, 037000749882, 030772035498, 037000832058, 030772042830, 037000749592, 037000828815, 030772098141, 037000749615, 037000749875, 037000863403, 030772042809, 037000749622, 037000833086, 037000828358, 037000831822, 030772097533, 030772228142, 037000828433, 030772228135, 037000794660, 030772042823, 030772228210, 030772228166, 030772035528, 037000749714, 037000749844, 030772097540, 037000772552, 037000773115, 030772098639, 037000829126, 037000833178, 037000829348, 030772228180, 037000773108, 037000828426, 037000749585, 037000833260, 030772035542, 037000799832 | M85: 59790
A86: PAMPERS | B86: Pampers | C86: PAMPERS_SENSITIVE | D86: Active | E86: Pampers® Sensitive™ | F86: Pampers® Sensitive™ | G86: https://www.pampers.com/en-us/products/pampers-sensitive-wipes | H86: https://images.ctfassets.net/9wtva4vhlgxb/3CFIkldpzkFvT7UjAOxben/d1a8eb563ede1f75cfef97fe97f98f81/10.png | I86: 030772098530, 037000941743, 030772073254, 037000845706, 030772204351, 030772073315, 030772168196, 030772073360, 030772269190, 037000870876, 030772073261, 037000967552, 030772269718, 037000894131, 037000731061, 037000751397, 037000195085 | M86: 16229
A87: PAMPERS | B87: Pampers | C87: pampers-swaddlers-sweet-dreams-wipes | D87: Inactive | E87: Pampers® Swaddlers Sweet Dreams Wipes | F87: Pampers® Swaddlers Sweet Dreams Wipes | G87: https://www.pampers.com/en-us/diapers-wipes/swaddlers-sweet-dreams-wipes | H87: https://images.ctfassets.net/9wtva4vhlgxb/3F4ytrV7tpvbdGesBCm7ss/642ebacf11a7969d96bff70f38fedcf5/sweetdreams_324x286.png | I87: 030772018798, 030772018804, 030772018811 | M87: 1
A88: PAMPERS | B88: Pampers | C88: 761043742 | D88: Inactive | E88: Pampers® Underjams™ | F88: Pampers® Underjams™ | G88: https://www.pampers.com/en-us/diapers-wipes/pampers-underjams-absorbent-night-wear-for-boys-and-girls | H88: https://images.ctfassets.net/9wtva4vhlgxb/4SL6JBRFEfbuYCVpJCB0hC/18e3edd60e8b0bcf0f4505be1054f9eb/M_UNDERJAMS_DIAPER_324x286_RETINA.png | M88: 580
A89: PAMPERS | B89: Pampers | C89: Pampers_ Pure_Protection_Diapers | D89: Active | E89: Pampers® Pure Protection | F89: Pampers® Pure Protection | G89: https://www.pampers.com/en-us/products/pampers-pure-protection-diapers | H89: https://images.ctfassets.net/9wtva4vhlgxb/3D2vSDnInBBOCBIlRvHsv5/96fc36d7ff09b19a33f2af622b54cd90/Pampers_pure_protection.png | I89: 037000596554, 037000275435, 037000596431, 037000972006, 037000976509, 037000596448, 037000275459, 037000596271, 037000971368, 037000596059, 030772079010, 037000595946, 037000275497, 030772080672, 037000596516, 037000276067, 037000595939, 037000595601, 030772049358, 037000596073, 030772049341, 037000596479, 037000596486, 030772046517, 037000275565, 037000971900, 037000596455, 037000596066, 037000595656, 037000275046, 037000275848, 037000276142, 030772054185, 037000276371, 037000596530, 030772050019, 030772050057, 030772080634, 037000971177, 037000595908, 037000596547, 030772098158, 030772049334, 037000276166, 037000595700, 030772079027, 037000275084 | M89: 1
A90: PAMPERS | B90: Pampers | C90: 761042388 | D90: Inactive | E90: Pampers® Swaddlers™ | F90: Pampers® Swaddlers™ | G90: https://www.pampers.com/en-us/diapers-wipes/pampers-swaddlers-diapers | H90: https://images.ctfassets.net/9wtva4vhlgxb/7ftRv7BloaHJHXVleyXUyI/1a29050893aea6965edbd6683f3fbbb1/Swaddlers_280x195.png | I90: 030772005378, 037000695462, 037000695479, 037000695486, 037000695493, 037000695509, 037000695516, 037000744887, 037000749585, 037000749592, 037000749615, 037000749622, 037000749684, 037000749691, 037000749714, 037000749844, 037000749875, 037000749882, 037000772552, 037000773061, 037000773078, 037000773108, 037000773115, 037000788782, 037000794660, 037000799788, 037000799818, 037000799825, 037000799832, 037000828358, 037000828365, 037000828426, 037000828433, 037000828761, 037000828792, 037000828815, 037000829126, 037000829317, 037000829324, 037000829348, 037000829799, 037000830481, 037000830498, 037000830504, 037000830535, 037000830559, 037000830627, 037000831822, 037000832058, 037000832249, 037000832270, 037000832775, 037000832805, 037000832959, 037000833086, 037000833178, 037000833260, 037000978176 | M90: 89
A91: PAMPERS | B91: Pampers | C91: Pampers_Splashers | D91: Active | E91: Pampers® Splashers™ | F91: Pampers® Splashers™ | G91: https://www.pampers.com/en-us/products/pampers-splashers-swim-pants-for-boys-and-girls | H91: https://images.ctfassets.net/9wtva4vhlgxb/Bi34ckgoqD99LCm2Exs3B/61970000898c0bdc376fb9f44b788acb/11.png | I91: 030772253861, 037000764595, 037000859239 | J91: 0030772253861, 0037000764595 | M91: 2895
A92: PAMPERS_US | B92: Pampers | C92: 761042421 | D92: Inactive | E92: Pampers Baby Dry Extra Protection | F92: Pampers Baby Dry Extra Protection | J92: 0037000864820, 0037000864837, 0037000864844, 0037000864851, 0037000864868, 0037000864875, 0037000864899, 0037000864905 | M92: 2320
A93: Pampers Cruisers 360 | B93: Pampers Cruisers 360 | C93: 80782544 | D93: Active | E93: Pampers Cruisers 360 S6 Super 1/48 | F93: Pampers Cruisers 360 Pull-On Diapers were designed for active babies and toddlers to provide an up to 100% leakproof fit - now with new EZ-Off tabs on the front of the diaper. Itâ€™s truly best of both the worlds with changes made easy â€“ it slides right on like a pant and tabs right off like a diaper. Just slide them on to apply, completely remove the EZ-off tabs from reach side, use the EZ-Off tabs to secure the diaper on both sides and youâ€™re done! | H93: https://sampling2-product-images-prod.s3.amazonaws.com/bvsampling/Pampers-80782544.png | I93: 030772094464, 030772094471, 030772094488, 030772142592, 037000715122 | M93: 96
C94: INFPGID2160755 | D94: Inactive | M94: 10
C95: 003700006755 | D95: Inactive | M95: 11
C96: INFPGID2028092 | D96: Inactive | M96: 5
C97: 37000940625 | D97: Inactive | M97: 41
C98: BABYDRYM7-BENL | D98: Inactive | M98: 1
C99: INFPGID2028461 | D99: Inactive | M99: 5
C100: 111 | D100: Inactive | M100: 0
...

Sheet pgdodotspain
A1: Bazaarvoice
A2: pgdodotspain R&R Key Metrics
A3: Run Date: Aug 12, 2026 12:00 AM UTC
A4: Instance: pgdodotspain
A5: Date range: All Time
A6: Date field: Review Submission Date
A7: Brand ID | B7: Brand | C7: Product ID | D7: Product Status | E7: Product Name | F7: Description | G7: Product Page URL | H7: Image URL | I7: UPC | J7: EAN | K7: Product Family | L7: Product Family - Expand | M7: # Approved Reviews
A8: DODOT | B8: Dodot | C8: 2100000 | D8: Inactive | E8: Dodot Happyjama Niñas | F8: Dodot Happyjama Niñas | G8: https://www.dodot.es/mas-producto/dodot-happyjama-ninas | H8: http://cdn.multibrand.pgsitecore.com/es-ES/-/media/Pampers/Dodot-ES/Images/Products/Product-plus/Dodot-Happyjama-Ninas/Diaper_Packshot_Master_HA_Girl_630.jpg?h=330&w=630&v=1-201609211224&hash=177E9922249E03C1FE9F2523665FA14D6538FB79&crop=1&sc=0 | J8: 8410108102056, 8410108102094 | M8: 3
A9: DODOT | B9: Dodot | C9: 2200000 | D9: Inactive | E9: Toallitas Dodot Básico | F9: Toallitas Dodot Básico | G9: https://www.dodot.es/mas-producto/toallitas-dodot-basico | H9: http://cdn.multibrand.pgsitecore.com/es-ES/-/media/Pampers/Dodot-ES/Images/Products/Product-plus/Toallitas-Dodot-Basico/Wipes_Packshot_Master_BA_AR3_630.jpg?h=330&w=630&v=1-201609220633&hash=4979CA0DE608D88CF5A23FCBA466D320F0D7EB9B&crop=1&sc=0 | J9: 7108172404633, 8410108104661 | M9: 27
A10: DODOT | B10: Dodot | C10: DODOT_SPLASHERS | D10: Active | E10: Dodot® Splashers | F10: Bañadores desechables Dodot® Splashers para bebés activos en el agua. Sin cierres laterales. Tallas 4 y 5. | G10: https://www.dodot.es/panales-toallitas/dodot-splashers | H10: https://images.ctfassets.net/2ql69mthp94m/3UJqx93lWCQDXxDm128dcB/97223cac5b87a958ad00bdc9c2d2f9b5/00030772204870_C1L1__2_.png?fm=avif&w=1920&q=75 | J10: 8001090698452, 8001090729132 | M10: 2
A11: DODOT | B11: Dodot | C11: 2110000 | D11: Inactive | E11: Dodot Happyjama Niños | F11: Dodot Happyjama Niños | G11: https://www.dodot.es/mas-producto/dodot-happyjama-ninos | H11: http://cdn.multibrand.pgsitecore.com/es-ES/-/media/Pampers/Dodot-ES/Images/Products/Product-plus/Dodot-Happyjama-Ninos/Diaper_Packshot_Master_HA_Boy_630.jpg?h=330&w=630&v=1-201609211224&hash=A259A59D6E60758AE152F0158B5DBFD18AE5A91A&crop=1&sc=0 | J11: 8410108101974, 8410108102018 | M11: 4
A12: PAMPERS | B12: Pampers | C12: 2120000 | D12: Inactive | E12: TOALLITAS Dodot® Sensitive | F12: TOALLITAS Dodot® Sensitive | G12: https://www.dodot.es/panales-toallitas/toallitas-dodot-sensitive | H12: https://images.ctfassets.net/bekpciakv9dp/1z73D4MzXu9Bzjo0D9zBs0/6b4701535dbc9e3fb7e0f8ee5100da72/M_TOALLITAS_SENSITIVE_324X286_RETINA.png | J12: 8410108122429, 8410108122498, 8410108122535, 8410108122573, 8410108122610, 8410108123402 | M12: 1926
A13: PAMPERS | B13: Pampers | C13: 2140000 | D13: Inactive | E13: TOALLITAS Dodot® Activity | F13: TOALLITAS Dodot® Activity | G13: https://www.dodot.es/panales-toallitas/toallitas-dodot-activity | H13: https://images.ctfassets.net/bekpciakv9dp/2dvPAlTzX8C8pgD6MdKZV4/8f51a41a5f11ddb12a4d697f9cc6701c/M_TOALLITAS_ACTIVITY_324X286_RETINA.png | J13: 4015400739388, 8001090787774, 8410108100618, 8410108100694, 8410108100724, 8410108100816 | M13: 685
A14: PAMPERS | B14: Pampers | C14: AQUA_PURE | D14: Inactive | E14: TOALLITAS Aqua Pure de Dodot® | F14: TOALLITAS Aqua Pure de Dodot® | G14: https://www.dodot.es/panales-toallitas/toallitas-dodot-pure | H14: https://images.ctfassets.net/bekpciakv9dp/ac0d0c4ce65ffdecf12ae103c4c459c0922aeae747a208a94336cad98da9bf9d/ed06896bfdae20a123b8c3702e7eb16e/M_TOALLITAS_AQUA_PURE_324X286_RETINA.png | J14: 8001841115498, 8001841115528, 8001841115542 | M14: 5
A15: PAMPERS | B15: Pampers | C15: 2160000 | D15: Inactive | E15: PAÑALES Dodot® Bebé-Seco | F15: PAÑALES Dodot® Bebé-Seco | G15: https://www.dodot.es/panales-toallitas/panales-dodot | H15: https://images.ctfassets.net/bekpciakv9dp/61JAqi6LBltVSwTAThi1gx/04d02f6bad424c9b416fcfc0cdb2e462/Dodot.com_Bebe-Seco_Producto_280x195px.png | J15: 4015400870562, 4015400870715, 4015400870777, 4015400870821, 4015400870869, 4015600951511, 4015600952266, 8001090188465, 8001090189325, 8001090280664, 8001090445223, 8001090514868, 8001090620347, 8006540618547, 8006540618608, 8006540618660 | M15: 1296
A16: PAMPERS | B16: Pampers | C16: TOALLITAS_Dodot_Cuidado_Total_Coco | D16: Inactive | E16: TOALLITAS Dodot® Cuidado Total Coco | F16: TOALLITAS Dodot® Cuidado Total Coco | G16: https://www.dodot.es/panales-toallitas/toallitas-dodot-cuidado-total-coco | H16: https://images.ctfassets.net/bekpciakv9dp/5T9nNLBjWTQScfOk3mVFXs/0a50ddb67c669836814b3902f1e93881/324x286_Dodot_Coco_Toallitas_Product_Tour.png | J16: 8006540618356 | M16: 1
A17: PAMPERS | B17: Pampers | C17: Ropa_Interior_Absorbente | D17: Inactive | E17: Ropa Interior Absorbente de Dodot® | F17: Ropa Interior Absorbente de Dodot® | G17: https://www.dodot.es/panales-toallitas/ropa-interior-absorbente-de-dodot | H17: https://images.ctfassets.net/bekpciakv9dp/2h3sJq3uolU2w0qGByPqEy/b971055a6bad3806a434fac66ca58bd2/Packshot.png | J17: 8006540260326, 8006540260340, 8006540260357, 8006540260371 | M17: 1
A18: PAMPERS | B18: Pampers | C18: TOALLITAS_MANOS_LIMPIAS | D18: Inactive | E18: Toallitas Dodot® Manos Limpias & GO | F18: Toallitas Dodot® Manos Limpias & GO | G18: https://www.dodot.es/panales-toallitas/toallitas-dodot-manos-limpias-go | H18: https://images.ctfassets.net/bekpciakv9dp/7olbP2LWxIM6QBzGZIXwLz/21684b1fecf42fe27aa5ac39aae2f038/pack_320x286.png | J18: 8006540222287 | M18: 1
A19: PAMPERS | B19: Pampers | C19: DODOT_ACTIVITY_PANTS | D19: Inactive | E19: PAÑALES-BRAGUITA Dodot® Activity Pants™ | F19: PAÑALES-BRAGUITA Dodot® Activity Pants™ | G19: https://www.dodot.es/panales-toallitas/dodot-activity-pants | H19: https://images.ctfassets.net/bekpciakv9dp/23mNwXHI0JTlG6qLWmEvYm/1ce12e547eb51fa68f365b96a3b05364/Dodot.com_Pants-Activity_Producto_320x286px.png | J19: 8001090993953, 8001090994011, 8001090994042 | M19: 13
... A26: PAMPERS | B26: Pampers | C26: 2190000 | D26: Inactive | E26: TOALLITAS Dodot® | F26: TOALLITAS Dodot® | G26: https://www.dodot.es/panales-toallitas/toallitas-dodot | H26: https://images.ctfassets.net/bekpciakv9dp/ebe8574899887ad8f9b2ead96e75239c38c1285e340b8f9fb1f302cf3f447c12/a95776187fa39eb77883d1f88f99ac64/M_TOALLITAS_324X286_RETINA.png | J26: 8001090134226, 8001090134257, 8001090134288, 8001090311504 | M26: 45
C27: 2140008 | D27: Inactive | M27: 0
C28: 2140003 | D28: Inactive | M28: 0
C29: 2140001 | D29: Inactive | M29: 0
C30: 1 | D30: Inactive | E30: Dodot Activity | F30: Con las toallitas Dodot Activity limpiarás el culito de tu bebé, incluso con las caquitas más difíciles, de una forma fácil y sin tener que frotar su piel | G30: http://www.dodot.es/toallitas-dodot-activity | H30: http://images.buzzillions.com/images_products/00/57/15517913_100.jpg | M30: 0
C31: 2140007 | D31: Inactive | M31: 0
C32: 2140000"" | D32: Inactive | M32: 1
C33: 2140005 | D33: Inactive | M33: 0
C34: 2140004 | D34: Inactive | M34: 0
C35: 2140002 | D35: Inactive | M35: 0
C36: 2140009 | D36: Inactive | M36: 0

Sheet pampers-ja_jp
A1: Bazaarvoice
A2: Pampers-JA_JP R&R Key Metrics
A3: Run Date: Aug 12, 2026 12:00 AM UTC
A4: Instance: pampers-ja_jp
A5: Date range: All Time
A6: Date field: Review Submission Date
A7: Brand ID | B7: Brand | C7: Product ID | D7: Product Status | E7: Product Name | F7: Description | G7: Product Page URL | H7: Image URL | I7: UPC | J7: EAN | K7: Product Family | L7: Product Family - Expand | M7: # Approved Reviews
A8: 15-JP | B8: Pampers JP | C8: 4902430148641 | D8: Inactive | E8: パンパース さらさらケアテープ（Sサイズ） | F8: 1)新改良！パンパースだけの一枚多いぐっすりシートでもっとすばやくさらさら。 2)パンパースだけの素肌と同じ弱酸性のシートで、お肌への刺激を防ぎます。 3)通気性のいいコットンシートが、ムレを逃がして赤ちゃんのお肌は快適。 * “コットンシート”はコットンのような肌ざわりのシートです。コットンは含まれていません。 | G8: http://www.jp.pampers.com/dry_taped_diapers_S | H8: http://media25.jp.pampers.com/ja_JP/images/pc/hb/products/prod_img_diapers_tappedS.jpg | J8: 4902430148641, 4902430574433 | M8: 1
A9: 15-JP | B9: Pampers JP | C9: 4902430215992 | D9: Inactive | E9: パンパースのはじめての肌へのいちばん （新生児サイズ） | F9: 妊娠、ご出産おめでとうございます。生まれたての赤ちゃんの肌はとってもデリケート！だからパンパースのはじめての肌へのいちばん。パンパースシリーズは、病産院使用率*No.1 生まれたての赤ちゃんにもお使いいただけます。*当社調査（新生児用データ） | G9: http://www.jp.pampers.com/dry_diapers_Newborns | H9: http://media252.jp.pampers.com/ja_JP/images/pc/hb/lsp/products/prod_image_main_diaper_dryXL.png | J9: 4902430421898 | M9: 4
A10: 15-JP | B10: Pampers JP | C10: 4902430148825 | D10: Inactive | E10: パンパースさらさらパンツ（Mサイズ） | F10: <ul> <li><strong>パンパースパンツ史上最高評価</strong><br />10年ぶりの大型改良の新しいパンパースさらさらパンツは、パンパースパンツ史上最高評価を受けました。<br />※Ｍサイズにおける生産ラインを含めた製品改良。</li> <li><strong>さらさらスリムジェル</strong><br />湿気まで吸収してムレさえ肌によせつけない！最長12時間お肌さらさら、朝までぐっすり。</li> <li><strong>やわらかベルトで締めつけ感ゼロへ</strong><br />ベルトがやわらかくなって、赤ちゃんの肌を締めつけずに安心のフィット感を実現しました。</li> <li><strong>赤ちゃんのおしりをすっぽりつつむかたちに改良！</strong><br />おしりをすっぽりつつむかたちになり、元気に動いてもおしりに食い込みにくくなりました。<br />※実際の着用感には個人差があります。</li> <li><strong>もちろん通気性ばっちり！コットンシート</strong><br />ムレを逃がして赤ちゃんのお肌は快適。<br />※“コットンシート”はコットンのような肌ざわりのシートです。コットンは含まれていません。</li> </ul> | G10: http://www.jp.pampers.com/dry_training_pants_M | H10: http://media252.jp.pampers.com/ja_JP/images/pc/hb/lsp/products/Pants_SJ_M.png | J10: 4902430148825, 4902430574327 | M10: 7
A11: 15-JP | B11: Pampers JP | C11: 4902430148948 | D11: Inactive | E11: パンパースさらさらパンツ（ビッグサイズ） | F11: <ul> <li><strong>パンパースパンツ史上最高評価</strong><br />10年ぶりの大型改良の新しいパンパースさらさらパンツは、パンパースパンツ史上最高評価を受けました。<br />※Ｍサイズにおける生産ラインを含めた製品改良。</li> <li><strong>さらさらスリムジェル</strong><br />湿気まで吸収してムレさえ肌によせつけない！最長12時間お肌さらさら、朝までぐっすり。</li> <li><strong>やわらかベルトで締めつけ感ゼロへ</strong><br />ベルトがやわらかくなって、赤ちゃんの肌を締めつけずに安心のフィット感を実現しました。</li> <li><strong>赤ちゃんのおしりをすっぽりつつむかたちに改良！</strong><br />おしりをすっぽりつつむかたちになり、元気に動いてもおしりに食い込みにくくなりました。<br />※実際の着用感には個人差があります。</li> <li><strong>もちろん通気性ばっちり！コットンシート</strong><br />ムレを逃がして赤ちゃんのお肌は快適。<br />※“コットンシート”はコットンのような肌ざわりのシートです。コットンは含まれていません。</li> </ul> | G11: http://www.jp.pampers.com/dry_training_pants_Bigsize | H11: http://media25.jp.pampers.com/ja_JP/images/pc/hb/lsp/products/Pants_SJ_XL.png | J11: 4902430148948, 4902430574389 | M11: 2
A12: 15-JP | B12: Pampers JP | C12: 8-JP | D12: Inactive | E12: パンパースのはじめての肌へのいちばん （新生児サイズ） | F12: 妊娠、ご出産おめでとうございます。生まれたての赤ちゃんの肌はとってもデリケート！だからパンパースのはじめての肌へのいちばん。パンパースシリーズは、病産院使用率*No.1 生まれたての赤ちゃんにもお使いいただけます。*当社調査（新生児用データ） | G12: http://dev25.jp.pampers.com/dry_diapers_Newborns | H12: http://dev25.jp.pampers.com/ja_JP/images/pc/hb/products/prod_img_diapers_gallopNB.jpg | M12: 1
A13: 15-JP | B13: Pampers JP | C13: 6-JP | D13: Inactive | E13: パンパース さらさらケアパンツ （ビックサイズ） | F13: 1)90%のママが実感！体型に合ってモレ防止 2) いろんな動きでもモレを防ぐ、のびのびフィット 3) 通気性のいいコットンシート*使用でオムツの中のムレを防ぎます。 * “コットンシート”はコットンのような肌ざわりのシートです。コットンは含まれていません。 | G13: http://www.jp.pampers.com/dry_training_pants_Bigsize | H13: http://media25.jp.pampers.com/ja_JP/images/pc/hb/products/prod_img_diapers_12f4.jpg | M13: 0
A14: 15-JP | B14: Pampers JP | C14: 4902430148597 | D14: Inactive | E14: パンパース さらさらケアテープ（新生児サイズ） | F14: 1) パンパースだけの一枚多いぐっすりシートでもっとすばやくさらさら。吸収力は最長10時間。 2) パンパースだけの素肌と同じ弱酸性のシートで、お肌への刺激を防ぎます。 3) 通気性のいいコットンシートが、ムレを逃がして赤ちゃんのお肌は快適。 * “コットンシート”はコットンのような肌ざわりのシートです。コットンは含まれていません。 | G14: http://www.jp.pampers.com/dry_taped_diapers_Newborns | H14: http://media251.jp.pampers.com/ja_JP/images/pc/hb/products/prod_img_diapers_tappedNB.jpg | J14: 4902430148597, 4902430574419 | M14: 1
A15: 15-JP | B15: Pampers JP | C15: 4902430421911 | D15: Inactive | E15: パンパースのはじめての肌へのいちばん （Sサイズ） | F15: 1) 肌を包むものだから、やわらかさプラス* 生まれたばかりの赤ちゃんをやさしく包んであげるために、コットンのようなやわらかさをオムツにプラス。 思わずさわりたくなるような、なめらかな肌ざわりを追求しました。 ※当社他製品比較 2) 穴あきメッシュでお肌への刺激となるゆるゆるうんちを吸収 生まれたばかりの赤ちゃんのおしりは、とってもかぶれやすい。 肌への刺激となるゆるゆるウンチを吸収し、できるだけ肌にくっつきにくくするために、独自の穴あきメッシュを使いました。 赤ちゃんをオムツかぶれから守ってあげるための、工夫です。 3) 360度※通気性 360度通気するから、ムレを防いでお肌快適。 生まれたばかりの赤ちゃんのお肌をオムツかぶれから守ります。 ※テープ・テープの受け部には通気性がありません。 4) 素肌とおなじ弱酸性の吸収層 パンパース独自の弱酸性の吸収層は、オムツの中を 素肌とおなじ弱酸性に近づける調整機能でおしっこやウンチによるお肌への刺激を防ぎます 5) 最長10時間の吸収力 パンパース独自の一枚多いシートがついて、最長10時間の吸収力 | G15: http://www.jp.pampers.com/dry_diapers_S | H15: http://media25.jp.pampers.com/ja_JP/images/pc/hb/products/prod_img_diapers_gallopS.jpg | J15: 4902430421911 | M15: 2
A16: 15-JP | B16: Pampers JP | C16: 11-JP | D16: Inactive | E16: パンパース ふわふわシート | F16: 素肌とおなじ弱酸性のふわふわシート。 デリケートな赤ちゃんの肌は、うんちやおしっこなど、色々な刺激にさらされています。パンパースのふわふわシートは、赤ちゃんのお肌を健康な素肌と同じ弱酸性に近づけるパンパース独自の成分を配合！敏感な赤ちゃんのお肌への刺激を防ぎます！ やわらかい素材で、デリケートな赤ちゃんの肌をごしごしせずに、ふわふわやさしくふきとれるから、お肌にやさしい。 一枚でたっぷりふける、厚手で大判サイズなのもうれしいですね。 | G16: http://dev25.jp.pampers.com/soft_wipes | H16: http://dev25.jp.pampers.com/ja_JP/images/pc/hb/products/prod_img_wipes_fuwafuwa.jpg | M16: 1
A17: 15-JP | B17: Pampers JP | C17: 7-JP | D17: Inactive | E17: パンパース 卒業パンツ | F17: 1) ぬれた感じがするシート 少量のおしっこを表面にとどめて、ぬれた感じに気づくきっかけをお子様に与えます。 2) パンパースならではのしっかり吸収力 3) 下着みたいなカタチと、男女別デザイン トイレへ誘いやすい しまじろうデザイン！ 全部で8種類のデザイン。1袋に2種類のデザインが入っています。 （まれに混在することがあります | G17: http://www.jp.pampers.com/training_pants | H17: http://media251.jp.pampers.com/ja_JP/images/pc/hb/products/prod_img_pants_trainingpants.jpg | M17: 1
A18: 15-JP | B18: Pampers JP | C18: 4902430522816 | D18: Inactive | E18: パンパースさらさらパンツ（Sサイズ） | F18: <ul> <li><strong>パンパースパンツ史上最高評価</strong><br />10年ぶりの大型改良の新しいパンパースさらさらパンツは、パンパースパンツ史上最高評価を受けました。<br />※Ｍサイズにおける生産ラインを含めた製品改良。</li> <li><strong>さらさらスリムジェル</strong><br />湿気まで吸収してムレさえ肌によせつけない！最長12時間お肌さらさら、朝までぐっすり。</li> <li><strong>やわらかベルトで締めつけ感ゼロへ</strong><br />ベルトがやわらかくなって、赤ちゃんの肌を締めつけずに安心のフィット感を実現しました。</li> <li><strong>赤ちゃんのおしりをすっぽりつつむかたちに改良！</strong><br />おしりをすっぽりつつむかたちになり、元気に動いてもおしりに食い込みにくくなりました。<br />※実際の着用感には個人差があります。</li> <li><strong>もちろん通気性ばっちり！コットンシート</strong><br />ムレを逃がして赤ちゃんのお肌は快適。<br />※“コットンシート”はコットンのような肌ざわりのシートです。コットンは含まれていません。</li> </ul> | G18: http://www.jp.pampers.com/dry_training_pants_S | H18: http://media252.jp.pampers.com/ja_JP/images/pc/hb/lsp/products/Pants_SJ_S.png | J18: 4902430522816, 4902430574297 | M18: 1
A19: 15-JP | B19: Pampers JP | C19: 4902430532921 | D19: Inactive | E19: パンパースパンツ（Sサイズ) | F19: 1) 独自の１枚多いさらさらシート2) 素早く吸収するから、朝までずっと、お肌さらさら。 3) もちろん通気性ばっちり！コットンシート 4)ムレを逃して赤ちゃんのお肌は快適 | G19: http://www.jp.pampers.com/dry_training_pants_S | H19: http://media252.jp.pampers.com/ja_JP/images/pc/hb/lsp/products/prod_image_main_pants_trainingS.png | J19: 4902430522816, 4902430574297 | M19: 0
A20: PAMPERS | B20: Pampers | C20: 4902430148887 | D20: Inactive | E20: パンパース さらさらパンツ | F20: パンパース さらさらパンツ | G20: https://www.jp.pampers.com/star-product/flagship-pants | H20: http://cdn.multibrand.pgsitecore.com/ja-JP/-/media/Pampers/Pampers-JP/Images/Products/Star-Products/Flagship-pants/packshot/FS_Pants_packshot.png?v=1-201605100421 | J20: 4902430157018, 4902430157056, 4902430157087, 4902430540346, 4902430574280, 4902430576277, 4902430576284, 4902430576291, 4902430617475, 4902430617482 | M20: 320
A21: PAMPERS | B21: Pampers | C21: PAMPERS_ONI_ONE_SAN_PANTS | D21: Inactive | E21: おにいさん・おねえさん気分パンツ | F21: おにいさん・おねえさん気分パンツ | G21: https://www.jp.pampers.com/products/oni-san-one-san-pants | H21: https://images.ctfassets.net/fr4hq1ibrhag/8fc5403651dadc269caf7c21d1afcb83be8ecc7f5124f9f96e586c5cc13e6a73/677f7328fe92dac1992356fd70705666/D_ONI_ONE_PANTS_560x390_RETINA | M21: 5
A22: PAMPERS | B22: Pampers | C22: Pampers_premium_line_pants | D22: Inactive | E22: 肌へのいちばんパンツMたっち～XL | F22: 肌へのいちばんパンツMたっち～XL | G22: https://www.jp.pampers.com/products/pampers-premium-line-pants | H22: https://images.ctfassets.net/fr4hq1ibrhag/24vQdxIBJcFKPz647zshJp/99335c3ccb6bc0fcd77cf0989770bd31/packshot_PRMpants_324_286.png | J22: 4902430680349, 4902430680387, 4902430680431, 4902430768603 | M22: 220
A23: PAMPERS | B23: Pampers | C23: LE_tape_preemie_Star | D23: Inactive | E23: パンパースはじめての肌へのいちばん 新生児用小さめ 3000ｇ | F23: パンパースはじめての肌へのいちばん 新生児用小さめ 3000ｇ | G23: https://www.jp.pampers.com/star-product/le-preemie | H23: http://cdn.multibrand.pgsitecore.com/ja-JP/-/media/Pampers/Pampers-JP/Images/Products/Product-Plus/LE_preemie/LE_preemie_packshot.jpg?h=230&w=440&v=1-201612150631&hash=E84E9BC5293A777EFE0C53EB98BC7C3267528256&crop=1&sc=0 | M23: 12
A24: PAMPERS | B24: Pampers | C24: HARAMAKI_PANTS | D24: Inactive | E24: パンパース®はらまきパンツ | F24: パンパース®はらまきパンツ | G24: https://www.jp.pampers.com/products/haramaki-pants | H24: https://images.ctfassets.net/fr4hq1ibrhag/6731d8958053d94bb674bef1e3e14dbc1bc4581841511fcce59d8351c0068750/ab958e1bf127dac0aa3e9fba1534de11/D_HARAMAKI_PANTS_560x390_RETINA | J24: 4902430686297, 4902430686815, 4902430686839, 4902430686877, 4902430686891, 4902430686907 | M24: 1
A25: PAMPERS | B25: Pampers | C25: 4902430177283 | D25: Inactive | E25: パンパース 卒業パンツ | F25: パンパース 卒業パンツ | G25: https://www.jp.pampers.com/product/toilet-training | H25: http://cdn.multibrand.pgsitecore.com/ja-JP/-/media/Pampers/Pampers-JP/Images/Products/Product-Plus/toilet_training/mv.png?v=1-201710120225 | J25: 4902430177283, 4902430177290 | M25: 12
A26: PAMPERS | B26: Pampers | C26: Pampers_Summer_Pants | D26: Inactive | E26: さらさら風通しパンツ | F26: さらさら風通しパンツ | G26: https://www.jp.pampers.com/products/kazetoushi | H26: https://images.ctfassets.net/fr4hq1ibrhag/1ucyWBLwtzdFVUMgHYMQ0K/b6b31574c9eb1ce3e9b0b1f92731b715/packshot_resize-removebg_0316.png | J26: 4987176039736, 4987176039743, 4987176039750, 4987176039767, 4987176039774, 4987176039781 | M26: 1
A27: PAMPERS | B27: Pampers | C27: Pampers_premium_line_tape | D27: Inactive | E27: はじめての肌へのいちばんテープ | F27: はじめての肌へのいちばんテープ | G27: https://www.jp.pampers.com/products/pampers-premium-line-tape | H27: https://images.ctfassets.net/fr4hq1ibrhag/5ZOqSNvhCLPiDuTaEYIcdq/d131f6ec3a67fbbd4cac068a0b2c96d9/TOP-Tape-S54_324x286.png | J27: 4902430679114, 4902430679138, 4902430679152, 4902430679176 | M27: 266
A28: PAMPERS | B28: Pampers | C28: Pampers_main_line_nightpants | D28: Inactive | E28: おやすみパンツ | F28: おやすみパンツ | G28: https://www.jp.pampers.com/products/pampers-oyasumipants | H28: https://images.ctfassets.net/fr4hq1ibrhag/3KA5iba2FMvUGKrrTOHUvS/6c4e9980fc35255a7742e4c3ab2d4ad7/Product-List-Oyasumi_324x286.png | J28: 4987176077172, 4987176077219, 4987176079381 | M28: 27
A29: PAMPERS | B29: Pampers | C29: 4-JP | D29: Inactive | E29: パンパース さらさらケア テープ | F29: パンパース さらさらケア テープ | G29: https://www.jp.pampers.com/star-product/flagship-tape | H29: http://cdn.multibrand.pgsitecore.com/ja-JP/-/media/Pampers/Pampers-JP/Images/Products/Star-Products/Flagship-tape/mainPackShot.png?v=1-201510072352 | J29: 4902430156882, 4902430156912, 4902430156943, 4902430156974, 4902430576307, 4902430576314, 4902430576321, 4902430576338 | M29: 153
A30: PAMPERS | B30: Pampers | C30: Pampers_LeadingEdge_Star | D30: Inactive | E30: パンパースのはじめての肌へのいちばん（テープ） | F30: パンパースのはじめての肌へのいちばん（テープ） | G30: https://www.jp.pampers.com/star-product/leading-edge | H30: http://cdn.multibrand.pgsitecore.com/ja-JP/-/media/Pampers/Pampers-JP/Images/Products/Product-Plus/LE-tape/LE_tape_packshot.jpg?h=230&w=440&v=1-201705150644&crop=1&sc=0 | J30: 4902430421904, 4902430421928, 4902430422291, 4902430422307 | M30: 727
A31: PAMPERS | B31: Pampers | C31: Pampers_toilet_training | D31: Inactive | E31: パンパース® 卒業パンツ | F31: パンパース® 卒業パンツ | G31: https://www.jp.pampers.com/products/pampers-toilet-training-pants | H31: https://images.ctfassets.net/fr4hq1ibrhag/7a105821e68c7918013b42bd6a242c28216011814a962e097433039f5deefcd1/026c9810f1a3f8572408e65028c8f218/D_TOILET_TRAINING_560x390_RETINA | J31: 4902430651950, 4902430651967 | M31: 20
A32: PAMPERS | B32: Pampers | C32: Pampers_main_line_tape | D32: Inactive | E32: さらさらケア テープ | F32: さらさらケア テープ | G32: https://www.jp.pampers.com/products/pampers-mainline-tape | H32: https://images.ctfassets.net/fr4hq1ibrhag/5UaHZ8llzduzPFSNEIXy3A/bc956253ccb9a49901f3afc8c64ea4d1/TOP-newborn-S_324x286.png | J32: 4902430574419, 4902430574433, 4902430574457, 4902430574471 | M32: 247
A33: PAMPERS | B33: Pampers | C33: 4902430599245 | D33: Inactive | E33: パンパースしっかり吸収パンツ | F33: パンパースしっかり吸収パンツ | G33: https://www.jp.pampers.com/star-product/value-tier | H33: http://cdn.multibrand.pgsitecore.com/ja-JP/-/media/Pampers/Pampers-JP/Images/Products/Primary/ValueTier_opened.png?v=1-201510071337 | J33: 4902430599245, 4902430599269 | M33: 11
A34: PAMPERS | B34: Pampers | C34: FS_pants_xxl_Star | D34: Inactive | E34: パンパース さらさらパンツ ビッグより大きいサイズ | F34: パンパース さらさらパンツ ビッグより大きいサイズ | G34: https://www.jp.pampers.com/product/fs-pants-xxl | H34: http://cdn.multibrand.pgsitecore.com/ja-JP/-/media/Pampers/Pampers-JP/Images/Products/Product-Plus/FS_pants_xxl/FS_pants_xxl_packshot.jpg?h=215&w=355&v=1-201612150506&hash=0CE6725A52B5DEF985388F27352485181115E892&crop=1&sc=0 | M34: 3
A35: PAMPERS | B35: Pampers | C35: pampers_main_line_pants | D35: Inactive | E35: さらさらケアパンツ Mたっち～XXL | F35: さらさらケアパンツ Mたっち～XXL | G35: https://www.jp.pampers.com/products/pampers-main-line-pants | H35: https://images.ctfassets.net/fr4hq1ibrhag/4q6qp26wzIb9cpxayTzZ27/6655f810d07803c4a2e87a722bb2c8e5/TOP-saracare-pants_324x286.png | J35: 4902430574327, 4902430574358, 4902430574389, 4902430756075 | M35: 449
A36: PAMPERS | B36: Pampers | C36: Pampers_LeadingEdgePants_Star | D36: Inactive | E36: パンパースの肌へのいちばん（パンツ） | F36: パンパースの肌へのいちばん（パンツ） | G36: https://www.jp.pampers.com/star-product/leading-edge-pants | H36: http://cdn.multibrand.pgsitecore.com/ja-JP/-/media/Pampers/Pampers-JP/Images/Products/Product-Plus/LE-pants/LE_pants_packshot.jpg?h=230&w=440&v=1-201706151250&crop=1&sc=0 | M36: 356
A37: PAMPERS | B37: Pampers | C37: 4902430707046 | D37: Inactive | E37: 肌へのいちばん おしりふき | F37: 肌へのいちばん おしりふき | G37: https://www.jp.pampers.com/products/pampers-wipe | H37: https://images.ctfassets.net/fr4hq1ibrhag/VRrb9U22MAHrvcrTqNhAg/d96d788b0837d58cdaedcaed58f4589e/Wipe_324x286.png | J37: 4902430707046 | M37: 245
A38: PAMPERS_JP | B38: Pampers | C38: 4902430368988 | D38: Inactive | E38: パンパースのはじめての肌への一番 | F38: パンパースのはじめての肌への一番 | J38: 4902430421904, 4902430421928, 4902430422291, 4902430422307 | M38: 7
C39: PAMPERS_OYASUMIPANTS_XXXL | D39: Inactive | M39: 2
C40: Pampers_Swaddlers | D40: Inactive | M40: 0

Sheet pampers-de_de
A1: Bazaarvoice
A2: Pampers-DE_DE R&R Key Metrics
A3: Run Date: Aug 12, 2026 12:00 AM UTC
A4: Instance: pampers-de_de
A5: Date range: All Time
A6: Date field: Review Submission Date
A7: Brand ID | B7: Brand | C7: Product ID | D7: Product Status | E7: Product Name | F7: Description | G7: Product Page URL | H7: Image URL | I7: UPC | J7: EAN | K7: Product Family | L7: Product Family - Expand | M7: # Approved Reviews
A8: 8-DE | B8: Pampers DE | C8: 711155945-DE | D8: Inactive | E8: Pampers Sensitive Feuchttücher | F8: Sanftere Reinigung mit weniger Wischen | G8: http://www.pampers.de/sensitive-feuchttuecher | H8: http://www.pampers.de/de_DE/images/pc/hb/lsp/products/prod_image_main_wipes_sensitive.png | M8: 4
A9: 8-DE | B9: Pampers DE | C9: 17-DE | D9: Inactive | E9: Pampers Baby Fresh Feuchttücher | F9: Die Pampers Baby Fresh Feuchttücher bieten ein extra sauberes Gefühl mit jedem Wisch. Die besondere Lotion enthält Aloe und einen erfrischenden Duft und hilft, die natürliche Balance der Haut wiederherzustellen. Die Pampers Baby Fresh Feuchttücher sind dermatologisch getestet, enthalten keine Seife und kein Alkohol und reinigen jedes Hautfältchen gründlich. | G9: http://www.pampers.de/pampers-baby-fresh-wipes | H9: http://www.pampers.de/de_DE/images/pc/hb/lsp/products/prod_image_main_wipes_babywipes.png | M9: 2
A10: PAMPERS | B10: Pampers | C10: PAMPERS_99WATER | D10: Active | E10: Pampers® Harmonie™ Aqua Feuchttücher | F10: Pampers® Harmonie™ Aqua Feuchttücher | G10: https://www.pampers.de/produkte/pampers-aqua-feuchttucher | H10: https://images.ctfassets.net/vvzbftwk9keg/6LQMGnoGn8C9CKFFpcADLS/2b21ff75bd78c15087f70ba9e1083dc2/pdp_pampers_aqua_no_back.png | J10: 8006530116596, 8006530116305, 8006530116152, 8700216722476, 8006540458563, 8006540510247, 8006530116206, 8006540811245, 8006540556139, 8006540811276, 8006530116558, 8006530116374, 8006540826669, 8006530116459, 8006540458525 | M10: 452
A11: PAMPERS | B11: Pampers | C11: PAMPERS_BABY_DRY | D11: Active | E11: Pampers® Baby-Dry™ | F11: Pampers® Baby-Dry™ | G11: https://www.pampers.de/produkte/pampers-baby-dry-windeln | H11: https://images.ctfassets.net/vvzbftwk9keg/4eLa3r137a1khLxJ0utwiM/49c3ba2597f81e06013abcfa82bb26d4/pdp_pampers_bd_taped_no_back.png | J11: 8006530288972, 8700216968829, 8006530381581, 8006530160537, 8006530143677, 8700216754170, 8700216812580, 8700216793230, 8700216812733, 8700216713436, 8700216754293, 8700216793421, 8006540785164, 8006530288958, 8006530140737, 8006540785133, 8700216812658, 8006530143394, 8700216291149, 8006530140522, 8700216812368, 8006530140683, 8700216793285, 8006530160605, 8006530160568, 8006530288965, 8700216713351, 8700216878029, 8006530143219, 8700216713337, 8700216812382, 8006530143264, 8700216146708, 8006530140416, 8700216968799, 8700216793469, 8700216812610, 8006530160599, 8006530140638, 8700216713160, 8006530143561, 8006530143868, 8006530144087, 8006530143691, 8700216793476, 8006530143998, 8700216754224, 8700216793353, 8700216713405, 8700216754149, 8700216812474, 8006530143738, 8006530143608, 8700216754156, 8006530143462, 8006530143943, 8006530160483, 8700216812726, 8700216713085, 8006530143554, 8006530381512, 8006530143301, 8700216754538, 8700216713238, 8006530143448, 8006530143813, 8700216812764, 8006530143523, 8700216812481, 8700216968812, 8006530143325, 8700216878005, 8700216775793, 8006530144056, 8006540861691, 8700216877985, 8006530160551, 8006530288927, 8700216793315, 8700216146715, 8006530143509, 8006530143653, 8700216775748, 8006530143639, 8006540785065, 8006530140782, 8700216877992, 8700216713139, 8006530381543, 8700216754323, 8700216793438, 8700216793377, 8006530140461, 8006540785188, 8006530160421, 8006530143400, 8006530143899, 8006530160629, 8700216713306, 8006530140515, 8006540785119, 8006530143240, 8006530289009, 8006530143721, 8006530144049, 8006540785089, 8700216754088, 8006530140720, 8700216793247, 8700216812405, 8006530143974, 8700216754361, 8006540785034, 8006530143349, 8006530160650, 8700216754125, 8006530143905, 8700216775755, 8006530381536, 8700216146654, 8006540785003, 8006530143967, 8700216812672, 8006530140805, 8700216754422 | M11: 11093
A12: PAMPERS | B12: Pampers | C12: PAMPERS_HARMONIE | D12: Active | E12: Pampers® Harmonie™ Windeln | F12: Pampers® Harmonie™ Windeln | G12: https://www.pampers.de/produkte/pampers-harmonie-windeln | H12: https://images.ctfassets.net/vvzbftwk9keg/6cBzbstT7yuxjDcafH0mbT/287dfdc63346812f1e63f19602215bd8/pdp_pampers_harmonie_taped_no_back.png | J12: 8700216668224, 8006540867921, 8700216668477, 8700216668194, 8700216668347, 8700216668729, 8700216668699, 8700216668255, 8700216251259, 8700216668163, 8700216668156, 8700216668675, 8700216668767, 8700216668323, 8006540867808, 8006540867891, 8700216251235, 8700216668231, 8700216668798, 8700216668149, 8006540987230 | M12: 908
A13: PAMPERS | B13: Pampers | C13: PAMPERS_SENSITIVE | D13: Active | E13: Pampers® Sensitive™ Feuchttücher | F13: Pampers® Sensitive™ Feuchttücher | G13: https://www.pampers.de/produkte/pampers-sensitive-feuchttucher | J13: 8001841062792, 8001841063188, 8006530134668, 8006530134750, 8001841041452, 8001841041391, 8001841062754, 8006540174531, 8006530134521, 8001841041421, 8001841041483 | M13: 1
A14: PAMPERS | B14: Pampers | C14: SPLASHERS_BABY_SHARK | D14: Active | E14: Pampers® Splashers Baby Shark™ Schwimmwindeln | F14: Pampers® Splashers Baby Shark™ Schwimmwindeln | G14: https://www.pampers.de/produkte/pampers-splashers | H14: https://images.ctfassets.net/vvzbftwk9keg/1QZPrLHNFMLQ5XA2yUksEs/803028d271beebd6d55e3a3cb4c4236b/pdp_pampers_splashers_no_back.png | J14: 8001090698346, 8001090698384, 8001090728951 | M14: 1
A15: PAMPERS | B15: Pampers | C15: PREMIUM_PROTECTION_PANTS | D15: Active | E15: Pampers® Premium Protection™ Pants | F15: Pampers® Premium Protection™ Pants | G15: https://www.pampers.de/produkte/pampers-premium-protection-pants | H15: https://images.ctfassets.net/vvzbftwk9keg/4QX7500kYRGUIOZUk2JaZA/b0ac803fcf132fb0c223688c49bbf154/pdp_pampers_pp_pants_no_back.png | J15: 8700216664332, 8700216679381, 8700216679176, 8006530286824, 8006530288644, 8006530283298, 8006540759059, 8006530288576, 8700216679435, 8006540710517, 8006530283311, 8700216679183, 8700216679121, 8700216679268, 8006540710494, 8700216679404, 8700216679336, 8700216679466, 8006540710531, 8006530288613, 8700216679275, 8700216679107, 8700216679312, 8006530283335, 8700216679091 | M15: 23
A16: PAMPERS | B16: Pampers | C16: PAMPERS_HARMONIE_PANTS | D16: Active | E16: Pampers® Harmonie Pants™ | F16: Pampers® Harmonie Pants™ | G16: https://www.pampers.de/produkte/pampers-harmonie-pants | H16: https://images.ctfassets.net/vvzbftwk9keg/12sSn2gGyrKGJHUKv3Ztr9/680210be9161ec0303cce953e3d936b0/pdp_pampers_harmonie_pants_no_back.png | J16: 8006540867952, 8006540867976, 8006540867990 | M16: 1
A17: PAMPERS | B17: Pampers | C17: PAMPERS_COCONUT_PURE_WIPES | D17: Inactive | E17: Pampers Harmonie Coconut Feuchttücher | F17: Pampers Harmonie Coconut Feuchttücher | G17: https://www.pampers.de/produkte/pampers-coconut-pure-wipes | H17: https://images.ctfassets.net/vvzbftwk9keg/tKoGMlP0kFta864qGJrJm/5375cd6e73d8a2f33272f874c5c03a14/324x286px_wipes_coco.png | J17: 8006540810286, 8006540810347, 8006540810361, 8006540815533, 8006540986165 | M17: 5
A18: PAMPERS | B18: Pampers | C18: PAMPERS_NEW_BABY_SENSITIVE | D18: Inactive | E18: Pampers New Baby Sensitive | F18: Pampers New Baby Sensitive | G18: https://www.pampers.de/starprodukt/pampers-new-baby-sensitive | H18: http://cdn.multibrand.pgsitecore.com/de-DE/-/media/Pampers/Pampers-DE/Images/Products/StarProduct/New-baby-sensitive/New-Baby-Sensitive-Packshot.png?v=1-201608021159 | J18: 4015400835813, 4015400835899 | M18: 373
A19: PAMPERS | B19: Pampers | C19: 7-DE | D19: Inactive | E19: Kandoo | F19: Kandoo | G19: https://www.pampers.de/regulares-produkt/kandoo | H19: http://cdn.multibrand.pgsitecore.com/de-DE/-/media/Pampers/Pampers-DE/Images/Products/Regular-Products/Primary/Kandoo_630x330.png?v=1-201503251056 | M19: 45
A20: PAMPERS | B20: Pampers | C20: 21-DE | D20: Inactive | E20: Pampers Bed Mats | F20: Pampers Bed Mats | G20: https://www.pampers.de/regulares-produkt/pampers-bedmats | H20: http://cdn.multibrand.pgsitecore.com/de-DE/-/media/Pampers/Pampers-DE/Images/Products/Regular-Products/Primary/BedMats_630x330.png?v=1-201608021159 | J20: 4015400333449 | M20: 27
A21: PAMPERS | B21: Pampers | C21: 19-DE | D21: Inactive | E21: FEUCHTTÜCHER Pampers® New Baby Sensitive™ Feuchttücher | F21: FEUCHTTÜCHER Pampers® New Baby Sensitive™ Feuchttücher | G21: https://www.pampers.de/produkte/pampers-new-baby-sensitive-feuchttucher | J21: 4015400623496, 4015400623588, 4015400670414 | M21: 1004
A22: PAMPERS | B22: Pampers | C22: 711155922-DE | D22: Inactive | E22: Pampers® Premium Protection™ New Baby | F22: Pampers® Premium Protection™ New Baby | G22: https://www.pampers.de/produkte/pampers-premium-protection-new-baby-windeln | H22: https://images.ctfassets.net/vvzbftwk9keg/79vDe4dEQ6447LkqcDtwuV/e0b668a3b776f624962f5274e56b30f0/324x286px_pp_daipers.png | J22: 8006540705513, 8006540705544, 8700216207423, 8700216207614, 8700216207645, 8700216207669, 8700216359122, 8700216359177, 8700216359207 | M22: 2821
A23: PAMPERS | B23: Pampers | C23: PAMPERS_PREMIUM_PROTECTION | D23: Active | E23: Pampers® Premium Protection™ Windeln | F23: Pampers® Premium Protection™ Windeln | G23: https://www.pampers.de/produkte/pampers-premium-protection-windeln | H23: https://images.ctfassets.net/vvzbftwk9keg/4rKAXdGJRKOAWHWDXQ31ml/dcd1a73a6652915fe29be6b4922af079/pdp_pampers_pp_taped_no_back.png | J23: 8006530131780, 8006530256797, 8006530189842, 8700216664554, 8700216664752, 8700216664585, 8006540705674, 8006530107105, 8700216664905, 8006530189866, 8006530132084, 8006530131605, 8006530256773, 8700216679015, 8700216665056, 8700216664448, 8006530189903, 8006530189804, 8006530131919, 8700216664479, 8700216665216, 8700216665162, 8006540705513, 8700216664936, 8700216665117, 8006530131148, 8006530131315, 8006530132114, 8006530131889, 8006530131650, 8700216418195, 8006530131964, 8006530152105, 8700216664899, 8700216665100, 8006530256698, 8700216664769, 8006530131766, 8006530152143, 8700216664721, 8006530131834, 8006530131575, 8700216664684, 8006530256810, 8700216664776, 8006530131506, 8006540705643, 8700216664844, 8006530131711, 8006530131216, 8006530132176, 8006530131360, 8006530131421, 8700216665193, 8006530189835, 8006530131469, 8006530132251, 8006530131629, 8006530256742, 8006530132008, 8006530131209, 8700216664677, 8006530256865, 8006530132374, 8006530256827, 8006530131179, 8006540705612, 8700216664509, 8700216665261, 8006530132169, 8006540705575, 8006530131681, 8006530107099, 8006530256704, 8006530132299, 8700216665308, 8006530152150, 8006530152181, 8700216664615, 8006530256735, 8006530131988, 8700216664547, 8006530131353, 8006530256841, 8006530107129, 8006540705544, 8006530132206, 8700216664622, 8700216664431, 8700216665001, 8006530132282, 8006530132350, 8006530131803, 8700216664370 | M23: 5949
A24: PAMPERS | B24: Pampers | C24: 22-DE | D24: Inactive | E24: Pampers Change Mats | F24: Pampers Change Mats | G24: https://www.pampers.de/regulares-produkt/pampers-changemats | H24: http://cdn.multibrand.pgsitecore.com/de-DE/-/media/Pampers/Pampers-DE/Images/Products/Regular-Products/Primary/ChangeMats_630x330.png?v=1-201608021159 | J24: 4015400827481 | M24: 93
A25: PAMPERS | B25: Pampers | C25: PSP-DE | D25: Inactive | E25: WINDELN Pampers Sleep and Play | F25: WINDELN Pampers Sleep and Play | G25: https://www.pampers.de/produkte/pampers-sleep-and-play-windeln | H25: http://cdn.multibrand.pgsitecore.com/de-DE/-/media/3D6658D8A0BF4E75B3E2D050FABCF4E1.ashx | J25: 4015400885399, 4015400886570, 4015400887140, 4015400887270, 4015400887539, 4015400888086, 4015400890300, 4015400892342 | M25: 126
A26: PAMPERS | B26: Pampers | C26: Pampers_Active_Fit_2 | D26: Inactive | E26: WINDELN Pampers Premium Protection Active Fit | F26: WINDELN Pampers Premium Protection Active Fit | G26: https://www.pampers.de/produkte/pampers-premium-protection-active-fit-windeln | H26: https://res.cloudinary.com/pmprs/image/upload/c_scale,f_auto,q_60/v20191209235035/pampersc1/de-de/-/media/pampers/pampers-de/images/products/product-oasis/closed-module/premium-protection-active-fit/closedmodule-activefit-de.png?v=1-201709211110 | J26: 4015400617778, 4015400617792, 4015400622543, 4015400696377, 4015400696407, 4015400696438, 4015400696469 | M26: 535
A27: PAMPERS | B27: Pampers | C27: PAMPERS_BABY_DRY_NIGHT_PANTS | D27: Active | E27: Pampers® Night Pants™ | F27: Pampers® Night Pants™ | G27: https://www.pampers.de/produkte/pampers-baby-dry-night-pants | H27: https://images.ctfassets.net/vvzbftwk9keg/26CEkGeBxZxiGU2nPmVHve/33e15bfb8973c16a580ee2270e52c2f2/pdp_pampers_night_pants_no_back.png | J27: 8006530256599, 8006530256278, 8006530256353, 8006530253147, 8700216669757, 8700216669887, 8700216958073, 8006530256575, 8006530253376, 8006530021173, 8006530021296, 8006530253437, 8006540711828, 8006530256537, 8006530256292, 8006530256346, 8006530253390, 8006530256643, 8700216958066, 8700216669832, 8006530253338, 8006530021210, 8006540710739, 8006530253468, 8700216958080, 8700216669764, 8006530253109, 8700216669696, 8006530189033, 8006540711309, 8006530256247, 8006530256551, 8006530021227, 8006530021241, 8006530256254, 8700216669795, 8006530253185, 8006530317894, 8006530021289, 8006530253314 | M27: 267
A28: PAMPERS | B28: Pampers | C28: Pampers_Splashers_Diapers | D28: Inactive | E28: Pampers Splashers | F28: Pampers Splashers | G28: https://www.pampers.de/regulares-produkt/pampers-splashers | H28: http://cdn.multibrand.pgsitecore.com/de-DE/-/media/Pampers/Pampers-DE/Images/Products/Regular-Products/Primary/540x327_01.png?v=1-201704131358 | J28: 8001090468093, 8001090468154, 8001090468710 | M28: 2
A29: PAMPERS | B29: Pampers | C29: 15-DE | D29: Inactive | E29: Pampers UnderJams Pyjama Pants - boys | F29: Pampers UnderJams Pyjama Pants - boys | G29: https://www.pampers.de/regulares-produkt/pampers-uderjams-pyjama-pants---boys | H29: http://cdn.multibrand.pgsitecore.com/de-DE/-/media/Pampers/Pampers-DE/Images/Products/Regular-Products/Primary/underjams_Boys_630x330.png?v=1-201608021159 | J29: 4015400345022, 4015400345275 | M29: 10
A30: PAMPERS | B30: Pampers | C30: PAMPERS_FRESH_CLEAN | D30: Active | E30: Pampers® Fresh Clean™ Feuchttücher | F30: Pampers® Fresh Clean™ Feuchttücher | G30: https://www.pampers.de/produkte/pampers-fresh-clean-feuchttucher | H30: https://images.ctfassets.net/vvzbftwk9keg/f4S2CMtEjG0QL7rzkvSCj/0a367e37f99dd6d685d48e0566d03e57/pdp_pampers_freshclean_no_back.png | J30: 8001841077598, 8006530134422, 8001841078441, 8001841078175, 8006530134583, 8006540174746, 8001841078052, 8006530134552, 8001841078137, 8001841078496, 8001841041360 | M30: 519
A31: PAMPERS | B31: Pampers | C31: 16-DE | D31: Inactive | E31: Pampers UnderJams Pyjama Pants - girls | F31: Pampers UnderJams Pyjama Pants - girls | G31: https://www.pampers.de/regulares-produkt/pampers-underjams-pyjama-pants---girls | H31: http://cdn.multibrand.pgsitecore.com/de-DE/-/media/Pampers/Pampers-DE/Images/Products/Regular-Products/Primary/Underjams_Girls_630x330.png?v=1-201608021159 | J31: 4015400345053, 4015400345305 | M31: 7
A32: PAMPERS | B32: Pampers | C32: PAMPERS_BABY_DRY_PANTS | D32: Active | E32: Pampers® Baby-Dry™ Pants | F32: Pampers® Baby-Dry™ Pants | G32: https://www.pampers.de/produkte/pampers-baby-dry-pants | H32: https://images.ctfassets.net/vvzbftwk9keg/2PyrigU93zoJ7VPTV7p0Un/eee4673842f3482412f3ac9901e032d4/pdp_pampers_bd_pants_no_back.png | J32: 8006530258821, 8006540710791, 8700216670531, 8006530204033, 8006530288491, 8006530204057, 8006530288538, 8006530288668, 8006530204132, 8006530253260, 8700216670500, 8006530256117, 8006530204088, 8006540711408, 8700216705301, 8006530254328, 8700216670418, 8700216670630, 8700216670555, 8006530256513, 8700216596701, 8700216614214, 8700216595841, 8006530385237, 8006530256469, 8006530256483, 8006530385282, 8700216670609, 8006530253482, 8700216670685, 8700216670647, 8006530253017, 8006530253215, 8006530276320, 8006530253079, 8006530254397, 8006540711781, 8006530385305, 8006530288545, 8006540710876, 8700216670517, 8700216614252, 8700216595810, 8006530253284, 8700216670371, 8006530253031, 8006530258869, 8006530254427, 8006540711248, 8006530258852, 8700216596671, 8700216595858, 8006530385343, 8700216670463, 8700216670401, 8006540711385, 8006530256421, 8700216596725, 8006540711767, 8006530204194, 8006530256391, 8700216929721, 8006530256124, 8006530253239, 8700216614290, 8006530254359, 8700216595681, 8700216595773, 8700216670593, 8006530253246, 8700216929691, 8006530256100, 8700216595759, 8700216596596, 8700216670456, 8006540711156, 8700216595704, 8700216596633, 8006530253130, 8006530288453, 8700216595629, 8006530253055 | M32: 2031
A33: PAMPERS | B33: Pampers | C33: PAMPERS_NINJAMAS_PYJAMA_PANTS | D33: Inactive | E33: NINJAMAS PYJAMA PANTS | F33: NINJAMAS PYJAMA PANTS | G33: https://www.pampers.de/produkte/pampers-ninjamas-pyjama-pants | H33: https://images.ctfassets.net/vvzbftwk9keg/3se9ssBRj7cJEAke26LSw2/23994cbc4eda6e0d81e2c6ff1e93d5d0/324x286px_ninjamas_boys.png | J33: 8006540630464, 8006540630488, 8006540630518, 8006540630549, 8006540630563, 8006540630587, 8006540630617, 8006540630648 | M33: 300
A34: PAMPERS | B34: Pampers | C34: 711155944-DE | D34: Inactive | E34: Pampers Simply Dry | F34: Pampers Simply Dry | G34: https://www.pampers.de/regulares-produkt/pampers-simply-dry | H34: http://cdn.multibrand.pgsitecore.com/de-DE/-/media/Pampers/Pampers-DE/Images/Products/Regular-Products/Primary/Simply_Dry_UNICEF_635x330.png?v=1-201608021159 | J34: 4015400549710, 4015400549741, 4015400549802, 4015400613909, 4015400686484, 4015400687030, 4015400687078, 4015400687092 | M34: 344
A35: PAMPERS_DE | B35: Pampers | C35: 3-DE | D35: Inactive | E35: Pampers Easy Up | F35: Pampers Easy Up | J35: 4015400535942, 4015400535973, 4015400536000, 4015400536031, 4015400536062, 4015400536277, 4015400536291 | M35: 9
A36: PAMPERS_DE | B36: Pampers | C36: 711155941-DE | D36: Inactive | E36: Pampers Active Fit | F36: Pampers Active Fit | J36: 4015400557456, 4015400557487, 4015400557517, 4015400557548, 4015400557579, 4015400617693, 4015400617778, 4015400617792, 4015400618232, 4015400618256, 4015400618270, 4015400618836, 4015400618898, 4015400618928, 4015400618959, 4015400619543, 4015400619574, 4015400619604, 4015400619635, 4015400619666, 4015400619697, 4015400622543, 4015400691969, 4015400696315, 4015400696377, 4015400696407, 4015400696438, 4015400696469, 4015400703327, 4015400729204 | M36: 850
A37: PAMPERS_DE | B37: Pampers | C37: 711155943-DE | D37: Inactive | E37: Pampers Baby-Dry | F37: Pampers Baby-Dry | G37: http://www.pampers.de/starprodukt/pampers-baby-dry | J37: 4015400689379, 4015400695578, 4015400695592, 4015400695615, 4015400695653, 4015400695677, 4015400695691, 4015400695714, 4015400695769, 4015400695783, 4015400695806, 4015400695837, 4015400696155, 4015400696186, 4015400696216, 4015400696247, 4015400705130, 4015400705161, 4015400717416, 4015400729624, 4015400729655, 4015400729679, 4015400730804 | M37: 2555
C38: 6-DE | D38: Inactive | M38: 1
C39: 10-DE | D39: Inactive | M39: 1
C40: 9-DE | D40: Inactive | M40: 15
C41: 1-DE | D41: Inactive | M41: 26
C42: 4-DE | D42: Inactive | M42: 42
C43: 2-DE | D43: Inactive | M43: 17

Sheet pampers-es
A1: Bazaarvoice
A2: Pampers-ES R&R Key Metrics
A3: Run Date: Aug 12, 2026 12:00 AM UTC
A4: Instance: pampers-es
A5: Date range: All Time
A6: Date field: Review Submission Date
A7: Brand ID | B7: Brand | C7: Product ID | D7: Product Status | E7: Product Name | F7: Description | G7: Product Page URL | H7: Image URL | I7: UPC | J7: EAN | K7: Product Family | L7: Product Family - Expand | M7: # Approved Reviews
A8: 16n8p5scqgr7lpve64m2tvx8c | B8: Pampers | C8: 930832 | D8: Inactive | E8: Toallitas con manzanilla ThickCare Touch de Pampers | F8: Las toallitas húmedas Pampers ThickCare son hipoalergénicas Las toallitas húmedas ThickCare son sobre 50% más resistentes que Huggies Natural Care* Textura gruesa y acolchada Limpia como un pañito con agua | G8: http://es.pampers.com/thickcare-touch-of-chamomile-wipes | H8: https://www.pampers.com/es_US/images/pc/hb/products/prod_img_wipes_pampers_thickcare_chamomile_NA.jpg | I8: 037000298854 | M8: 1
A9: 16n8p5scqgr7lpve64m2tvx8c | B9: Pampers | C9: 930814 | D9: Inactive | E9: Toallitas frescas para bebé SoftCare de Pampers | F9: Las toallitas húmedas SoftCare limpian suavemente como un pañito de bebé con agua Tienen agua pura y loción con vitamina E Las toallitas Pampers SoftCare son hipoalergénicas Con fragancia agradable a talco de bebé Miles de celditas limpiadoras suaves para ayudar a dejar la piel del bebé sintiéndose perfectamente limpia | G9: http://es.pampers.com/softcare-baby-fresh-wipes | H9: https://www.pampers.com/es_US/images/pc/hb/products/prod_img_wipes_babyfresh_NA.jpg | I9: 037000060826 | M9: 1
A10: 16n8p5scqgr7lpve64m2tvx8c | B10: Pampers | C10: 261054781 | D10: Inactive | E10: Pampers® Cruisers con diseños de USA | F10: Nuevos diseños de USA de edición limitada Sus tres areas de ajuste le dan a tu bebé toda la libertad para jugar a su manera Hasta 12 horas de protección contra derrames | G10: http://es.pampers.com/pampers-cruisers-usa-prints | H10: https://www.pampers.com/es_US/images/pc/hb/products/prod_img_diapers_cruiser_usa_NA.jpg | I10: 037000830122, 037000830139, 037000830146 | M10: 1
A11: 16n8p5scqgr7lpve64m2tvx8c | B11: Pampers | C11: 10930814 | D11: Inactive | E11: Toallitas frescas para bebé SoftCare de Pampers | F11: Las toallitas húmedas SoftCare limpian suavemente como un pañito de bebé con agua Tienen agua pura y loción con vitamina E Las toallitas Pampers SoftCare son hipoalergénicas Con fragancia agradable a talco de bebé Miles de celditas limpiadoras suaves para ayudar a dejar la piel del bebé sintiéndose perfectamente limpia | G11: http://es.pampers.com/softcare-baby-fresh-wipes | H11: https://www.pampers.com/es_US/images/pc/hb/products/prod_img_wipes_babyfresh_NA.jpg | I11: 037000060826 | M11: 2
A12: 16n8p5scqgr7lpve64m2tvx8c | B12: Pampers | C12: 10930827 | D12: Inactive | E12: Pañales Pampers® Swaddlers | F12: Indicador de humedad que cambia de color (tamaños NB, 1, 2) La elección #1 de los hospitales (basado en los datos de venta) Suavidad acolchada parecida a una cobjita envuelve a los bebés en comodidad y seguridad Lados elásticos suaves y cierres sobrepuestos brindan un ajuste flexible a los infantes Apertura para el cordón umbilical (tamaño NB solamente) | G12: http://es.pampers.com/new-baby-diapers-swaddlers | H12: https://www.pampers.com/es_US/images/pc/hb/products/prod_img_diapers_swaddlers_NA.jpg | I12: 037000285199, 037000285229, 037000285502, 037000348955, 037000397984 | M12: 3
A13: 16n8p5scqgr7lpve64m2tvx8c | B13: Pampers | C13: 930824 | D13: Inactive | E13: Pañales Pampers Prints Limited Edition para niños y niñas | F13: Dos diseños divertidos en cada caja: diamantes y autos para los niños; flores y lunares para las niñas La misma absorbencia y ajuste que ya conoces y te gusta de los pañales Pampers Disponible en tamaño 1/2, 3 y 4 para que tu bebé esté a la moda en todas las etapas Lados súper elásticos para un ajuste flexible Fun diapers that make great baby shower gifts | G13: http://www.pampers.com/es_US/proddetail/id/930824 | H13: http://www.pampers.com/es_US/products/new_layout/images/Nprd_print_new.gif | I13: 037000500964, 037000500971, 037000501022, 037000501053, 037000503354, 037000503361 | M13: 3
A14: 16n8p5scqgr7lpve64m2tvx8c | B14: Pampers | C14: 261044173 | D14: Inactive | E14: Toallitas húmedas desechables Kandoo | F14: Limpia hasta 30% mejor que el papel de baño Perfecto para manos pequeñas- aproximadamente del tamaño de dos láminas de papel de baño Toallitas Smellin' Melon, Magic Melon, Funny Berry, Sensitive | G14: http://es.pampers.com/flushable-wipes-kandoo | H14: http://es.pampers.com/es_US/images/pc/hb/lsp/products/prod_image_wipes_kandoo.png | I14: 037000041757, 037000048770, 037000159186 | M14: 18
A15: 16n8p5scqgr7lpve64m2tvx8c | B15: Pampers | C15: 261044286 | D15: Inactive | E15: Jabón de manos espumoso, jabón para el cuerpo y champú | G15: http://es.pampers.com/hand-soap-for-kids-kandoo | H15: http://es.pampers.com/es_US/images/pc/hb/lsp/products/prod_img_more_kandoo_soap_NA.jpg | I15: 037000002116, 037000002123, 037000002130, 037000002178, 037000008002, 037000065883 | M15: 18
A16: 16n8p5scqgr7lpve64m2tvx8c | B16: Pampers | C16: 261044151 | D16: Inactive | E16: Calzoncitos de entrenamiento Pampers® Easy Ups para niñas | F16: Menos derrames que los otros calzoncitos de aprendizaje líderes Hasta 12 horas de protección, incluso de noche Diseños de Dora the Explorer para las niñas Centro especialmente ubicado para absorber la orina de las nenas Indicador gráfico de humedad Gane puntos Pampers Rewards® con cada compra de Pampers. | G16: http://es.pampers.com/potty-training-girls-easy-ups | H16: http://es.pampers.com/es_US/images/pc/hb/lsp/products/prod_image_pants_easyupsgirls.png | I16: 037000265832, 037000265856, 037000265870 | M16: 32
A17: 16n8p5scqgr7lpve64m2tvx8c | B17: Pampers | C17: 10930815 | D17: Inactive | E17: Toallitas húmedas Pampers® SoftCare, sin fragancia | F17: Las toallitas húmedas Softcare sin fragancia tienen agua pura Loción con aloe natural y Vitamina E Las toallitas húmedas SoftCare tienen miles de celidtas limpiadoras suaves Limpian suavemente como un pañito de bebé con agua Hipoalergénicas | G17: http://es.pampers.com/softcare-unscented-wipes | H17: https://www.pampers.com/es_US/images/pc/hb/products/prod_img_wipes_softcare_unscented_NA.jpg | I17: 037000061618 | M17: 1
A18: 16n8p5scqgr7lpve64m2tvx8c | B18: Pampers | C18: 10930826 | D18: Inactive | E18: Toallitas húmedas Pampers® Sensitive ThickCare | F18: Las toallitas húmedas Pampers Sensitive ThickCare tienen loción PureCare para acondicionar la piel de tu bebé Las toallitas húmedas Sensitive ThickCare han sido probadas por dermatólogos y son hipoalergénicas Suavidad que ha sido probada clínicamente y libres de perfumes Más gruesas* para limpiar el sucio de la piel (*vs. Pampers SoftCare™) Tienen agua pura | G18: http://es.pampers.com/pampers-sensitive-thickcare-wipes | H18: https://www.pampers.com/es_US/images/pc/hb/products/prod_img_wipes_pampers_thickcare_sensitive_NA.jpg | I18: 037000229476 | M18: 1
A19: 16n8p5scqgr7lpve64m2tvx8c | B19: Pampers | C19: 261044145 | D19: Inactive | E19: Calzoncitos de entrenamiento Pampers® Easy Ups para niños | F19: Menos derrames que los otros calzoncitos de aprendizaje líderes Hasta 12 horas de protección, incluso de noche Diseños de Thomas the Tank Engine) Centro especialmente ubicado para absorber la orina de los varones Indicador gráfico de humedad Gane puntos Pampers Rewards® con cada compra de Pampers. | G19: http://es.pampers.com/potty-training-boys-easy-ups | H19: http://es.pampers.com/es_US/images/pc/hb/lsp/products/prod_image_pants_easyupsboys.png | I19: 037000265849, 037000265863, 037000265900 | M19: 39
A20: 16n8p5scqgr7lpve64m2tvx8c | B20: Pampers | C20: 10930807 | D20: Inactive | E20: Toallitas húmedas Pampers® Sensitive | F20: Las toallitas húmedas Pampers Sensitive han sido probadas por dermatólogos Hipoalergénicas y libres de perfumes La toallita húmeda #1 de los hospitales (basado en los datos de venta) Toallitas húmedas cuya suavidad ha sido probada clínicamente para la piel de tu bebé Las toallitas húmedas Pampers Sensitive tienen loción PureCare, la cual acondiciona la piel de tu bebé | G20: http://es.pampers.com/pampers-sensitive-wipes | H20: https://www.pampers.com/es_US/images/pc/hb/products/prod_img_wipes_sensitive_NA.jpg | I20: 037000436904 | M20: 2
A21: 16n8p5scqgr7lpve64m2tvx8c | B21: Pampers | C21: 10930828 | D21: Inactive | E21: Pañales Pampers® Cruisers | F21: El ajuste “3-Way Fit” brinda a los bebés nuestro mejor ajuste que les da la libertad de jugar a su manera Los pañales Pampers Cruisers brindan hasta 12 horas de protección contra los derrames Ahora con la suavidad acolchada de Swaddlers Los diseños nuevos de Sesame Street tienen tus personajes favoritos en cada pañal | G21: http://es.pampers.com/pampers-cruisers | H21: https://www.pampers.com/es_US/images/pc/hb/products/prod_img_pampers_cruisers_NA.jpg | I21: 037000262640, 037000278481, 037000278740, 037000279402, 037000279525 | M21: 12
A22: 16n8p5scqgr7lpve64m2tvx8c | B22: Pampers | C22: 10930802 | D22: Inactive | E22: Pañales Pampers® Swaddlers Sensitive | F22: Suaves e hipoalergénicos Tienen un toque de aloe Ultra transpirabilidad Indicador de humedad que cambia de color (tamaños NB, 1, 2) Apertura para el cordón umbilical (tamaño NB solamente) | G22: http://es.pampers.com/swaddlers-sensitive-diapers | H22: https://www.pampers.com/es_US/images/pc/hb/products/prod_img_diapers_swaddlers_sensitive_NA.jpg | I22: 037000280521, 037000280668, 037000280811, 037000281023, 037000281153 | M22: 2
A23: 16n8p5scqgr7lpve64m2tvx8c | B23: Pampers | C23: 930826 | D23: Inactive | E23: Toallitas húmedas Pampers® Sensitive ThickCare | F23: Las toallitas húmedas Pampers Sensitive ThickCare tienen loción PureCare para acondicionar la piel de tu bebé Las toallitas húmedas Sensitive ThickCare han sido probadas por dermatólogos y son hipoalergénicas Suavidad que ha sido probada clínicamente y libres de perfumes Más gruesas* para limpiar el sucio de la piel (*vs. Pampers SoftCare™) Tienen agua pura | G23: http://es.pampers.com/pampers-sensitive-thickcare-wipes | H23: https://www.pampers.com/es_US/images/pc/hb/products/prod_img_wipes_pampers_thickcare_sensitive_NA.jpg | I23: 037000229476 | M23: 1
A24: PAMPERS | B24: Pampers | C24: 261044229 | D24: Inactive | E24: Pampers® Cruisers™ | F24: Pampers® Cruisers™ | G24: https://www.pampers-es.com/es-us/panales-toallitas/panales-pampers-cruisers-old | H24: https://images.ctfassets.net/6x11wdx755bh/4a6ca0517b9a31f223d03d9b95e201929a2add7f23b1db746ae784d06a6485fb/d901b4d0f029db02319e9a3bfed1e1ed/D_CRUISERS_560x390_RETINA.png | I24: 037000644552, 037000752523 | M24: 291
A25: PAMPERS | B25: Pampers | C25: 261044163 | D25: Inactive | E25: Ropa interior nocturna absorbente Pampers UnderJams para niños | F25: Ropa interior nocturna absorbente Pampers UnderJams para niños | G25: https://www.pampers-es.com/es-us/producto-estrella/ropa-interior-nocturna-absorbente-pampers-underjams-para-ninos | H25: https://res.cloudinary.com/pmprs/image/upload/c_scale,f_auto,q_60/v20160720231725/pampersc3/es-us/-/media/pampers/pampers-us/images/products/underjams_boys_open.png?v=2-201607202317 | I25: 037000173915, 037000173977, 037000174004, 037000315346, 037000820147, 037000929574, 037000929598, 037000929611, 037000929635 | M25: 17
A26: PAMPERS | B26: Pampers | C26: 261044165 | D26: Inactive | E26: Ropa interior nocturna absorbente Pampers UnderJams para niñas | F26: Ropa interior nocturna absorbente Pampers UnderJams para niñas | G26: https://www.pampers-es.com/es-us/producto-estrella/ropa-interior-nocturna-absorbente-pampers-underjams-para-ninas | H26: https://res.cloudinary.com/pmprs/image/upload/c_scale,f_auto,q_60/v20160720231725/pampersc3/es-us/-/media/pampers/pampers-us/images/products/underjams_girls_open.png?v=2-201607202317 | I26: 037000174011, 037000929567, 037000929581, 037000929604, 037000929628 | M26: 13
A27: PAMPERS | B27: Pampers | C27: 261044282 | D27: Inactive | E27: Pampers Baby Dry Extra Protection | F27: Pampers Baby Dry Extra Protection | G27: https://www.pampers-es.com/es-us/producto-estrella/pampers-baby-dry-extra-protection | H27: https://cdn.multibrand3.pgsitecore.com/es-US/-/media/Pampers/Pampers-US/Images/Products/Extra_Protection_Open.png?v=2-201607202317 | I27: 037000864820, 037000864837, 037000864844, 037000864851, 037000864868, 037000864875, 037000864905 | M27: 28
A28: PAMPERS | B28: Pampers | C28: 261044225 | D28: Inactive | E28: Pampers® Swaddlers Sensitive™ | F28: Pampers® Swaddlers Sensitive™ | G28: https://www.pampers-es.com/es-us/panales-toallitas/panales-pampers-swaddlers-sensitive | H28: https://images.ctfassets.net/6x11wdx755bh/3d711eee47c5531a5898265eee5761f0070eb06c23982832d7124e65652f0f98/88c3c1f43df25c0ad0abca03414ac912/D_SENSITIVE_SWADDLERS_560x390_RETINA.png | M28: 103
A29: PAMPERS | B29: Pampers | C29: 261057383 | D29: Inactive | E29: Toallitas Pampers Natural Clean | F29: Toallitas Pampers Natural Clean | G29: https://www.pampers-es.com/es-us/producto-estrella/toallitas-pampers-natural-clean | H29: https://res.cloudinary.com/pmprs/image/upload/c_scale,f_auto,q_60/v20160720231714/pampersc3/es-us/-/media/pampers/pampers-us/images/products/natural-clean_630x330.png?v=2-201607202317 | I29: 037000282525, 037000282532, 037000282655, 037000282723, 037000827887, 037000836742, 037000836766, 037000870968, 037000870982, 037000894001 | M29: 55
A30: PAMPERS | B30: Pampers | C30: EASYUPS_BOYS_GIRLS | D30: Inactive | E30: Pampers® Easy Ups™ | F30: Pampers® Easy Ups™ | G30: https://www.pampers-es.com/es-us/panales-toallitas/calzoncitos-de-entrenamiento-pampers-easy-ups-para-ninos-y-ninas-old | H30: https://images.ctfassets.net/6x11wdx755bh/2bFXPn0OubO8CHKsdLd6HE/787c065558da819b488e734965f997e9/easyups_280x195.png | I30: 037000691969, 037000764687 | M30: 43
A31: PAMPERS | B31: Pampers | C31: 261044284 | D31: Inactive | E31: Pampers® Splashers™ | F31: Pampers® Splashers™ | G31: https://www.pampers-es.com/es-us/panales-toallitas/trajes-de-bano-pampers-splashers-para-ninos-y-ninas-old | H31: https://images.ctfassets.net/6x11wdx755bh/97adac275ffd9bdda7d800768d66e0d9569a8f313c29f6c0dd3165bc9d8f64b6/669f89f3199aa517cdf7554c1a651be7/D_SPLASHERS_560x390_RETINA.png | I31: 037000764571, 037000765950 | M31: 31
A32: PAMPERS | B32: Pampers | C32: Pampers_Premium_Care | D32: Inactive | E32: Pampers Premium Care | F32: Pampers Premium Care | G32: https://www.pampers-es.com/es-us/producto-estrella/pampers-premium-care | H32: https://res.cloudinary.com/pmprs/image/upload/c_scale,f_auto,q_60/v20160720231731/pampersc3/es-us/-/media/pampers/pampers-us/images/products/wmt_premium_open.png?v=2-201607202317 | I32: 037000949022 | M32: 4
A33: PAMPERS | B33: Pampers | C33: 261057382 | D33: Inactive | E33: Pampers® Complete Clean™ Baby Fresh Scent | F33: Pampers® Complete Clean™ Baby Fresh Scent | G33: https://www.pampers-es.com/es-us/panales-toallitas/toallitas-pampers-complete-clean-baby-fresh-old | H33: https://images.ctfassets.net/6x11wdx755bh/080ebab346c33b9fffc69e7be8aecb10d13399d3ad4b61031c90b876853a119b/5f0c004268494fd6348456d6873061d6/D_COMPLETE_CLEAN_BABY_FRESH_560x390_RETINA.png | I33: 037000755364 | M33: 92
A34: PAMPERS | B34: Pampers | C34: 261057381 | D34: Inactive | E34: Pampers® Sensitive™ | F34: Pampers® Sensitive™ | G34: https://www.pampers-es.com/es-us/panales-toallitas/toallitas-pampers-sensitive-old | H34: https://images.ctfassets.net/6x11wdx755bh/5c09eaf9bc4e9475c8bf89fc880e4ddb2a1d51ffcada27f29e319304a65743af/6c76163229b68c3f1523195193f6a351/D_SENSITIVE_WIPES_560x390_RETINA.png | I34: 037000845706, 037000967552 | M34: 255
A35: PAMPERS | B35: Pampers | C35: 261044261 | D35: Inactive | E35: Pampers® Baby-Dry™ | F35: Pampers® Baby-Dry™ | G35: https://www.pampers-es.com/es-us/panales-toallitas/panales-pampers-baby-dry-old | H35: https://images.ctfassets.net/6x11wdx755bh/60f365ca095d6539277121dbca957c6afad565502d2f263eb4789936edb1abd0/a25a792ef6cfc502a47a50a150d78f5d/D_BABYDRY_560x390_RETINA.png | I35: 037000862208 | M35: 264
A36: PAMPERS | B36: Pampers | C36: 261044222 | D36: Inactive | E36: Pampers® Swaddlers™ | F36: Pampers® Swaddlers™ | G36: https://www.pampers-es.com/es-us/panales-toallitas/panales-pampers-swaddlers-old | H36: https://images.ctfassets.net/6x11wdx755bh/2BbiOsoJZ4otuiu1GaVISr/a1038f4147d708f8aa26a26336d3f341/swaddlers_280x195.png | I36: 037000303749 | M36: 549
C37: Pampers_BabyDry | D37: Inactive | M37: 1
C38: Pampers_ Pure_Protection_Diapers | D38: Inactive | M38: 1
